Workbook

Sheet README
A1: ShopKart – Module 2 solution workbook
A2: Every number in this file comes from a formula. Change a raw value and the summaries update.
A4: Sheet order (follow the videos):
A5: orders_raw – the messy export (5,055 rows). Column M flags duplicate rows (Video 2.2).
A6: orders_clean – after Data > Remove duplicates (5,000 rows). Columns M–W are helper cleaning formulas (Videos 2.2–2.4).
A7: city_map – old city spelling to standard name, used by city_clean.
A8: products, customers – lookup tables (unchanged).
A9: Summary – SUMIFS / COUNTIFS / AVERAGEIFS by city, category and month (Video 2.4).
A10: Pivot_check – formula version of the city x category pivot table built in Video 2.5.
A11: Report – one-page answer to 3 business questions with charts (Video 2.6).
A13: Colour key: dark header = data column; light orange header = helper formula column; green cells = key answers.
A14: Works in Google Sheets and Excel 365. XLOOKUP needs Excel 2021/365 or Google Sheets.

Sheet Report
A1: ShopKart 2025 – one-page report
A2: Source: orders_clean (5,000 orders after cleaning). All numbers are live formulas.
A4: Total revenue | C4: Orders | E4: Avg order value | G4: Return rate
A5: =Summary!B3 -> 14704650 | C5: =Summary!B4 -> 5000 | E5: =Summary!B5 -> 2940.9299 | G5: =Summary!B7 -> 0.1374
A7: Q1. Which city brings the most revenue?
A8: ="Answer: "&INDEX(Summary!$A$11:$A$20,MATCH(MAX(Summary!$B$11:$B$20),Summary!$B$11:$B$20,0))&" with ₹"&TEXT(MAX(Summary!$B$11:$B$20),"#,##0")&" ("&TEXT(MAX(Summary!$B$11:$B$20)/Summary!B3,"0.0%")&" of all revenue)." -> Answer: Delhi with ₹2,323,405 (15.8% of all revenue).
A10: Q2. Which month is our peak, and how big is it?
A11: ="Answer: "&INDEX(Summary!$B$33:$B$44,MATCH(MAX(Summary!$C$33:$C$44),Summary!$C$33:$C$44,0))&" with ₹"&TEXT(MAX(Summary!$C$33:$C$44),"#,##0")&", "&TEXT(MAX(Summary!$C$33:$C$44)/MIN(Summary!$C$33:$C$44),"0.0")&"x the weakest month ("&INDEX(Summary!$B$33:$B$44,MATCH(MIN(Summary!$C$33:$C$44),Summary!$C$33:$C$44,0))&")." -> Answer: Oct with ₹1,978,317, 2.5x the weakest month (May).
A13: Q3. Is any city returning far more orders than the rest?
A14: ="Answer: "&INDEX(Summary!$A$11:$A$20,MATCH(MAX(Summary!$F$11:$F$20),Summary!$F$11:$F$20,0))&" returns "&TEXT(MAX(Summary!$F$11:$F$20),"0.0%")&" of orders vs "&TEXT(Summary!B7,"0.0%")&" overall ("&TEXT(MAX(Summary!$F$11:$F$20)/Summary!B7,"0.0")&"x). Investigate delivery and products there." -> Answer: Pune returns 32.4% of orders vs 13.7% overall (2.4x). Investigate delivery and products there.

Sheet orders_raw
A1: order_id | B1: order_date | C1: customer_id | D1: product_id | E1: quantity | F1: unit_price | G1: discount | H1: city | I1: payment_mode | J1: delivery_days | K1: rating | L1: returned | M1: dup_flag | O1: Rows | P1: =COUNTA(A2:A5056) -> 5055
A2: O10001 | B2: 2025-01-01 | C2: C0593 | D2: P048 | E2: 6 | F2: 362 | G2: 0.2 | H2: Delhi | I2: COD | J2: 4 | K2: 2 | L2: N | M2: =IF(COUNTIF($A$2:A2,A2)>1,"DUPLICATE","") | O2: Duplicates | P2: =COUNTIF(M2:M5056,"DUPLICATE") -> 55
A3: O10002 | B3: 2025-01-01 | C3: C0367 | D3: P049 | E3: 2 | F3: 300 | G3: 0.05 | H3: Chennai | I3: Debit Card | J3: 4 | K3: 5 | L3: N | M3: =IF(COUNTIF($A$2:A3,A3)>1,"DUPLICATE","") | O3: Rows after removing | P3: =P1-P2 -> 5000
A4: O10003 | B4: 2025-01-01 | C4: C0707 | D4: P020 | E4: 1 | F4: 2258 | G4: 0.05 | H4: DELHI | I4: Debit Card | J4: 2 | K4: 3 | L4: N | M4: =IF(COUNTIF($A$2:A4,A4)>1,"DUPLICATE","")
A5: O10004 | B5: 2025-01-01 | C5: C0118 | D5: P026 | E5: 2 | F5: 2020 | G5: 0.15 | H5: Lucknow | I5: COD | J5: 4 | K5: 4 | L5: Y | M5: =IF(COUNTIF($A$2:A5,A5)>1,"DUPLICATE","")
A6: O10005 | B6: 2025-01-01 | C6: C0238 | D6: P026 | E6: 2 | F6: 1937 | G6: 0.1 | H6: Chennai | I6: UPI | J6: 2 | K6: 4 | L6: N | M6: =IF(COUNTIF($A$2:A6,A6)>1,"DUPLICATE","")
A7: O10006 | B7: 2025-01-01 | C7: C0561 | D7: P014 | E7: 2 | F7: 1440 | G7: 0.05 | H7: Delhi | I7: UPI | J7: 5 | K7: 4 | L7: N | M7: =IF(COUNTIF($A$2:A7,A7)>1,"DUPLICATE","")
A8: O10007 | B8: 2025-01-01 | C8: C0460 | D8: P009 | E8: 2 | F8: 15303 | G8: 0.2 | H8: Kolkata | I8: UPI | J8: 3 | K8: 5 | L8: N | M8: =IF(COUNTIF($A$2:A8,A8)>1,"DUPLICATE","")
A9: O10008 | B9: 2025-01-01 | C9: C0311 | D9: P009 | E9: 1 | F9: 14841 | G9: 0.05 | H9: Pune | I9: Credit Card | J9: 4 | K9: 4 | L9: N | M9: =IF(COUNTIF($A$2:A9,A9)>1,"DUPLICATE","")
A10: O10009 | B10: 2025-01-01 | C10: C0566 | D10: P010 | E10: 2 | F10: 18548 | G10: 0.05 | H10: Chennai | I10: Debit Card | J10: 3 | K10: 5 | L10: N | M10: =IF(COUNTIF($A$2:A10,A10)>1,"DUPLICATE","")
A11: O10010 | B11: 2025-01-01 | C11: C0454 | D11: P040 | E11: 2 | F11: 348 | G11: 0 | H11: Chennai | I11: Credit Card | J11: 3 | K11: 3 | L11: N | M11: =IF(COUNTIF($A$2:A11,A11)>1,"DUPLICATE","")
A12: O10011 | B12: 2025-01-01 | C12: C0086 | D12: P054 | E12: 2 | F12: 1494 | G12: 0 | H12: Hyderabad | I12: Debit Card | J12: 2 | K12: 4 | L12: N | M12: =IF(COUNTIF($A$2:A12,A12)>1,"DUPLICATE","")
A13: O10012 | B13: 2025-01-01 | C13: C0097 | D13: P051 | E13: 1 | F13: 248 | G13: 0.2 | H13: Delhi | I13: Credit Card | J13: 3 | K13: 4 | L13: N | M13: =IF(COUNTIF($A$2:A13,A13)>1,"DUPLICATE","")
A14: O10013 | B14: 2025-01-02 | C14: C0403 | D14: P015 | E14: 1 | F14: 3128 | G14: 0.15 | H14: Ahmedabad | I14: Credit Card | J14: 3 | K14: 4 | L14: Y | M14: =IF(COUNTIF($A$2:A14,A14)>1,"DUPLICATE","")
A15: O10014 | B15: 2025-01-02 | C15: C0663 | D15: P003 | E15: 1 | F15: 3910 | G15: 0.2 | H15: Ahmedabad | I15: UPI | J15: 5 | K15: 5 | L15: N | M15: =IF(COUNTIF($A$2:A15,A15)>1,"DUPLICATE","")
... A29: O10028 | B29: 2025-01-03 | C29: C0464 | D29: P057 | E29: 1 | F29: 335 | G29: 0.05 | H29: Bengaluru | I29: UPI | J29: 3 | K29: 4 | L29: N | M29: =IF(COUNTIF($A$2:A29,A29)>1,"DUPLICATE","")
A30: O10029 | B30: 2025-01-03 | C30: C0116 | D30: P035 | E30: 2 | F30: ₹626 | H30: Chennai | I30: Debit Card | J30: 4 | K30: 3 | L30: N | M30: =IF(COUNTIF($A$2:A30,A30)>1,"DUPLICATE","")
A31: O10030 | B31: 2025-01-03 | C31: C0016 | D31: P056 | E31: 1 | F31: 463 | G31: 0 | H31: Mumbai | I31: UPI | J31: 3 | K31: 5 | L31: N | M31: =IF(COUNTIF($A$2:A31,A31)>1,"DUPLICATE","")
A32: O10031 | B32: 2025-01-03 | C32: C0411 | D32: P023 | E32: 1 | F32: 1622 | G32: 0 | H32: Hyderabad | I32: UPI | J32: 4 | K32: 3 | L32: Y | M32: =IF(COUNTIF($A$2:A32,A32)>1,"DUPLICATE","")
A33: O10032 | B33: 2025-01-03 | C33: C0697 | D33: P021 | E33: 2 | F33: 685 | G33: 0.1 | H33: Bengaluru | I33: UPI | J33: 4 | K33: 3 | L33: N | M33: =IF(COUNTIF($A$2:A33,A33)>1,"DUPLICATE","")
A34: O10033 | B34: 2025-01-03 | C34: C0423 | D34: P023 | E34: 3 | F34: 1669 | G34: 0.05 | H34: Mumbai | I34: Debit Card | J34: 5 | K34: 5 | L34: N | M34: =IF(COUNTIF($A$2:A34,A34)>1,"DUPLICATE","")
A35: O10034 | B35: 03-01-2025 | C35: C0240 | D35: P047 | E35: 4 | F35: 1077 | G35: 0.1 | H35: Mumbai | J35: 3 | K35: 5 | L35: N | M35: =IF(COUNTIF($A$2:A35,A35)>1,"DUPLICATE","")
A36: O10035 | B36: 2025-01-03 | C36: C0797 | D36: P016 | E36: 2 | F36: 1859 | G36: 0 | H36: hyderabad | I36: Net Banking | J36: 4 | K36: 5 | L36: N | M36: =IF(COUNTIF($A$2:A36,A36)>1,"DUPLICATE","")
A37: O10036 | B37: 2025-01-04 | C37: C0631 | D37: P005 | E37: 1 | F37: 900 | G37: 0.15 | H37: Delhi | I37: UPI | J37: 4 | K37: 4 | L37: N | M37: =IF(COUNTIF($A$2:A37,A37)>1,"DUPLICATE","")
A38: O10037 | B38: 2025-01-04 | C38: C0100 | D38: P045 | E38: 2 | F38: 310 | G38: 0.1 | H38: Hyderabad | I38: UPI | J38: 3 | L38: N | M38: =IF(COUNTIF($A$2:A38,A38)>1,"DUPLICATE","")
A39: O10038 | B39: 2025-01-04 | C39: C0392 | D39: P033 | E39: 2 | F39: 3247 | G39: 0 | H39: Mumbai | I39: Credit Card | J39: 5 | K39: 5 | L39: N | M39: =IF(COUNTIF($A$2:A39,A39)>1,"DUPLICATE","")
A40: O10039 | B40: 2025-01-04 | C40: C0457 | D40: P019 | E40: 1 | F40: 1176 | G40: 0.15 | H40: Mumbai | I40: Net Banking | J40: 3 | K40: 5 | L40: No | M40: =IF(COUNTIF($A$2:A40,A40)>1,"DUPLICATE","")
A41: O10040 | B41: 2025-01-04 | C41: C0160 | D41: P020 | E41: 4 | F41: 2408 | G41: 0.2 | H41: Bengaluru | I41: Debit Card | J41: 6 | K41: 4 | L41: N | M41: =IF(COUNTIF($A$2:A41,A41)>1,"DUPLICATE","")
A42: O10041 | B42: 2025-01-04 | C42: C0178 | D42: P002 | E42: 1 | F42: ₹2,551 | G42: 0 | H42: Chennai | I42: UPI | J42: 3 | K42: 4 | L42: N | M42: =IF(COUNTIF($A$2:A42,A42)>1,"DUPLICATE","")
A43: O10042 | B43: 2025-01-05 | C43: C0191 | D43: P025 | E43: 1 | F43: 1312 | G43: 0 | H43: Delhi | I43: COD | J43: 5 | K43: 3 | L43: N | M43: =IF(COUNTIF($A$2:A43,A43)>1,"DUPLICATE","")
A44: O10043 | B44: 2025-01-05 | C44: C0300 | D44: P003 | E44: 2 | F44: 4070 | G44: 0.05 | H44: Chennai | I44: Debit Card | J44: 2 | K44: 5 | L44: N | M44: =IF(COUNTIF($A$2:A44,A44)>1,"DUPLICATE","")
A45: O10044 | B45: 2025-01-05 | C45: C0422 | D45: P016 | E45: 2 | F45: 1871 | G45: 0.2 | H45: Hyderabad | I45: UPI | J45: 4 | K45: 4 | L45: N | M45: =IF(COUNTIF($A$2:A45,A45)>1,"DUPLICATE","")
A46: O10045 | B46: 2025-01-05 | C46: C0553 | D46: P008 | E46: 1 | F46: 384 | G46: 0.2 | H46: Bengaluru | I46: UPI | J46: 5 | K46: 4 | L46: N | M46: =IF(COUNTIF($A$2:A46,A46)>1,"DUPLICATE","")
A47: O10046 | B47: 2025-01-05 | C47: C0122 | D47: P060 | E47: 1 | F47: 414 | G47: 0.1 | H47: Delhi | I47: Debit Card | J47: 6 | K47: 3 | L47: N | M47: =IF(COUNTIF($A$2:A47,A47)>1,"DUPLICATE","")
A48: O10047 | B48: 2025-01-05 | C48: C0147 | D48: P008 | E48: 1 | F48: 409 | G48: 0 | H48: Lucknow | I48: UPI | J48: 8 | K48: 2 | L48: Yes | M48: =IF(COUNTIF($A$2:A48,A48)>1,"DUPLICATE","")
A49: O10048 | B49: 2025-01-05 | C49: C0418 | D49: P008 | E49: 1 | F49: 400 | G49: 0 | H49: Bengaluru | I49: UPI | J49: 2 | L49: N | M49: =IF(COUNTIF($A$2:A49,A49)>1,"DUPLICATE","")
A50: O10049 | B50: 2025-01-05 | C50: C0075 | D50: P023 | E50: 1 | F50: 1649 | G50: 0.05 | H50: Delhi | I50: Credit Card | J50: 6 | K50: 3 | L50: Y | M50: =IF(COUNTIF($A$2:A50,A50)>1,"DUPLICATE","")
A51: O10050 | B51: 2025-01-05 | C51: C0349 | D51: P018 | E51: 2 | F51: 2447 | G51: 0 | H51: Lucknow | J51: 6 | K51: 3 | L51: Y | M51: =IF(COUNTIF($A$2:A51,A51)>1,"DUPLICATE","")
A52: O10051 | B52: 2025-01-05 | C52: C0416 | D52: P026 | E52: 1 | F52: 2044 | G52: 0 | H52: Kolkata | I52: Credit Card | J52: 2 | K52: 5 | L52: N | M52: =IF(COUNTIF($A$2:A52,A52)>1,"DUPLICATE","")
A53: O10052 | B53: 2025-01-05 | C53: C0244 | D53: P006 | E53: 1 | F53: 1518 | G53: 0.05 | H53: Jaipur | I53: COD | J53: 5 | K53: 4 | L53: N | M53: =IF(COUNTIF($A$2:A53,A53)>1,"DUPLICATE","")
A54: O10053 | B54: 2025-01-05 | C54: C0767 | D54: P017 | E54: 1 | F54: 1259 | G54: 0.15 | H54: Delhi | I54: COD | J54: 5 | K54: 3 | L54: Y | M54: =IF(COUNTIF($A$2:A54,A54)>1,"DUPLICATE","")
A55: O10054 | B55: 2025-01-05 | C55: C0531 | D55: P025 | E55: 1 | F55: 1340 | G55: 0 | H55: Chennai | I55: Credit Card | J55: 2 | K55: 4 | L55: N | M55: =IF(COUNTIF($A$2:A55,A55)>1,"DUPLICATE","")
A56: O10055 | B56: 2025-01-05 | C56: C0357 | D56: P038 | E56: 2 | F56: 875 | G56: 0 | H56: Bengaluru | I56: Debit Card | J56: 4 | K56: 3 | L56: N | M56: =IF(COUNTIF($A$2:A56,A56)>1,"DUPLICATE","")
A57: O10056 | B57: 2025-01-05 | C57: C0449 | D57: P004 | E57: 1 | F57: 1350 | H57: Pune | I57: COD | J57: 5 | K57: 3 | L57: Y | M57: =IF(COUNTIF($A$2:A57,A57)>1,"DUPLICATE","")
A58: O10057 | B58: 2025-01-05 | C58: C0027 | D58: P024 | E58: 3 | F58: 1956 | G58: 0 | H58: Delhi | I58: Debit Card | J58: 2 | K58: 5 | L58: N | M58: =IF(COUNTIF($A$2:A58,A58)>1,"DUPLICATE","")
A59: O10058 | B59: 2025-01-05 | C59: C0759 | D59: P039 | E59: 2 | F59: 401 | G59: 0.05 | H59: Ahmedabad | I59: UPI | J59: 6 | K59: 3 | L59: Y | M59: =IF(COUNTIF($A$2:A59,A59)>1,"DUPLICATE","")
A60: O10059 | B60: 2025-01-06 | C60: C0404 | D60: P046 | E60: 2 | F60: 469 | G60: 0.15 | H60: Kolkata | I60: Credit Card | J60: 6 | K60: 4 | L60: N | M60: =IF(COUNTIF($A$2:A60,A60)>1,"DUPLICATE","")
A61: O10060 | B61: 2025-01-06 | C61: C0634 | D61: P001 | E61: 1 | F61: 1954 | G61: 0.05 | H61: mumbai | I61: UPI | J61: 3 | K61: 4 | L61: N | M61: =IF(COUNTIF($A$2:A61,A61)>1,"DUPLICATE","")
A62: O10061 | B62: 2025-01-06 | C62: C0736 | D62: P030 | E62: 2 | F62: 385 | G62: 0.1 | H62: pune | I62: UPI | J62: 4 | K62: 4 | L62: N | M62: =IF(COUNTIF($A$2:A62,A62)>1,"DUPLICATE","")
A63: O10062 | B63: 2025-01-06 | C63: C0465 | D63: P024 | E63: 1 | F63: 1975 | G63: 0 | H63: Pune | I63: COD | J63: 7 | K63: 3 | L63: N | M63: =IF(COUNTIF($A$2:A63,A63)>1,"DUPLICATE","")
A64: O10063 | B64: 2025-01-06 | C64: C0571 | D64: P053 | E64: 3 | F64: 620 | G64: 0.2 | H64: Calcutta | I64: Credit Card | J64: 4 | K64: 4 | L64: N | M64: =IF(COUNTIF($A$2:A64,A64)>1,"DUPLICATE","")
A65: O10064 | B65: 2025-01-06 | C65: C0023 | D65: P008 | E65: 2 | F65: 395 | G65: 0.2 | H65: kolkata | I65: UPI | J65: 5 | K65: 4 | L65: N | M65: =IF(COUNTIF($A$2:A65,A65)>1,"DUPLICATE","")
A66: O10065 | B66: 2025-01-06 | C66: C0565 | D66: P030 | E66: 1 | F66: 416 | G66: 0.1 | H66: Kolkata | I66: Debit Card | J66: 4 | K66: 3 | L66: N | M66: =IF(COUNTIF($A$2:A66,A66)>1,"DUPLICATE","")
A67: O10066 | B67: 2025-01-06 | C67: C0040 | D67: P024 | E67: 1 | F67: 1880 | G67: 0 | H67: Pune | I67: COD | J67: 5 | K67: 3 | L67: Y | M67: =IF(COUNTIF($A$2:A67,A67)>1,"DUPLICATE","")
A68: O10067 | B68: 2025-01-06 | C68: C0612 | D68: P029 | E68: 1 | F68: 676 | G68: 0 | H68: Chennai | I68: Debit Card | J68: 5 | K68: 5 | L68: N | M68: =IF(COUNTIF($A$2:A68,A68)>1,"DUPLICATE","")
A69: O10068 | B69: 06-01-2025 | C69: C0017 | D69: P022 | E69: 1 | F69: ₹981 | H69: Ahmedabad | I69: Credit Card | J69: 2 | K69: 4 | L69: N | M69: =IF(COUNTIF($A$2:A69,A69)>1,"DUPLICATE","")
A70: O10069 | B70: 2025-01-07 | C70: C0080 | D70: P037 | E70: 2 | F70: 512 | G70: 0.05 | H70: Chennai | I70: Net Banking | J70: 4 | K70: 5 | L70: N | M70: =IF(COUNTIF($A$2:A70,A70)>1,"DUPLICATE","")
A71: O10070 | B71: 2025-01-07 | C71: C0070 | D71: P031 | E71: 2 | F71: 798 | G71: 0 | H71: Chennai | I71: UPI | J71: 4 | K71: 5 | L71: N | M71: =IF(COUNTIF($A$2:A71,A71)>1,"DUPLICATE","")
A72: O10071 | B72: 2025-01-07 | C72: C0409 | D72: P024 | E72: 2 | F72: 1880 | G72: 0.3 | H72: Ahmedabad | J72: 4 | L72: N | M72: =IF(COUNTIF($A$2:A72,A72)>1,"DUPLICATE","")
A73: O10072 | B73: 2025-01-07 | C73: C0795 | D73: P005 | E73: 1 | F73: 891 | H73: Bengaluru | I73: UPI | J73: 4 | K73: 5 | L73: N | M73: =IF(COUNTIF($A$2:A73,A73)>1,"DUPLICATE","")
A74: O10073 | B74: 2025-01-07 | C74: C0728 | D74: P025 | E74: 2 | F74: 1329 | G74: 0 | H74: Mumbai | I74: UPI | J74: 3 | K74: 4 | L74: N | M74: =IF(COUNTIF($A$2:A74,A74)>1,"DUPLICATE","")
A75: O10074 | B75: 2025-01-07 | C75: C0173 | D75: P014 | E75: 1 | F75: 1481 | G75: 0 | H75: Chennai | I75: upi | J75: 4 | K75: 4 | L75: N | M75: =IF(COUNTIF($A$2:A75,A75)>1,"DUPLICATE","")
A76: O10075 | B76: 2025-01-07 | C76: C0461 | D76: P017 | E76: 2 | F76: 1321 | G76: 0 | H76: Bengaluru | I76: Debit Card | J76: 4 | K76: 4 | L76: N | M76: =IF(COUNTIF($A$2:A76,A76)>1,"DUPLICATE","")
A77: O10076 | B77: 2025-01-07 | C77: C0695 | D77: P042 | E77: 1 | F77: 988 | G77: 0.15 | H77: Pune | I77: COD | J77: 7 | K77: 4 | L77: N | M77: =IF(COUNTIF($A$2:A77,A77)>1,"DUPLICATE","")
A78: O10077 | B78: 2025-01-07 | C78: C0503 | D78: P025 | E78: 3 | F78: 1253 | G78: 0.1 | H78: Bengaluru | I78: UPI | J78: 5 | K78: 3 | L78: N | M78: =IF(COUNTIF($A$2:A78,A78)>1,"DUPLICATE","")
A79: O10078 | B79: 2025-01-07 | C79: C0400 | D79: P033 | E79: 3 | F79: 3358 | G79: 0.2 | H79: Jaipur | I79: UPI | J79: 5 | K79: 4 | L79: No | M79: =IF(COUNTIF($A$2:A79,A79)>1,"DUPLICATE","")
A80: O10079 | B80: 2025-01-07 | C80: C0502 | D80: P015 | E80: 1 | F80: 2860 | G80: 0 | H80: bengaluru | I80: Credit Card | J80: 4 | K80: 3 | L80: N | M80: =IF(COUNTIF($A$2:A80,A80)>1,"DUPLICATE","")
A81: O10080 | B81: 2025-01-08 | C81: C0325 | D81: P060 | E81: 4 | F81: 413 | G81: 0.1 | H81: Hyderabad | I81: UPI | J81: 4 | K81: 3 | L81: N | M81: =IF(COUNTIF($A$2:A81,A81)>1,"DUPLICATE","")
A82: O10081 | B82: 2025-01-08 | C82: C0627 | D82: P008 | E82: 1 | F82: 394 | G82: 0 | H82: Delhi | I82: UPI | J82: 4 | K82: 3 | L82: N | M82: =IF(COUNTIF($A$2:A82,A82)>1,"DUPLICATE","")
A83: O10082 | B83: 2025-01-08 | C83: C0587 | D83: P018 | E83: 2 | F83: 2597 | G83: 0.15 | H83: Delhi | I83: COD | J83: 3 | K83: 3 | L83: Y | M83: =IF(COUNTIF($A$2:A83,A83)>1,"DUPLICATE","")
A84: O10083 | B84: 2025-01-08 | C84: C0527 | D84: P011 | E84: 1 | F84: 1232 | G84: 0 | H84: Pune | I84: Credit Card | J84: 7 | L84: Y | M84: =IF(COUNTIF($A$2:A84,A84)>1,"DUPLICATE","")
A85: O10084 | B85: 2025-01-08 | C85: C0570 | D85: P040 | E85: 1 | F85: 355 | G85: 0.05 | H85: Chennai | I85: UPI | J85: 6 | K85: 4 | L85: N | M85: =IF(COUNTIF($A$2:A85,A85)>1,"DUPLICATE","")
A86: O10085 | B86: 2025-01-08 | C86: C0724 | D86: P005 | E86: 1 | F86: 916 | G86: 0.05 | H86: Chennai | I86: Debit Card | J86: 3 | K86: 5 | L86: N | M86: =IF(COUNTIF($A$2:A86,A86)>1,"DUPLICATE","")
A87: O10086 | B87: 2025-01-08 | C87: C0738 | D87: P020 | E87: 2 | F87: 2360 | G87: 0 | H87: Pune | I87: UPI | J87: 7 | K87: 3 | L87: N | M87: =IF(COUNTIF($A$2:A87,A87)>1,"DUPLICATE","")
A88: O10087 | B88: 2025-01-08 | C88: C0238 | D88: P021 | E88: 3 | F88: 676 | G88: 0.15 | H88: Chennai | I88: UPI | J88: 3 | K88: 5 | L88: N | M88: =IF(COUNTIF($A$2:A88,A88)>1,"DUPLICATE","")
A89: O10088 | B89: 2025-01-08 | C89: C0207 | D89: P036 | E89: 2 | F89: 2592 | G89: 0.2 | H89: Delhi | I89: COD | J89: 4 | K89: 3 | L89: N | M89: =IF(COUNTIF($A$2:A89,A89)>1,"DUPLICATE","")
A90: O10089 | B90: 2025-01-09 | C90: C0227 | D90: P015 | E90: 1 | F90: 2943 | G90: 0 | H90: hyderabad | I90: COD | J90: 3 | K90: 4 | L90: N | M90: =IF(COUNTIF($A$2:A90,A90)>1,"DUPLICATE","")
A91: O10090 | B91: 2025-01-09 | C91: C0312 | D91: P033 | E91: 1 | F91: 3442 | G91: 0 | H91: Mumbai | I91: UPI | J91: 5 | K91: 4 | L91: N | M91: =IF(COUNTIF($A$2:A91,A91)>1,"DUPLICATE","")
A92: O10091 | B92: 2025-01-09 | C92: C0574 | D92: P058 | E92: 3 | F92: 192 | G92: 0 | H92: Mumbai | I92: COD | J92: 3 | K92: 5 | L92: N | M92: =IF(COUNTIF($A$2:A92,A92)>1,"DUPLICATE","")
A93: O10092 | B93: 2025-01-09 | C93: C0521 | D93: P037 | E93: 2 | F93: 501 | G93: 0 | H93: Mumbai | I93: Debit Card | J93: 2 | K93: 4 | L93: N | M93: =IF(COUNTIF($A$2:A93,A93)>1,"DUPLICATE","")
A94: O10093 | B94: 2025-01-09 | C94: C0056 | D94: P056 | E94: 3 | F94: 430 | G94: 0.2 | H94: Bengaluru | I94: Net Banking | J94: 4 | K94: 2 | L94: Y | M94: =IF(COUNTIF($A$2:A94,A94)>1,"DUPLICATE","")
A95: O10094 | B95: 2025-01-09 | C95: C0486 | D95: P039 | E95: 2 | F95: 405 | G95: 0.1 | H95: Chennai | I95: Net Banking | J95: 4 | K95: 4 | L95: N | M95: =IF(COUNTIF($A$2:A95,A95)>1,"DUPLICATE","")
A96: O10095 | B96: 2025-01-09 | C96: C0512 | D96: P060 | E96: 2 | F96: 410 | G96: 0 | H96: Lucknow | I96: UPI | J96: 8 | K96: 4 | L96: N | M96: =IF(COUNTIF($A$2:A96,A96)>1,"DUPLICATE","")
... A103: O10102 | B103: 2025-01-10 | C103: C0384 | D103: P015 | E103: 1 | F103: 2930 | G103: 0.3 | H103: Lucknow | I103: COD | J103: 6 | K103: 4 | L103: N | M103: =IF(COUNTIF($A$2:A103,A103)>1,"DUPLICATE","")
A104: O10103 | B104: 2025-01-10 | C104: C0104 | D104: P042 | E104: 1 | F104: 961 | G104: 0.1 | H104: Delhi | J104: 5 | K104: 4 | L104: N | M104: =IF(COUNTIF($A$2:A104,A104)>1,"DUPLICATE","")
A105: O10104 | B105: 2025-01-10 | C105: C0397 | D105: P033 | E105: 1 | F105: 3444 | G105: 0 | H105: Hyderabad | I105: UPI | J105: 7 | K105: 4 | L105: N | M105: =IF(COUNTIF($A$2:A105,A105)>1,"DUPLICATE","")
A106: O10105 | B106: 2025-01-10 | C106: C0138 | D106: P012 | E106: 1 | F106: 2111 | G106: 0 | H106: Delhi | I106: Credit Card | J106: 4 | K106: 5 | L106: N | M106: =IF(COUNTIF($A$2:A106,A106)>1,"DUPLICATE","")
A107: O10106 | B107: 2025-01-10 | C107: C0117 | D107: P028 | E107: 2 | F107: 1076 | G107: 0.3 | H107: Kolkata | I107: UPI | J107: 4 | K107: 5 | L107: N | M107: =IF(COUNTIF($A$2:A107,A107)>1,"DUPLICATE","")
A108: O10107 | B108: 2025-01-10 | C108: C0327 | D108: P020 | E108: 1 | F108: 2345 | G108: 0.05 | H108: Mumbai | I108: Credit Card | J108: 3 | K108: 4 | L108: N | M108: =IF(COUNTIF($A$2:A108,A108)>1,"DUPLICATE","")
A109: O10108 | B109: 2025-01-10 | C109: C0268 | D109: P038 | E109: 1 | F109: 879 | G109: 0 | H109: Bengaluru | I109: Credit Card | J109: 2 | K109: 4 | L109: N | M109: =IF(COUNTIF($A$2:A109,A109)>1,"DUPLICATE","")
A110: O10109 | B110: 2025-01-10 | C110: C0475 | D110: P020 | E110: 1 | F110: 2263 | G110: 0 | H110: Mumbai | I110: UPI | J110: 3 | K110: 4 | L110: Y | M110: =IF(COUNTIF($A$2:A110,A110)>1,"DUPLICATE","")
A111: O10110 | B111: 2025-01-10 | C111: C0160 | D111: P018 | E111: 4 | F111: ₹2,563 | G111: 0.15 | H111: Bengaluru | I111: UPI | J111: 6 | K111: 3 | L111: Y | M111: =IF(COUNTIF($A$2:A111,A111)>1,"DUPLICATE","")
A112: O10111 | B112: 10-01-2025 | C112: C0010 | D112: P012 | E112: 1 | F112: 2235 | G112: 0.2 | H112: Mumbai | I112: COD | J112: 4 | K112: 4 | L112: N | M112: =IF(COUNTIF($A$2:A112,A112)>1,"DUPLICATE","")
A113: O10112 | B113: 2025-01-10 | C113: C0143 | D113: P054 | E113: 2 | F113: ₹1,540 | G113: 0.05 | H113: DELHI | I113: Net Banking | J113: 2 | K113: 3 | L113: N | M113: =IF(COUNTIF($A$2:A113,A113)>1,"DUPLICATE","")
A114: O10113 | B114: 2025-01-11 | C114: C0032 | D114: P057 | E114: 1 | F114: 351 | G114: 0 | H114: Hyderabad | I114: Credit Card | J114: 2 | K114: 4 | L114: N | M114: =IF(COUNTIF($A$2:A114,A114)>1,"DUPLICATE","")
A115: O10114 | B115: 2025-01-11 | C115: C0640 | D115: P036 | E115: 3 | F115: 2451 | G115: 0.05 | H115: Ahmedabad | I115: UPI | J115: 3 | K115: 5 | L115: N | M115: =IF(COUNTIF($A$2:A115,A115)>1,"DUPLICATE","")
A116: O10115 | B116: 2025-01-11 | C116: C0270 | D116: P017 | E116: 1 | F116: 1340 | G116: 0.15 | H116: Bengaluru | I116: COD | J116: 3 | K116: 5 | L116: Y | M116: =IF(COUNTIF($A$2:A116,A116)>1,"DUPLICATE","")
A117: O10116 | B117: 2025-01-11 | C117: C0351 | D117: P014 | E117: 1 | F117: 1492 | G117: 0.05 | H117: Pune | I117: Credit Card | J117: 4 | K117: 5 | L117: N | M117: =IF(COUNTIF($A$2:A117,A117)>1,"DUPLICATE","")
A118: O10117 | B118: 2025-01-12 | C118: C0528 | D118: P006 | E118: 2 | F118: 1454 | G118: 0.2 | H118: Jaipur | I118: Debit Card | J118: 4 | K118: 3 | L118: N | M118: =IF(COUNTIF($A$2:A118,A118)>1,"DUPLICATE","")
A119: O10118 | B119: 2025-01-12 | C119: C0462 | D119: P008 | E119: 1 | F119: 416 | G119: 0.15 | H119: Mumbai | I119: UPI | J119: 3 | K119: 4 | L119: N | M119: =IF(COUNTIF($A$2:A119,A119)>1,"DUPLICATE","")
...

Sheet orders_clean
A1: order_id | B1: order_date | C1: customer_id | D1: product_id | E1: quantity | F1: unit_price | G1: discount | H1: city | I1: payment_mode | J1: delivery_days | K1: rating | L1: returned | M1: order_date_clean | N1: order_month | O1: city_trim | P1: city_clean | Q1: unit_price_num | R1: quantity_clean | S1: discount_num | T1: payment_clean | U1: returned_clean | V1: revenue | W1: category
A2: O10001 | B2: 2025-01-01 | C2: C0593 | D2: P048 | E2: 6 | F2: 362 | G2: 0.2 | H2: Delhi | I2: COD | J2: 4 | K2: 2 | L2: N | M2: =IF(ISNUMBER(B2),B2,IF(MID(B2,3,1)="-",DATE(VALUE(RIGHT(B2,4)),VALUE(MID(B2,4,2)),VALUE(LEFT(B2,2))),DATE(VALUE(LEFT(B2,4)),VALUE(MID(B2,6,2)),VALUE(RIGHT(B2,2))))) -> 45658 | N2: =MONTH(M2) -> 1 | O2: =PROPER(TRIM(H2)) -> Delhi | P2: =IFERROR(VLOOKUP(O2,city_map!$A$2:$B$6,2,FALSE()),O2) -> Delhi | Q2: =IF(ISNUMBER(F2),F2,VALUE(SUBSTITUTE(SUBSTITUTE(F2,"₹",""),",",""))) -> 362 | R2: =IF(E2=99,1,E2) -> 6 | S2: =IF(G2="",0,G2) -> 0.2 | T2: =IF(I2="","Unknown",IF(I2="upi","UPI",I2)) -> COD | U2: =IF(L2="Yes","Y",IF(L2="No","N",L2)) -> N | V2: =ROUND(R2*Q2*(1-S2),2) -> 1737.6 | W2: =_xlfn.XLOOKUP(D2,products!$A$2:$A$61,products!$C$2:$C$61,"Not found") -> Books
A3: O10002 | B3: 2025-01-01 | C3: C0367 | D3: P049 | E3: 2 | F3: 300 | G3: 0.05 | H3: Chennai | I3: Debit Card | J3: 4 | K3: 5 | L3: N | M3: =IF(ISNUMBER(B3),B3,IF(MID(B3,3,1)="-",DATE(VALUE(RIGHT(B3,4)),VALUE(MID(B3,4,2)),VALUE(LEFT(B3,2))),DATE(VALUE(LEFT(B3,4)),VALUE(MID(B3,6,2)),VALUE(RIGHT(B3,2))))) -> 45658 | N3: =MONTH(M3) -> 1 | O3: =PROPER(TRIM(H3)) -> Chennai | P3: =IFERROR(VLOOKUP(O3,city_map!$A$2:$B$6,2,FALSE()),O3) -> Chennai | Q3: =IF(ISNUMBER(F3),F3,VALUE(SUBSTITUTE(SUBSTITUTE(F3,"₹",""),",",""))) -> 300 | R3: =IF(E3=99,1,E3) -> 2 | S3: =IF(G3="",0,G3) -> 0.05 | T3: =IF(I3="","Unknown",IF(I3="upi","UPI",I3)) -> Debit Card | U3: =IF(L3="Yes","Y",IF(L3="No","N",L3)) -> N | V3: =ROUND(R3*Q3*(1-S3),2) -> 570 | W3: =_xlfn.XLOOKUP(D3,products!$A$2:$A$61,products!$C$2:$C$61,"Not found") -> Beauty
A4: O10003 | B4: 2025-01-01 | C4: C0707 | D4: P020 | E4: 1 | F4: 2258 | G4: 0.05 | H4: DELHI | I4: Debit Card | J4: 2 | K4: 3 | L4: N | M4: =IF(ISNUMBER(B4),B4,IF(MID(B4,3,1)="-",DATE(VALUE(RIGHT(B4,4)),VALUE(MID(B4,4,2)),VALUE(LEFT(B4,2))),DATE(VALUE(LEFT(B4,4)),VALUE(MID(B4,6,2)),VALUE(RIGHT(B4,2))))) -> 45658 | N4: =MONTH(M4) -> 1 | O4: =PROPER(TRIM(H4)) -> Delhi | P4: =IFERROR(VLOOKUP(O4,city_map!$A$2:$B$6,2,FALSE()),O4) -> Delhi | Q4: =IF(ISNUMBER(F4),F4,VALUE(SUBSTITUTE(SUBSTITUTE(F4,"₹",""),",",""))) -> 2258 | R4: =IF(E4=99,1,E4) -> 1 | S4: =IF(G4="",0,G4) -> 0.05 | T4: =IF(I4="","Unknown",IF(I4="upi","UPI",I4)) -> Debit Card | U4: =IF(L4="Yes","Y",IF(L4="No","N",L4)) -> N | V4: =ROUND(R4*Q4*(1-S4),2) -> 2145.1 | W4: =_xlfn.XLOOKUP(D4,products!$A$2:$A$61,products!$C$2:$C$61,"Not found") -> Fashion
A5: O10004 | B5: 2025-01-01 | C5: C0118 | D5: P026 | E5: 2 | F5: 2020 | G5: 0.15 | H5: Lucknow | I5: COD | J5: 4 | K5: 4 | L5: Y | M5: =IF(ISNUMBER(B5),B5,IF(MID(B5,3,1)="-",DATE(VALUE(RIGHT(B5,4)),VALUE(MID(B5,4,2)),VALUE(LEFT(B5,2))),DATE(VALUE(LEFT(B5,4)),VALUE(MID(B5,6,2)),VALUE(RIGHT(B5,2))))) -> 45658 | N5: =MONTH(M5) -> 1 | O5: =PROPER(TRIM(H5)) -> Lucknow | P5: =IFERROR(VLOOKUP(O5,city_map!$A$2:$B$6,2,FALSE()),O5) -> Lucknow | Q5: =IF(ISNUMBER(F5),F5,VALUE(SUBSTITUTE(SUBSTITUTE(F5,"₹",""),",",""))) -> 2020 | R5: =IF(E5=99,1,E5) -> 2 | S5: =IF(G5="",0,G5) -> 0.15 | T5: =IF(I5="","Unknown",IF(I5="upi","UPI",I5)) -> COD | U5: =IF(L5="Yes","Y",IF(L5="No","N",L5)) -> Y | V5: =ROUND(R5*Q5*(1-S5),2) -> 3434 | W5: =_xlfn.XLOOKUP(D5,products!$A$2:$A$61,products!$C$2:$C$61,"Not found") -> Home
A6: O10005 | B6: 2025-01-01 | C6: C0238 | D6: P026 | E6: 2 | F6: 1937 | G6: 0.1 | H6: Chennai | I6: UPI | J6: 2 | K6: 4 | L6: N | M6: =IF(ISNUMBER(B6),B6,IF(MID(B6,3,1)="-",DATE(VALUE(RIGHT(B6,4)),VALUE(MID(B6,4,2)),VALUE(LEFT(B6,2))),DATE(VALUE(LEFT(B6,4)),VALUE(MID(B6,6,2)),VALUE(RIGHT(B6,2))))) -> 45658 | N6: =MONTH(M6) -> 1 | O6: =PROPER(TRIM(H6)) -> Chennai | P6: =IFERROR(VLOOKUP(O6,city_map!$A$2:$B$6,2,FALSE()),O6) -> Chennai | Q6: =IF(ISNUMBER(F6),F6,VALUE(SUBSTITUTE(SUBSTITUTE(F6,"₹",""),",",""))) -> 1937 | R6: =IF(E6=99,1,E6) -> 2 | S6: =IF(G6="",0,G6) -> 0.1 | T6: =IF(I6="","Unknown",IF(I6="upi","UPI",I6)) -> UPI | U6: =IF(L6="Yes","Y",IF(L6="No","N",L6)) -> N | V6: =ROUND(R6*Q6*(1-S6),2) -> 3486.6 | W6: =_xlfn.XLOOKUP(D6,products!$A$2:$A$61,products!$C$2:$C$61,"Not found") -> Home
A7: O10006 | B7: 2025-01-01 | C7: C0561 | D7: P014 | E7: 2 | F7: 1440 | G7: 0.05 | H7: Delhi | I7: UPI | J7: 5 | K7: 4 | L7: N | M7: =IF(ISNUMBER(B7),B7,IF(MID(B7,3,1)="-",DATE(VALUE(RIGHT(B7,4)),VALUE(MID(B7,4,2)),VALUE(LEFT(B7,2))),DATE(VALUE(LEFT(B7,4)),VALUE(MID(B7,6,2)),VALUE(RIGHT(B7,2))))) -> 45658 | N7: =MONTH(M7) -> 1 | O7: =PROPER(TRIM(H7)) -> Delhi | P7: =IFERROR(VLOOKUP(O7,city_map!$A$2:$B$6,2,FALSE()),O7) -> Delhi | Q7: =IF(ISNUMBER(F7),F7,VALUE(SUBSTITUTE(SUBSTITUTE(F7,"₹",""),",",""))) -> 1440 | R7: =IF(E7=99,1,E7) -> 2 | S7: =IF(G7="",0,G7) -> 0.05 | T7: =IF(I7="","Unknown",IF(I7="upi","UPI",I7)) -> UPI | U7: =IF(L7="Yes","Y",IF(L7="No","N",L7)) -> N | V7: =ROUND(R7*Q7*(1-S7),2) -> 2736 | W7: =_xlfn.XLOOKUP(D7,products!$A$2:$A$61,products!$C$2:$C$61,"Not found") -> Fashion
A8: O10007 | B8: 2025-01-01 | C8: C0460 | D8: P009 | E8: 2 | F8: 15303 | G8: 0.2 | H8: Kolkata | I8: UPI | J8: 3 | K8: 5 | L8: N | M8: =IF(ISNUMBER(B8),B8,IF(MID(B8,3,1)="-",DATE(VALUE(RIGHT(B8,4)),VALUE(MID(B8,4,2)),VALUE(LEFT(B8,2))),DATE(VALUE(LEFT(B8,4)),VALUE(MID(B8,6,2)),VALUE(RIGHT(B8,2))))) -> 45658 | N8: =MONTH(M8) -> 1 | O8: =PROPER(TRIM(H8)) -> Kolkata | P8: =IFERROR(VLOOKUP(O8,city_map!$A$2:$B$6,2,FALSE()),O8) -> Kolkata | Q8: =IF(ISNUMBER(F8),F8,VALUE(SUBSTITUTE(SUBSTITUTE(F8,"₹",""),",",""))) -> 15303 | R8: =IF(E8=99,1,E8) -> 2 | S8: =IF(G8="",0,G8) -> 0.2 | T8: =IF(I8="","Unknown",IF(I8="upi","UPI",I8)) -> UPI | U8: =IF(L8="Yes","Y",IF(L8="No","N",L8)) -> N | V8: =ROUND(R8*Q8*(1-S8),2) -> 24484.8 | W8: =_xlfn.XLOOKUP(D8,products!$A$2:$A$61,products!$C$2:$C$61,"Not found") -> Electronics
A9: O10008 | B9: 2025-01-01 | C9: C0311 | D9: P009 | E9: 1 | F9: 14841 | G9: 0.05 | H9: Pune | I9: Credit Card | J9: 4 | K9: 4 | L9: N | M9: =IF(ISNUMBER(B9),B9,IF(MID(B9,3,1)="-",DATE(VALUE(RIGHT(B9,4)),VALUE(MID(B9,4,2)),VALUE(LEFT(B9,2))),DATE(VALUE(LEFT(B9,4)),VALUE(MID(B9,6,2)),VALUE(RIGHT(B9,2))))) -> 45658 | N9: =MONTH(M9) -> 1 | O9: =PROPER(TRIM(H9)) -> Pune | P9: =IFERROR(VLOOKUP(O9,city_map!$A$2:$B$6,2,FALSE()),O9) -> Pune | Q9: =IF(ISNUMBER(F9),F9,VALUE(SUBSTITUTE(SUBSTITUTE(F9,"₹",""),",",""))) -> 14841 | R9: =IF(E9=99,1,E9) -> 1 | S9: =IF(G9="",0,G9) -> 0.05 | T9: =IF(I9="","Unknown",IF(I9="upi","UPI",I9)) -> Credit Card | U9: =IF(L9="Yes","Y",IF(L9="No","N",L9)) -> N | V9: =ROUND(R9*Q9*(1-S9),2) -> 14098.95 | W9: =_xlfn.XLOOKUP(D9,products!$A$2:$A$61,products!$C$2:$C$61,"Not found") -> Electronics
A10: O10009 | B10: 2025-01-01 | C10: C0566 | D10: P010 | E10: 2 | F10: 18548 | G10: 0.05 | H10: Chennai | I10: Debit Card | J10: 3 | K10: 5 | L10: N | M10: =IF(ISNUMBER(B10),B10,IF(MID(B10,3,1)="-",DATE(VALUE(RIGHT(B10,4)),VALUE(MID(B10,4,2)),VALUE(LEFT(B10,2))),DATE(VALUE(LEFT(B10,4)),VALUE(MID(B10,6,2)),VALUE(RIGHT(B10,2))))) -> 45658 | N10: =MONTH(M10) -> 1 | O10: =PROPER(TRIM(H10)) -> Chennai | P10: =IFERROR(VLOOKUP(O10,city_map!$A$2:$B$6,2,FALSE()),O10) -> Chennai | Q10: =IF(ISNUMBER(F10),F10,VALUE(SUBSTITUTE(SUBSTITUTE(F10,"₹",""),",",""))) -> 18548 | R10: =IF(E10=99,1,E10) -> 2 | S10: =IF(G10="",0,G10) -> 0.05 | T10: =IF(I10="","Unknown",IF(I10="upi","UPI",I10)) -> Debit Card | U10: =IF(L10="Yes","Y",IF(L10="No","N",L10)) -> N | V10: =ROUND(R10*Q10*(1-S10),2) -> 35241.2 | W10: =_xlfn.XLOOKUP(D10,products!$A$2:$A$61,products!$C$2:$C$61,"Not found") -> Electronics
A11: O10010 | B11: 2025-01-01 | C11: C0454 | D11: P040 | E11: 2 | F11: 348 | G11: 0 | H11: Chennai | I11: Credit Card | J11: 3 | K11: 3 | L11: N | M11: =IF(ISNUMBER(B11),B11,IF(MID(B11,3,1)="-",DATE(VALUE(RIGHT(B11,4)),VALUE(MID(B11,4,2)),VALUE(LEFT(B11,2))),DATE(VALUE(LEFT(B11,4)),VALUE(MID(B11,6,2)),VALUE(RIGHT(B11,2))))) -> 45658 | N11: =MONTH(M11) -> 1 | O11: =PROPER(TRIM(H11)) -> Chennai | P11: =IFERROR(VLOOKUP(O11,city_map!$A$2:$B$6,2,FALSE()),O11) -> Chennai | Q11: =IF(ISNUMBER(F11),F11,VALUE(SUBSTITUTE(SUBSTITUTE(F11,"₹",""),",",""))) -> 348 | R11: =IF(E11=99,1,E11) -> 2 | S11: =IF(G11="",0,G11) -> 0 | T11: =IF(I11="","Unknown",IF(I11="upi","UPI",I11)) -> Credit Card | U11: =IF(L11="Yes","Y",IF(L11="No","N",L11)) -> N | V11: =ROUND(R11*Q11*(1-S11),2) -> 696 | W11: =_xlfn.XLOOKUP(D11,products!$A$2:$A$61,products!$C$2:$C$61,"Not found") -> Books
A12: O10011 | B12: 2025-01-01 | C12: C0086 | D12: P054 | E12: 2 | F12: 1494 | G12: 0 | H12: Hyderabad | I12: Debit Card | J12: 2 | K12: 4 | L12: N | M12: =IF(ISNUMBER(B12),B12,IF(MID(B12,3,1)="-",DATE(VALUE(RIGHT(B12,4)),VALUE(MID(B12,4,2)),VALUE(LEFT(B12,2))),DATE(VALUE(LEFT(B12,4)),VALUE(MID(B12,6,2)),VALUE(RIGHT(B12,2))))) -> 45658 | N12: =MONTH(M12) -> 1 | O12: =PROPER(TRIM(H12)) -> Hyderabad | P12: =IFERROR(VLOOKUP(O12,city_map!$A$2:$B$6,2,FALSE()),O12) -> Hyderabad | Q12: =IF(ISNUMBER(F12),F12,VALUE(SUBSTITUTE(SUBSTITUTE(F12,"₹",""),",",""))) -> 1494 | R12: =IF(E12=99,1,E12) -> 2 | S12: =IF(G12="",0,G12) -> 0 | T12: =IF(I12="","Unknown",IF(I12="upi","UPI",I12)) -> Debit Card | U12: =IF(L12="Yes","Y",IF(L12="No","N",L12)) -> N | V12: =ROUND(R12*Q12*(1-S12),2) -> 2988 | W12: =_xlfn.XLOOKUP(D12,products!$A$2:$A$61,products!$C$2:$C$61,"Not found") -> Beauty
A13: O10012 | B13: 2025-01-01 | C13: C0097 | D13: P051 | E13: 1 | F13: 248 | G13: 0.2 | H13: Delhi | I13: Credit Card | J13: 3 | K13: 4 | L13: N | M13: =IF(ISNUMBER(B13),B13,IF(MID(B13,3,1)="-",DATE(VALUE(RIGHT(B13,4)),VALUE(MID(B13,4,2)),VALUE(LEFT(B13,2))),DATE(VALUE(LEFT(B13,4)),VALUE(MID(B13,6,2)),VALUE(RIGHT(B13,2))))) -> 45658 | N13: =MONTH(M13) -> 1 | O13: =PROPER(TRIM(H13)) -> Delhi | P13: =IFERROR(VLOOKUP(O13,city_map!$A$2:$B$6,2,FALSE()),O13) -> Delhi | Q13: =IF(ISNUMBER(F13),F13,VALUE(SUBSTITUTE(SUBSTITUTE(F13,"₹",""),",",""))) -> 248 | R13: =IF(E13=99,1,E13) -> 1 | S13: =IF(G13="",0,G13) -> 0.2 | T13: =IF(I13="","Unknown",IF(I13="upi","UPI",I13)) -> Credit Card | U13: =IF(L13="Yes","Y",IF(L13="No","N",L13)) -> N | V13: =ROUND(R13*Q13*(1-S13),2) -> 198.4 | W13: =_xlfn.XLOOKUP(D13,products!$A$2:$A$61,products!$C$2:$C$61,"Not found") -> Beauty
... A29: O10028 | B29: 2025-01-03 | C29: C0464 | D29: P057 | E29: 1 | F29: 335 | G29: 0.05 | H29: Bengaluru | I29: UPI | J29: 3 | K29: 4 | L29: N | M29: =IF(ISNUMBER(B29),B29,IF(MID(B29,3,1)="-",DATE(VALUE(RIGHT(B29,4)),VALUE(MID(B29,4,2)),VALUE(LEFT(B29,2))),DATE(VALUE(LEFT(B29,4)),VALUE(MID(B29,6,2)),VALUE(RIGHT(B29,2))))) -> 45660 | N29: =MONTH(M29) -> 1 | O29: =PROPER(TRIM(H29)) -> Bengaluru | P29: =IFERROR(VLOOKUP(O29,city_map!$A$2:$B$6,2,FALSE()),O29) -> Bengaluru | Q29: =IF(ISNUMBER(F29),F29,VALUE(SUBSTITUTE(SUBSTITUTE(F29,"₹",""),",",""))) -> 335 | R29: =IF(E29=99,1,E29) -> 1 | S29: =IF(G29="",0,G29) -> 0.05 | T29: =IF(I29="","Unknown",IF(I29="upi","UPI",I29)) -> UPI | U29: =IF(L29="Yes","Y",IF(L29="No","N",L29)) -> N | V29: =ROUND(R29*Q29*(1-S29),2) -> 318.25 | W29: =_xlfn.XLOOKUP(D29,products!$A$2:$A$61,products!$C$2:$C$61,"Not found") -> Beauty
A30: O10029 | B30: 2025-01-03 | C30: C0116 | D30: P035 | E30: 2 | F30: ₹626 | H30: Chennai | I30: Debit Card | J30: 4 | K30: 3 | L30: N | M30: =IF(ISNUMBER(B30),B30,IF(MID(B30,3,1)="-",DATE(VALUE(RIGHT(B30,4)),VALUE(MID(B30,4,2)),VALUE(LEFT(B30,2))),DATE(VALUE(LEFT(B30,4)),VALUE(MID(B30,6,2)),VALUE(RIGHT(B30,2))))) -> 45660 | N30: =MONTH(M30) -> 1 | O30: =PROPER(TRIM(H30)) -> Chennai | P30: =IFERROR(VLOOKUP(O30,city_map!$A$2:$B$6,2,FALSE()),O30) -> Chennai | Q30: =IF(ISNUMBER(F30),F30,VALUE(SUBSTITUTE(SUBSTITUTE(F30,"₹",""),",",""))) -> 626 | R30: =IF(E30=99,1,E30) -> 2 | S30: =IF(G30="",0,G30) -> 0 | T30: =IF(I30="","Unknown",IF(I30="upi","UPI",I30)) -> Debit Card | U30: =IF(L30="Yes","Y",IF(L30="No","N",L30)) -> N | V30: =ROUND(R30*Q30*(1-S30),2) -> 1252 | W30: =_xlfn.XLOOKUP(D30,products!$A$2:$A$61,products!$C$2:$C$61,"Not found") -> Home
A31: O10030 | B31: 2025-01-03 | C31: C0016 | D31: P056 | E31: 1 | F31: 463 | G31: 0 | H31: Mumbai | I31: UPI | J31: 3 | K31: 5 | L31: N | M31: =IF(ISNUMBER(B31),B31,IF(MID(B31,3,1)="-",DATE(VALUE(RIGHT(B31,4)),VALUE(MID(B31,4,2)),VALUE(LEFT(B31,2))),DATE(VALUE(LEFT(B31,4)),VALUE(MID(B31,6,2)),VALUE(RIGHT(B31,2))))) -> 45660 | N31: =MONTH(M31) -> 1 | O31: =PROPER(TRIM(H31)) -> Mumbai | P31: =IFERROR(VLOOKUP(O31,city_map!$A$2:$B$6,2,FALSE()),O31) -> Mumbai | Q31: =IF(ISNUMBER(F31),F31,VALUE(SUBSTITUTE(SUBSTITUTE(F31,"₹",""),",",""))) -> 463 | R31: =IF(E31=99,1,E31) -> 1 | S31: =IF(G31="",0,G31) -> 0 | T31: =IF(I31="","Unknown",IF(I31="upi","UPI",I31)) -> UPI | U31: =IF(L31="Yes","Y",IF(L31="No","N",L31)) -> N | V31: =ROUND(R31*Q31*(1-S31),2) -> 463 | W31: =_xlfn.XLOOKUP(D31,products!$A$2:$A$61,products!$C$2:$C$61,"Not found") -> Beauty
A32: O10031 | B32: 2025-01-03 | C32: C0411 | D32: P023 | E32: 1 | F32: 1622 | G32: 0 | H32: Hyderabad | I32: UPI | J32: 4 | K32: 3 | L32: Y | M32: =IF(ISNUMBER(B32),B32,IF(MID(B32,3,1)="-",DATE(VALUE(RIGHT(B32,4)),VALUE(MID(B32,4,2)),VALUE(LEFT(B32,2))),DATE(VALUE(LEFT(B32,4)),VALUE(MID(B32,6,2)),VALUE(RIGHT(B32,2))))) -> 45660 | N32: =MONTH(M32) -> 1 | O32: =PROPER(TRIM(H32)) -> Hyderabad | P32: =IFERROR(VLOOKUP(O32,city_map!$A$2:$B$6,2,FALSE()),O32) -> Hyderabad | Q32: =IF(ISNUMBER(F32),F32,VALUE(SUBSTITUTE(SUBSTITUTE(F32,"₹",""),",",""))) -> 1622 | R32: =IF(E32=99,1,E32) -> 1 | S32: =IF(G32="",0,G32) -> 0 | T32: =IF(I32="","Unknown",IF(I32="upi","UPI",I32)) -> UPI | U32: =IF(L32="Yes","Y",IF(L32="No","N",L32)) -> Y | V32: =ROUND(R32*Q32*(1-S32),2) -> 1622 | W32: =_xlfn.XLOOKUP(D32,products!$A$2:$A$61,products!$C$2:$C$61,"Not found") -> Fashion
A33: O10032 | B33: 2025-01-03 | C33: C0697 | D33: P021 | E33: 2 | F33: 685 | G33: 0.1 | H33: Bengaluru | I33: UPI | J33: 4 | K33: 3 | L33: N | M33: =IF(ISNUMBER(B33),B33,IF(MID(B33,3,1)="-",DATE(VALUE(RIGHT(B33,4)),VALUE(MID(B33,4,2)),VALUE(LEFT(B33,2))),DATE(VALUE(LEFT(B33,4)),VALUE(MID(B33,6,2)),VALUE(RIGHT(B33,2))))) -> 45660 | N33: =MONTH(M33) -> 1 | O33: =PROPER(TRIM(H33)) -> Bengaluru | P33: =IFERROR(VLOOKUP(O33,city_map!$A$2:$B$6,2,FALSE()),O33) -> Bengaluru | Q33: =IF(ISNUMBER(F33),F33,VALUE(SUBSTITUTE(SUBSTITUTE(F33,"₹",""),",",""))) -> 685 | R33: =IF(E33=99,1,E33) -> 2 | S33: =IF(G33="",0,G33) -> 0.1 | T33: =IF(I33="","Unknown",IF(I33="upi","UPI",I33)) -> UPI | U33: =IF(L33="Yes","Y",IF(L33="No","N",L33)) -> N | V33: =ROUND(R33*Q33*(1-S33),2) -> 1233 | W33: =_xlfn.XLOOKUP(D33,products!$A$2:$A$61,products!$C$2:$C$61,"Not found") -> Fashion
A34: O10033 | B34: 2025-01-03 | C34: C0423 | D34: P023 | E34: 3 | F34: 1669 | G34: 0.05 | H34: Mumbai | I34: Debit Card | J34: 5 | K34: 5 | L34: N | M34: =IF(ISNUMBER(B34),B34,IF(MID(B34,3,1)="-",DATE(VALUE(RIGHT(B34,4)),VALUE(MID(B34,4,2)),VALUE(LEFT(B34,2))),DATE(VALUE(LEFT(B34,4)),VALUE(MID(B34,6,2)),VALUE(RIGHT(B34,2))))) -> 45660 | N34: =MONTH(M34) -> 1 | O34: =PROPER(TRIM(H34)) -> Mumbai | P34: =IFERROR(VLOOKUP(O34,city_map!$A$2:$B$6,2,FALSE()),O34) -> Mumbai | Q34: =IF(ISNUMBER(F34),F34,VALUE(SUBSTITUTE(SUBSTITUTE(F34,"₹",""),",",""))) -> 1669 | R34: =IF(E34=99,1,E34) -> 3 | S34: =IF(G34="",0,G34) -> 0.05 | T34: =IF(I34="","Unknown",IF(I34="upi","UPI",I34)) -> Debit Card | U34: =IF(L34="Yes","Y",IF(L34="No","N",L34)) -> N | V34: =ROUND(R34*Q34*(1-S34),2) -> 4756.65 | W34: =_xlfn.XLOOKUP(D34,products!$A$2:$A$61,products!$C$2:$C$61,"Not found") -> Fashion
A35: O10034 | B35: 03-01-2025 | C35: C0240 | D35: P047 | E35: 4 | F35: 1077 | G35: 0.1 | H35: Mumbai | J35: 3 | K35: 5 | L35: N | M35: =IF(ISNUMBER(B35),B35,IF(MID(B35,3,1)="-",DATE(VALUE(RIGHT(B35,4)),VALUE(MID(B35,4,2)),VALUE(LEFT(B35,2))),DATE(VALUE(LEFT(B35,4)),VALUE(MID(B35,6,2)),VALUE(RIGHT(B35,2))))) -> 45660 | N35: =MONTH(M35) -> 1 | O35: =PROPER(TRIM(H35)) -> Mumbai | P35: =IFERROR(VLOOKUP(O35,city_map!$A$2:$B$6,2,FALSE()),O35) -> Mumbai | Q35: =IF(ISNUMBER(F35),F35,VALUE(SUBSTITUTE(SUBSTITUTE(F35,"₹",""),",",""))) -> 1077 | R35: =IF(E35=99,1,E35) -> 4 | S35: =IF(G35="",0,G35) -> 0.1 | T35: =IF(I35="","Unknown",IF(I35="upi","UPI",I35)) -> Unknown | U35: =IF(L35="Yes","Y",IF(L35="No","N",L35)) -> N | V35: =ROUND(R35*Q35*(1-S35),2) -> 3877.2 | W35: =_xlfn.XLOOKUP(D35,products!$A$2:$A$61,products!$C$2:$C$61,"Not found") -> Books
A36: O10035 | B36: 2025-01-03 | C36: C0797 | D36: P016 | E36: 2 | F36: 1859 | G36: 0 | H36: hyderabad | I36: Net Banking | J36: 4 | K36: 5 | L36: N | M36: =IF(ISNUMBER(B36),B36,IF(MID(B36,3,1)="-",DATE(VALUE(RIGHT(B36,4)),VALUE(MID(B36,4,2)),VALUE(LEFT(B36,2))),DATE(VALUE(LEFT(B36,4)),VALUE(MID(B36,6,2)),VALUE(RIGHT(B36,2))))) -> 45660 | N36: =MONTH(M36) -> 1 | O36: =PROPER(TRIM(H36)) -> Hyderabad | P36: =IFERROR(VLOOKUP(O36,city_map!$A$2:$B$6,2,FALSE()),O36) -> Hyderabad | Q36: =IF(ISNUMBER(F36),F36,VALUE(SUBSTITUTE(SUBSTITUTE(F36,"₹",""),",",""))) -> 1859 | R36: =IF(E36=99,1,E36) -> 2 | S36: =IF(G36="",0,G36) -> 0 | T36: =IF(I36="","Unknown",IF(I36="upi","UPI",I36)) -> Net Banking | U36: =IF(L36="Yes","Y",IF(L36="No","N",L36)) -> N | V36: =ROUND(R36*Q36*(1-S36),2) -> 3718 | W36: =_xlfn.XLOOKUP(D36,products!$A$2:$A$61,products!$C$2:$C$61,"Not found") -> Fashion
A37: O10036 | B37: 2025-01-04 | C37: C0631 | D37: P005 | E37: 1 | F37: 900 | G37: 0.15 | H37: Delhi | I37: UPI | J37: 4 | K37: 4 | L37: N | M37: =IF(ISNUMBER(B37),B37,IF(MID(B37,3,1)="-",DATE(VALUE(RIGHT(B37,4)),VALUE(MID(B37,4,2)),VALUE(LEFT(B37,2))),DATE(VALUE(LEFT(B37,4)),VALUE(MID(B37,6,2)),VALUE(RIGHT(B37,2))))) -> 45661 | N37: =MONTH(M37) -> 1 | O37: =PROPER(TRIM(H37)) -> Delhi | P37: =IFERROR(VLOOKUP(O37,city_map!$A$2:$B$6,2,FALSE()),O37) -> Delhi | Q37: =IF(ISNUMBER(F37),F37,VALUE(SUBSTITUTE(SUBSTITUTE(F37,"₹",""),",",""))) -> 900 | R37: =IF(E37=99,1,E37) -> 1 | S37: =IF(G37="",0,G37) -> 0.15 | T37: =IF(I37="","Unknown",IF(I37="upi","UPI",I37)) -> UPI | U37: =IF(L37="Yes","Y",IF(L37="No","N",L37)) -> N | V37: =ROUND(R37*Q37*(1-S37),2) -> 765 | W37: =_xlfn.XLOOKUP(D37,products!$A$2:$A$61,products!$C$2:$C$61,"Not found") -> Electronics
A38: O10037 | B38: 2025-01-04 | C38: C0100 | D38: P045 | E38: 2 | F38: 310 | G38: 0.1 | H38: Hyderabad | I38: UPI | J38: 3 | L38: N | M38: =IF(ISNUMBER(B38),B38,IF(MID(B38,3,1)="-",DATE(VALUE(RIGHT(B38,4)),VALUE(MID(B38,4,2)),VALUE(LEFT(B38,2))),DATE(VALUE(LEFT(B38,4)),VALUE(MID(B38,6,2)),VALUE(RIGHT(B38,2))))) -> 45661 | N38: =MONTH(M38) -> 1 | O38: =PROPER(TRIM(H38)) -> Hyderabad | P38: =IFERROR(VLOOKUP(O38,city_map!$A$2:$B$6,2,FALSE()),O38) -> Hyderabad | Q38: =IF(ISNUMBER(F38),F38,VALUE(SUBSTITUTE(SUBSTITUTE(F38,"₹",""),",",""))) -> 310 | R38: =IF(E38=99,1,E38) -> 2 | S38: =IF(G38="",0,G38) -> 0.1 | T38: =IF(I38="","Unknown",IF(I38="upi","UPI",I38)) -> UPI | U38: =IF(L38="Yes","Y",IF(L38="No","N",L38)) -> N | V38: =ROUND(R38*Q38*(1-S38),2) -> 558 | W38: =_xlfn.XLOOKUP(D38,products!$A$2:$A$61,products!$C$2:$C$61,"Not found") -> Books
A39: O10038 | B39: 2025-01-04 | C39: C0392 | D39: P033 | E39: 2 | F39: 3247 | G39: 0 | H39: Mumbai | I39: Credit Card | J39: 5 | K39: 5 | L39: N | M39: =IF(ISNUMBER(B39),B39,IF(MID(B39,3,1)="-",DATE(VALUE(RIGHT(B39,4)),VALUE(MID(B39,4,2)),VALUE(LEFT(B39,2))),DATE(VALUE(LEFT(B39,4)),VALUE(MID(B39,6,2)),VALUE(RIGHT(B39,2))))) -> 45661 | N39: =MONTH(M39) -> 1 | O39: =PROPER(TRIM(H39)) -> Mumbai | P39: =IFERROR(VLOOKUP(O39,city_map!$A$2:$B$6,2,FALSE()),O39) -> Mumbai | Q39: =IF(ISNUMBER(F39),F39,VALUE(SUBSTITUTE(SUBSTITUTE(F39,"₹",""),",",""))) -> 3247 | R39: =IF(E39=99,1,E39) -> 2 | S39: =IF(G39="",0,G39) -> 0 | T39: =IF(I39="","Unknown",IF(I39="upi","UPI",I39)) -> Credit Card | U39: =IF(L39="Yes","Y",IF(L39="No","N",L39)) -> N | V39: =ROUND(R39*Q39*(1-S39),2) -> 6494 | W39: =_xlfn.XLOOKUP(D39,products!$A$2:$A$61,products!$C$2:$C$61,"Not found") -> Home
A40: O10039 | B40: 2025-01-04 | C40: C0457 | D40: P019 | E40: 1 | F40: 1176 | G40: 0.15 | H40: Mumbai | I40: Net Banking | J40: 3 | K40: 5 | L40: No | M40: =IF(ISNUMBER(B40),B40,IF(MID(B40,3,1)="-",DATE(VALUE(RIGHT(B40,4)),VALUE(MID(B40,4,2)),VALUE(LEFT(B40,2))),DATE(VALUE(LEFT(B40,4)),VALUE(MID(B40,6,2)),VALUE(RIGHT(B40,2))))) -> 45661 | N40: =MONTH(M40) -> 1 | O40: =PROPER(TRIM(H40)) -> Mumbai | P40: =IFERROR(VLOOKUP(O40,city_map!$A$2:$B$6,2,FALSE()),O40) -> Mumbai | Q40: =IF(ISNUMBER(F40),F40,VALUE(SUBSTITUTE(SUBSTITUTE(F40,"₹",""),",",""))) -> 1176 | R40: =IF(E40=99,1,E40) -> 1 | S40: =IF(G40="",0,G40) -> 0.15 | T40: =IF(I40="","Unknown",IF(I40="upi","UPI",I40)) -> Net Banking | U40: =IF(L40="Yes","Y",IF(L40="No","N",L40)) -> N | V40: =ROUND(R40*Q40*(1-S40),2) -> 999.6 | W40: =_xlfn.XLOOKUP(D40,products!$A$2:$A$61,products!$C$2:$C$61,"Not found") -> Fashion
A41: O10040 | B41: 2025-01-04 | C41: C0160 | D41: P020 | E41: 4 | F41: 2408 | G41: 0.2 | H41: Bengaluru | I41: Debit Card | J41: 6 | K41: 4 | L41: N | M41: =IF(ISNUMBER(B41),B41,IF(MID(B41,3,1)="-",DATE(VALUE(RIGHT(B41,4)),VALUE(MID(B41,4,2)),VALUE(LEFT(B41,2))),DATE(VALUE(LEFT(B41,4)),VALUE(MID(B41,6,2)),VALUE(RIGHT(B41,2))))) -> 45661 | N41: =MONTH(M41) -> 1 | O41: =PROPER(TRIM(H41)) -> Bengaluru | P41: =IFERROR(VLOOKUP(O41,city_map!$A$2:$B$6,2,FALSE()),O41) -> Bengaluru | Q41: =IF(ISNUMBER(F41),F41,VALUE(SUBSTITUTE(SUBSTITUTE(F41,"₹",""),",",""))) -> 2408 | R41: =IF(E41=99,1,E41) -> 4 | S41: =IF(G41="",0,G41) -> 0.2 | T41: =IF(I41="","Unknown",IF(I41="upi","UPI",I41)) -> Debit Card | U41: =IF(L41="Yes","Y",IF(L41="No","N",L41)) -> N | V41: =ROUND(R41*Q41*(1-S41),2) -> 7705.6 | W41: =_xlfn.XLOOKUP(D41,products!$A$2:$A$61,products!$C$2:$C$61,"Not found") -> Fashion
A42: O10041 | B42: 2025-01-04 | C42: C0178 | D42: P002 | E42: 1 | F42: ₹2,551 | G42: 0 | H42: Chennai | I42: UPI | J42: 3 | K42: 4 | L42: N | M42: =IF(ISNUMBER(B42),B42,IF(MID(B42,3,1)="-",DATE(VALUE(RIGHT(B42,4)),VALUE(MID(B42,4,2)),VALUE(LEFT(B42,2))),DATE(VALUE(LEFT(B42,4)),VALUE(MID(B42,6,2)),VALUE(RIGHT(B42,2))))) -> 45661 | N42: =MONTH(M42) -> 1 | O42: =PROPER(TRIM(H42)) -> Chennai | P42: =IFERROR(VLOOKUP(O42,city_map!$A$2:$B$6,2,FALSE()),O42) -> Chennai | Q42: =IF(ISNUMBER(F42),F42,VALUE(SUBSTITUTE(SUBSTITUTE(F42,"₹",""),",",""))) -> 2551 | R42: =IF(E42=99,1,E42) -> 1 | S42: =IF(G42="",0,G42) -> 0 | T42: =IF(I42="","Unknown",IF(I42="upi","UPI",I42)) -> UPI | U42: =IF(L42="Yes","Y",IF(L42="No","N",L42)) -> N | V42: =ROUND(R42*Q42*(1-S42),2) -> 2551 | W42: =_xlfn.XLOOKUP(D42,products!$A$2:$A$61,products!$C$2:$C$61,"Not found") -> Electronics
A43: O10042 | B43: 2025-01-05 | C43: C0191 | D43: P025 | E43: 1 | F43: 1312 | G43: 0 | H43: Delhi | I43: COD | J43: 5 | K43: 3 | L43: N | M43: =IF(ISNUMBER(B43),B43,IF(MID(B43,3,1)="-",DATE(VALUE(RIGHT(B43,4)),VALUE(MID(B43,4,2)),VALUE(LEFT(B43,2))),DATE(VALUE(LEFT(B43,4)),VALUE(MID(B43,6,2)),VALUE(RIGHT(B43,2))))) -> 45662 | N43: =MONTH(M43) -> 1 | O43: =PROPER(TRIM(H43)) -> Delhi | P43: =IFERROR(VLOOKUP(O43,city_map!$A$2:$B$6,2,FALSE()),O43) -> Delhi | Q43: =IF(ISNUMBER(F43),F43,VALUE(SUBSTITUTE(SUBSTITUTE(F43,"₹",""),",",""))) -> 1312 | R43: =IF(E43=99,1,E43) -> 1 | S43: =IF(G43="",0,G43) -> 0 | T43: =IF(I43="","Unknown",IF(I43="upi","UPI",I43)) -> COD | U43: =IF(L43="Yes","Y",IF(L43="No","N",L43)) -> N | V43: =ROUND(R43*Q43*(1-S43),2) -> 1312 | W43: =_xlfn.XLOOKUP(D43,products!$A$2:$A$61,products!$C$2:$C$61,"Not found") -> Home
A44: O10043 | B44: 2025-01-05 | C44: C0300 | D44: P003 | E44: 2 | F44: 4070 | G44: 0.05 | H44: Chennai | I44: Debit Card | J44: 2 | K44: 5 | L44: N | M44: =IF(ISNUMBER(B44),B44,IF(MID(B44,3,1)="-",DATE(VALUE(RIGHT(B44,4)),VALUE(MID(B44,4,2)),VALUE(LEFT(B44,2))),DATE(VALUE(LEFT(B44,4)),VALUE(MID(B44,6,2)),VALUE(RIGHT(B44,2))))) -> 45662 | N44: =MONTH(M44) -> 1 | O44: =PROPER(TRIM(H44)) -> Chennai | P44: =IFERROR(VLOOKUP(O44,city_map!$A$2:$B$6,2,FALSE()),O44) -> Chennai | Q44: =IF(ISNUMBER(F44),F44,VALUE(SUBSTITUTE(SUBSTITUTE(F44,"₹",""),",",""))) -> 4070 | R44: =IF(E44=99,1,E44) -> 2 | S44: =IF(G44="",0,G44) -> 0.05 | T44: =IF(I44="","Unknown",IF(I44="upi","UPI",I44)) -> Debit Card | U44: =IF(L44="Yes","Y",IF(L44="No","N",L44)) -> N | V44: =ROUND(R44*Q44*(1-S44),2) -> 7733 | W44: =_xlfn.XLOOKUP(D44,products!$A$2:$A$61,products!$C$2:$C$61,"Not found") -> Electronics
A45: O10044 | B45: 2025-01-05 | C45: C0422 | D45: P016 | E45: 2 | F45: 1871 | G45: 0.2 | H45: Hyderabad | I45: UPI | J45: 4 | K45: 4 | L45: N | M45: =IF(ISNUMBER(B45),B45,IF(MID(B45,3,1)="-",DATE(VALUE(RIGHT(B45,4)),VALUE(MID(B45,4,2)),VALUE(LEFT(B45,2))),DATE(VALUE(LEFT(B45,4)),VALUE(MID(B45,6,2)),VALUE(RIGHT(B45,2))))) -> 45662 | N45: =MONTH(M45) -> 1 | O45: =PROPER(TRIM(H45)) -> Hyderabad | P45: =IFERROR(VLOOKUP(O45,city_map!$A$2:$B$6,2,FALSE()),O45) -> Hyderabad | Q45: =IF(ISNUMBER(F45),F45,VALUE(SUBSTITUTE(SUBSTITUTE(F45,"₹",""),",",""))) -> 1871 | R45: =IF(E45=99,1,E45) -> 2 | S45: =IF(G45="",0,G45) -> 0.2 | T45: =IF(I45="","Unknown",IF(I45="upi","UPI",I45)) -> UPI | U45: =IF(L45="Yes","Y",IF(L45="No","N",L45)) -> N | V45: =ROUND(R45*Q45*(1-S45),2) -> 2993.6 | W45: =_xlfn.XLOOKUP(D45,products!$A$2:$A$61,products!$C$2:$C$61,"Not found") -> Fashion
A46: O10045 | B46: 2025-01-05 | C46: C0553 | D46: P008 | E46: 1 | F46: 384 | G46: 0.2 | H46: Bengaluru | I46: UPI | J46: 5 | K46: 4 | L46: N | M46: =IF(ISNUMBER(B46),B46,IF(MID(B46,3,1)="-",DATE(VALUE(RIGHT(B46,4)),VALUE(MID(B46,4,2)),VALUE(LEFT(B46,2))),DATE(VALUE(LEFT(B46,4)),VALUE(MID(B46,6,2)),VALUE(RIGHT(B46,2))))) -> 45662 | N46: =MONTH(M46) -> 1 | O46: =PROPER(TRIM(H46)) -> Bengaluru | P46: =IFERROR(VLOOKUP(O46,city_map!$A$2:$B$6,2,FALSE()),O46) -> Bengaluru | Q46: =IF(ISNUMBER(F46),F46,VALUE(SUBSTITUTE(SUBSTITUTE(F46,"₹",""),",",""))) -> 384 | R46: =IF(E46=99,1,E46) -> 1 | S46: =IF(G46="",0,G46) -> 0.2 | T46: =IF(I46="","Unknown",IF(I46="upi","UPI",I46)) -> UPI | U46: =IF(L46="Yes","Y",IF(L46="No","N",L46)) -> N | V46: =ROUND(R46*Q46*(1-S46),2) -> 307.2 | W46: =_xlfn.XLOOKUP(D46,products!$A$2:$A$61,products!$C$2:$C$61,"Not found") -> Electronics
A47: O10046 | B47: 2025-01-05 | C47: C0122 | D47: P060 | E47: 1 | F47: 414 | G47: 0.1 | H47: Delhi | I47: Debit Card | J47: 6 | K47: 3 | L47: N | M47: =IF(ISNUMBER(B47),B47,IF(MID(B47,3,1)="-",DATE(VALUE(RIGHT(B47,4)),VALUE(MID(B47,4,2)),VALUE(LEFT(B47,2))),DATE(VALUE(LEFT(B47,4)),VALUE(MID(B47,6,2)),VALUE(RIGHT(B47,2))))) -> 45662 | N47: =MONTH(M47) -> 1 | O47: =PROPER(TRIM(H47)) -> Delhi | P47: =IFERROR(VLOOKUP(O47,city_map!$A$2:$B$6,2,FALSE()),O47) -> Delhi | Q47: =IF(ISNUMBER(F47),F47,VALUE(SUBSTITUTE(SUBSTITUTE(F47,"₹",""),",",""))) -> 414 | R47: =IF(E47=99,1,E47) -> 1 | S47: =IF(G47="",0,G47) -> 0.1 | T47: =IF(I47="","Unknown",IF(I47="upi","UPI",I47)) -> Debit Card | U47: =IF(L47="Yes","Y",IF(L47="No","N",L47)) -> N | V47: =ROUND(R47*Q47*(1-S47),2) -> 372.6 | W47: =_xlfn.XLOOKUP(D47,products!$A$2:$A$61,products!$C$2:$C$61,"Not found") -> Beauty
A48: O10047 | B48: 2025-01-05 | C48: C0147 | D48: P008 | E48: 1 | F48: 409 | G48: 0 | H48: Lucknow | I48: UPI | J48: 8 | K48: 2 | L48: Yes | M48: =IF(ISNUMBER(B48),B48,IF(MID(B48,3,1)="-",DATE(VALUE(RIGHT(B48,4)),VALUE(MID(B48,4,2)),VALUE(LEFT(B48,2))),DATE(VALUE(LEFT(B48,4)),VALUE(MID(B48,6,2)),VALUE(RIGHT(B48,2))))) -> 45662 | N48: =MONTH(M48) -> 1 | O48: =PROPER(TRIM(H48)) -> Lucknow | P48: =IFERROR(VLOOKUP(O48,city_map!$A$2:$B$6,2,FALSE()),O48) -> Lucknow | Q48: =IF(ISNUMBER(F48),F48,VALUE(SUBSTITUTE(SUBSTITUTE(F48,"₹",""),",",""))) -> 409 | R48: =IF(E48=99,1,E48) -> 1 | S48: =IF(G48="",0,G48) -> 0 | T48: =IF(I48="","Unknown",IF(I48="upi","UPI",I48)) -> UPI | U48: =IF(L48="Yes","Y",IF(L48="No","N",L48)) -> Y | V48: =ROUND(R48*Q48*(1-S48),2) -> 409 | W48: =_xlfn.XLOOKUP(D48,products!$A$2:$A$61,products!$C$2:$C$61,"Not found") -> Electronics
A49: O10048 | B49: 2025-01-05 | C49: C0418 | D49: P008 | E49: 1 | F49: 400 | G49: 0 | H49: Bengaluru | I49: UPI | J49: 2 | L49: N | M49: =IF(ISNUMBER(B49),B49,IF(MID(B49,3,1)="-",DATE(VALUE(RIGHT(B49,4)),VALUE(MID(B49,4,2)),VALUE(LEFT(B49,2))),DATE(VALUE(LEFT(B49,4)),VALUE(MID(B49,6,2)),VALUE(RIGHT(B49,2))))) -> 45662 | N49: =MONTH(M49) -> 1 | O49: =PROPER(TRIM(H49)) -> Bengaluru | P49: =IFERROR(VLOOKUP(O49,city_map!$A$2:$B$6,2,FALSE()),O49) -> Bengaluru | Q49: =IF(ISNUMBER(F49),F49,VALUE(SUBSTITUTE(SUBSTITUTE(F49,"₹",""),",",""))) -> 400 | R49: =IF(E49=99,1,E49) -> 1 | S49: =IF(G49="",0,G49) -> 0 | T49: =IF(I49="","Unknown",IF(I49="upi","UPI",I49)) -> UPI | U49: =IF(L49="Yes","Y",IF(L49="No","N",L49)) -> N | V49: =ROUND(R49*Q49*(1-S49),2) -> 400 | W49: =_xlfn.XLOOKUP(D49,products!$A$2:$A$61,products!$C$2:$C$61,"Not found") -> Electronics
A50: O10049 | B50: 2025-01-05 | C50: C0075 | D50: P023 | E50: 1 | F50: 1649 | G50: 0.05 | H50: Delhi | I50: Credit Card | J50: 6 | K50: 3 | L50: Y | M50: =IF(ISNUMBER(B50),B50,IF(MID(B50,3,1)="-",DATE(VALUE(RIGHT(B50,4)),VALUE(MID(B50,4,2)),VALUE(LEFT(B50,2))),DATE(VALUE(LEFT(B50,4)),VALUE(MID(B50,6,2)),VALUE(RIGHT(B50,2))))) -> 45662 | N50: =MONTH(M50) -> 1 | O50: =PROPER(TRIM(H50)) -> Delhi | P50: =IFERROR(VLOOKUP(O50,city_map!$A$2:$B$6,2,FALSE()),O50) -> Delhi | Q50: =IF(ISNUMBER(F50),F50,VALUE(SUBSTITUTE(SUBSTITUTE(F50,"₹",""),",",""))) -> 1649 | R50: =IF(E50=99,1,E50) -> 1 | S50: =IF(G50="",0,G50) -> 0.05 | T50: =IF(I50="","Unknown",IF(I50="upi","UPI",I50)) -> Credit Card | U50: =IF(L50="Yes","Y",IF(L50="No","N",L50)) -> Y | V50: =ROUND(R50*Q50*(1-S50),2) -> 1566.55 | W50: =_xlfn.XLOOKUP(D50,products!$A$2:$A$61,products!$C$2:$C$61,"Not found") -> Fashion
A51: O10050 | B51: 2025-01-05 | C51: C0349 | D51: P018 | E51: 2 | F51: 2447 | G51: 0 | H51: Lucknow | J51: 6 | K51: 3 | L51: Y | M51: =IF(ISNUMBER(B51),B51,IF(MID(B51,3,1)="-",DATE(VALUE(RIGHT(B51,4)),VALUE(MID(B51,4,2)),VALUE(LEFT(B51,2))),DATE(VALUE(LEFT(B51,4)),VALUE(MID(B51,6,2)),VALUE(RIGHT(B51,2))))) -> 45662 | N51: =MONTH(M51) -> 1 | O51: =PROPER(TRIM(H51)) -> Lucknow | P51: =IFERROR(VLOOKUP(O51,city_map!$A$2:$B$6,2,FALSE()),O51) -> Lucknow | Q51: =IF(ISNUMBER(F51),F51,VALUE(SUBSTITUTE(SUBSTITUTE(F51,"₹",""),",",""))) -> 2447 | R51: =IF(E51=99,1,E51) -> 2 | S51: =IF(G51="",0,G51) -> 0 | T51: =IF(I51="","Unknown",IF(I51="upi","UPI",I51)) -> Unknown | U51: =IF(L51="Yes","Y",IF(L51="No","N",L51)) -> Y | V51: =ROUND(R51*Q51*(1-S51),2) -> 4894 | W51: =_xlfn.XLOOKUP(D51,products!$A$2:$A$61,products!$C$2:$C$61,"Not found") -> Fashion
A52: O10051 | B52: 2025-01-05 | C52: C0416 | D52: P026 | E52: 1 | F52: 2044 | G52: 0 | H52: Kolkata | I52: Credit Card | J52: 2 | K52: 5 | L52: N | M52: =IF(ISNUMBER(B52),B52,IF(MID(B52,3,1)="-",DATE(VALUE(RIGHT(B52,4)),VALUE(MID(B52,4,2)),VALUE(LEFT(B52,2))),DATE(VALUE(LEFT(B52,4)),VALUE(MID(B52,6,2)),VALUE(RIGHT(B52,2))))) -> 45662 | N52: =MONTH(M52) -> 1 | O52: =PROPER(TRIM(H52)) -> Kolkata | P52: =IFERROR(VLOOKUP(O52,city_map!$A$2:$B$6,2,FALSE()),O52) -> Kolkata | Q52: =IF(ISNUMBER(F52),F52,VALUE(SUBSTITUTE(SUBSTITUTE(F52,"₹",""),",",""))) -> 2044 | R52: =IF(E52=99,1,E52) -> 1 | S52: =IF(G52="",0,G52) -> 0 | T52: =IF(I52="","Unknown",IF(I52="upi","UPI",I52)) -> Credit Card | U52: =IF(L52="Yes","Y",IF(L52="No","N",L52)) -> N | V52: =ROUND(R52*Q52*(1-S52),2) -> 2044 | W52: =_xlfn.XLOOKUP(D52,products!$A$2:$A$61,products!$C$2:$C$61,"Not found") -> Home
A53: O10052 | B53: 2025-01-05 | C53: C0244 | D53: P006 | E53: 1 | F53: 1518 | G53: 0.05 | H53: Jaipur | I53: COD | J53: 5 | K53: 4 | L53: N | M53: =IF(ISNUMBER(B53),B53,IF(MID(B53,3,1)="-",DATE(VALUE(RIGHT(B53,4)),VALUE(MID(B53,4,2)),VALUE(LEFT(B53,2))),DATE(VALUE(LEFT(B53,4)),VALUE(MID(B53,6,2)),VALUE(RIGHT(B53,2))))) -> 45662 | N53: =MONTH(M53) -> 1 | O53: =PROPER(TRIM(H53)) -> Jaipur | P53: =IFERROR(VLOOKUP(O53,city_map!$A$2:$B$6,2,FALSE()),O53) -> Jaipur | Q53: =IF(ISNUMBER(F53),F53,VALUE(SUBSTITUTE(SUBSTITUTE(F53,"₹",""),",",""))) -> 1518 | R53: =IF(E53=99,1,E53) -> 1 | S53: =IF(G53="",0,G53) -> 0.05 | T53: =IF(I53="","Unknown",IF(I53="upi","UPI",I53)) -> COD | U53: =IF(L53="Yes","Y",IF(L53="No","N",L53)) -> N | V53: =ROUND(R53*Q53*(1-S53),2) -> 1442.1 | W53: =_xlfn.XLOOKUP(D53,products!$A$2:$A$61,products!$C$2:$C$61,"Not found") -> Electronics
A54: O10053 | B54: 2025-01-05 | C54: C0767 | D54: P017 | E54: 1 | F54: 1259 | G54: 0.15 | H54: Delhi | I54: COD | J54: 5 | K54: 3 | L54: Y | M54: =IF(ISNUMBER(B54),B54,IF(MID(B54,3,1)="-",DATE(VALUE(RIGHT(B54,4)),VALUE(MID(B54,4,2)),VALUE(LEFT(B54,2))),DATE(VALUE(LEFT(B54,4)),VALUE(MID(B54,6,2)),VALUE(RIGHT(B54,2))))) -> 45662 | N54: =MONTH(M54) -> 1 | O54: =PROPER(TRIM(H54)) -> Delhi | P54: =IFERROR(VLOOKUP(O54,city_map!$A$2:$B$6,2,FALSE()),O54) -> Delhi | Q54: =IF(ISNUMBER(F54),F54,VALUE(SUBSTITUTE(SUBSTITUTE(F54,"₹",""),",",""))) -> 1259 | R54: =IF(E54=99,1,E54) -> 1 | S54: =IF(G54="",0,G54) -> 0.15 | T54: =IF(I54="","Unknown",IF(I54="upi","UPI",I54)) -> COD | U54: =IF(L54="Yes","Y",IF(L54="No","N",L54)) -> Y | V54: =ROUND(R54*Q54*(1-S54),2) -> 1070.15 | W54: =_xlfn.XLOOKUP(D54,products!$A$2:$A$61,products!$C$2:$C$61,"Not found") -> Fashion
A55: O10054 | B55: 2025-01-05 | C55: C0531 | D55: P025 | E55: 1 | F55: 1340 | G55: 0 | H55: Chennai | I55: Credit Card | J55: 2 | K55: 4 | L55: N | M55: =IF(ISNUMBER(B55),B55,IF(MID(B55,3,1)="-",DATE(VALUE(RIGHT(B55,4)),VALUE(MID(B55,4,2)),VALUE(LEFT(B55,2))),DATE(VALUE(LEFT(B55,4)),VALUE(MID(B55,6,2)),VALUE(RIGHT(B55,2))))) -> 45662 | N55: =MONTH(M55) -> 1 | O55: =PROPER(TRIM(H55)) -> Chennai | P55: =IFERROR(VLOOKUP(O55,city_map!$A$2:$B$6,2,FALSE()),O55) -> Chennai | Q55: =IF(ISNUMBER(F55),F55,VALUE(SUBSTITUTE(SUBSTITUTE(F55,"₹",""),",",""))) -> 1340 | R55: =IF(E55=99,1,E55) -> 1 | S55: =IF(G55="",0,G55) -> 0 | T55: =IF(I55="","Unknown",IF(I55="upi","UPI",I55)) -> Credit Card | U55: =IF(L55="Yes","Y",IF(L55="No","N",L55)) -> N | V55: =ROUND(R55*Q55*(1-S55),2) -> 1340 | W55: =_xlfn.XLOOKUP(D55,products!$A$2:$A$61,products!$C$2:$C$61,"Not found") -> Home
A56: O10055 | B56: 2025-01-05 | C56: C0357 | D56: P038 | E56: 2 | F56: 875 | G56: 0 | H56: Bengaluru | I56: Debit Card | J56: 4 | K56: 3 | L56: N | M56: =IF(ISNUMBER(B56),B56,IF(MID(B56,3,1)="-",DATE(VALUE(RIGHT(B56,4)),VALUE(MID(B56,4,2)),VALUE(LEFT(B56,2))),DATE(VALUE(LEFT(B56,4)),VALUE(MID(B56,6,2)),VALUE(RIGHT(B56,2))))) -> 45662 | N56: =MONTH(M56) -> 1 | O56: =PROPER(TRIM(H56)) -> Bengaluru | P56: =IFERROR(VLOOKUP(O56,city_map!$A$2:$B$6,2,FALSE()),O56) -> Bengaluru | Q56: =IF(ISNUMBER(F56),F56,VALUE(SUBSTITUTE(SUBSTITUTE(F56,"₹",""),",",""))) -> 875 | R56: =IF(E56=99,1,E56) -> 2 | S56: =IF(G56="",0,G56) -> 0 | T56: =IF(I56="","Unknown",IF(I56="upi","UPI",I56)) -> Debit Card | U56: =IF(L56="Yes","Y",IF(L56="No","N",L56)) -> N | V56: =ROUND(R56*Q56*(1-S56),2) -> 1750 | W56: =_xlfn.XLOOKUP(D56,products!$A$2:$A$61,products!$C$2:$C$61,"Not found") -> Books
A57: O10056 | B57: 2025-01-05 | C57: C0449 | D57: P004 | E57: 1 | F57: 1350 | H57: Pune | I57: COD | J57: 5 | K57: 3 | L57: Y | M57: =IF(ISNUMBER(B57),B57,IF(MID(B57,3,1)="-",DATE(VALUE(RIGHT(B57,4)),VALUE(MID(B57,4,2)),VALUE(LEFT(B57,2))),DATE(VALUE(LEFT(B57,4)),VALUE(MID(B57,6,2)),VALUE(RIGHT(B57,2))))) -> 45662 | N57: =MONTH(M57) -> 1 | O57: =PROPER(TRIM(H57)) -> Pune | P57: =IFERROR(VLOOKUP(O57,city_map!$A$2:$B$6,2,FALSE()),O57) -> Pune | Q57: =IF(ISNUMBER(F57),F57,VALUE(SUBSTITUTE(SUBSTITUTE(F57,"₹",""),",",""))) -> 1350 | R57: =IF(E57=99,1,E57) -> 1 | S57: =IF(G57="",0,G57) -> 0 | T57: =IF(I57="","Unknown",IF(I57="upi","UPI",I57)) -> COD | U57: =IF(L57="Yes","Y",IF(L57="No","N",L57)) -> Y | V57: =ROUND(R57*Q57*(1-S57),2) -> 1350 | W57: =_xlfn.XLOOKUP(D57,products!$A$2:$A$61,products!$C$2:$C$61,"Not found") -> Electronics
A58: O10057 | B58: 2025-01-05 | C58: C0027 | D58: P024 | E58: 3 | F58: 1956 | G58: 0 | H58: Delhi | I58: Debit Card | J58: 2 | K58: 5 | L58: N | M58: =IF(ISNUMBER(B58),B58,IF(MID(B58,3,1)="-",DATE(VALUE(RIGHT(B58,4)),VALUE(MID(B58,4,2)),VALUE(LEFT(B58,2))),DATE(VALUE(LEFT(B58,4)),VALUE(MID(B58,6,2)),VALUE(RIGHT(B58,2))))) -> 45662 | N58: =MONTH(M58) -> 1 | O58: =PROPER(TRIM(H58)) -> Delhi | P58: =IFERROR(VLOOKUP(O58,city_map!$A$2:$B$6,2,FALSE()),O58) -> Delhi | Q58: =IF(ISNUMBER(F58),F58,VALUE(SUBSTITUTE(SUBSTITUTE(F58,"₹",""),",",""))) -> 1956 | R58: =IF(E58=99,1,E58) -> 3 | S58: =IF(G58="",0,G58) -> 0 | T58: =IF(I58="","Unknown",IF(I58="upi","UPI",I58)) -> Debit Card | U58: =IF(L58="Yes","Y",IF(L58="No","N",L58)) -> N | V58: =ROUND(R58*Q58*(1-S58),2) -> 5868 | W58: =_xlfn.XLOOKUP(D58,products!$A$2:$A$61,products!$C$2:$C$61,"Not found") -> Fashion
A59: O10058 | B59: 2025-01-05 | C59: C0759 | D59: P039 | E59: 2 | F59: 401 | G59: 0.05 | H59: Ahmedabad | I59: UPI | J59: 6 | K59: 3 | L59: Y | M59: =IF(ISNUMBER(B59),B59,IF(MID(B59,3,1)="-",DATE(VALUE(RIGHT(B59,4)),VALUE(MID(B59,4,2)),VALUE(LEFT(B59,2))),DATE(VALUE(LEFT(B59,4)),VALUE(MID(B59,6,2)),VALUE(RIGHT(B59,2))))) -> 45662 | N59: =MONTH(M59) -> 1 | O59: =PROPER(TRIM(H59)) -> Ahmedabad | P59: =IFERROR(VLOOKUP(O59,city_map!$A$2:$B$6,2,FALSE()),O59) -> Ahmedabad | Q59: =IF(ISNUMBER(F59),F59,VALUE(SUBSTITUTE(SUBSTITUTE(F59,"₹",""),",",""))) -> 401 | R59: =IF(E59=99,1,E59) -> 2 | S59: =IF(G59="",0,G59) -> 0.05 | T59: =IF(I59="","Unknown",IF(I59="upi","UPI",I59)) -> UPI | U59: =IF(L59="Yes","Y",IF(L59="No","N",L59)) -> Y | V59: =ROUND(R59*Q59*(1-S59),2) -> 761.9 | W59: =_xlfn.XLOOKUP(D59,products!$A$2:$A$61,products!$C$2:$C$61,"Not found") -> Books
A60: O10059 | B60: 2025-01-06 | C60: C0404 | D60: P046 | E60: 2 | F60: 469 | G60: 0.15 | H60: Kolkata | I60: Credit Card | J60: 6 | K60: 4 | L60: N | M60: =IF(ISNUMBER(B60),B60,IF(MID(B60,3,1)="-",DATE(VALUE(RIGHT(B60,4)),VALUE(MID(B60,4,2)),VALUE(LEFT(B60,2))),DATE(VALUE(LEFT(B60,4)),VALUE(MID(B60,6,2)),VALUE(RIGHT(B60,2))))) -> 45663 | N60: =MONTH(M60) -> 1 | O60: =PROPER(TRIM(H60)) -> Kolkata | P60: =IFERROR(VLOOKUP(O60,city_map!$A$2:$B$6,2,FALSE()),O60) -> Kolkata | Q60: =IF(ISNUMBER(F60),F60,VALUE(SUBSTITUTE(SUBSTITUTE(F60,"₹",""),",",""))) -> 469 | R60: =IF(E60=99,1,E60) -> 2 | S60: =IF(G60="",0,G60) -> 0.15 | T60: =IF(I60="","Unknown",IF(I60="upi","UPI",I60)) -> Credit Card | U60: =IF(L60="Yes","Y",IF(L60="No","N",L60)) -> N | V60: =ROUND(R60*Q60*(1-S60),2) -> 797.3 | W60: =_xlfn.XLOOKUP(D60,products!$A$2:$A$61,products!$C$2:$C$61,"Not found") -> Books
A61: O10060 | B61: 2025-01-06 | C61: C0634 | D61: P001 | E61: 1 | F61: 1954 | G61: 0.05 | H61: mumbai | I61: UPI | J61: 3 | K61: 4 | L61: N | M61: =IF(ISNUMBER(B61),B61,IF(MID(B61,3,1)="-",DATE(VALUE(RIGHT(B61,4)),VALUE(MID(B61,4,2)),VALUE(LEFT(B61,2))),DATE(VALUE(LEFT(B61,4)),VALUE(MID(B61,6,2)),VALUE(RIGHT(B61,2))))) -> 45663 | N61: =MONTH(M61) -> 1 | O61: =PROPER(TRIM(H61)) -> Mumbai | P61: =IFERROR(VLOOKUP(O61,city_map!$A$2:$B$6,2,FALSE()),O61) -> Mumbai | Q61: =IF(ISNUMBER(F61),F61,VALUE(SUBSTITUTE(SUBSTITUTE(F61,"₹",""),",",""))) -> 1954 | R61: =IF(E61=99,1,E61) -> 1 | S61: =IF(G61="",0,G61) -> 0.05 | T61: =IF(I61="","Unknown",IF(I61="upi","UPI",I61)) -> UPI | U61: =IF(L61="Yes","Y",IF(L61="No","N",L61)) -> N | V61: =ROUND(R61*Q61*(1-S61),2) -> 1856.3 | W61: =_xlfn.XLOOKUP(D61,products!$A$2:$A$61,products!$C$2:$C$61,"Not found") -> Electronics
A62: O10061 | B62: 2025-01-06 | C62: C0736 | D62: P030 | E62: 2 | F62: 385 | G62: 0.1 | H62: pune | I62: UPI | J62: 4 | K62: 4 | L62: N | M62: =IF(ISNUMBER(B62),B62,IF(MID(B62,3,1)="-",DATE(VALUE(RIGHT(B62,4)),VALUE(MID(B62,4,2)),VALUE(LEFT(B62,2))),DATE(VALUE(LEFT(B62,4)),VALUE(MID(B62,6,2)),VALUE(RIGHT(B62,2))))) -> 45663 | N62: =MONTH(M62) -> 1 | O62: =PROPER(TRIM(H62)) -> Pune | P62: =IFERROR(VLOOKUP(O62,city_map!$A$2:$B$6,2,FALSE()),O62) -> Pune | Q62: =IF(ISNUMBER(F62),F62,VALUE(SUBSTITUTE(SUBSTITUTE(F62,"₹",""),",",""))) -> 385 | R62: =IF(E62=99,1,E62) -> 2 | S62: =IF(G62="",0,G62) -> 0.1 | T62: =IF(I62="","Unknown",IF(I62="upi","UPI",I62)) -> UPI | U62: =IF(L62="Yes","Y",IF(L62="No","N",L62)) -> N | V62: =ROUND(R62*Q62*(1-S62),2) -> 693 | W62: =_xlfn.XLOOKUP(D62,products!$A$2:$A$61,products!$C$2:$C$61,"Not found") -> Home
A63: O10062 | B63: 2025-01-06 | C63: C0465 | D63: P024 | E63: 1 | F63: 1975 | G63: 0 | H63: Pune | I63: COD | J63: 7 | K63: 3 | L63: N | M63: =IF(ISNUMBER(B63),B63,IF(MID(B63,3,1)="-",DATE(VALUE(RIGHT(B63,4)),VALUE(MID(B63,4,2)),VALUE(LEFT(B63,2))),DATE(VALUE(LEFT(B63,4)),VALUE(MID(B63,6,2)),VALUE(RIGHT(B63,2))))) -> 45663 | N63: =MONTH(M63) -> 1 | O63: =PROPER(TRIM(H63)) -> Pune | P63: =IFERROR(VLOOKUP(O63,city_map!$A$2:$B$6,2,FALSE()),O63) -> Pune | Q63: =IF(ISNUMBER(F63),F63,VALUE(SUBSTITUTE(SUBSTITUTE(F63,"₹",""),",",""))) -> 1975 | R63: =IF(E63=99,1,E63) -> 1 | S63: =IF(G63="",0,G63) -> 0 | T63: =IF(I63="","Unknown",IF(I63="upi","UPI",I63)) -> COD | U63: =IF(L63="Yes","Y",IF(L63="No","N",L63)) -> N | V63: =ROUND(R63*Q63*(1-S63),2) -> 1975 | W63: =_xlfn.XLOOKUP(D63,products!$A$2:$A$61,products!$C$2:$C$61,"Not found") -> Fashion
A64: O10063 | B64: 2025-01-06 | C64: C0571 | D64: P053 | E64: 3 | F64: 620 | G64: 0.2 | H64: Calcutta | I64: Credit Card | J64: 4 | K64: 4 | L64: N | M64: =IF(ISNUMBER(B64),B64,IF(MID(B64,3,1)="-",DATE(VALUE(RIGHT(B64,4)),VALUE(MID(B64,4,2)),VALUE(LEFT(B64,2))),DATE(VALUE(LEFT(B64,4)),VALUE(MID(B64,6,2)),VALUE(RIGHT(B64,2))))) -> 45663 | N64: =MONTH(M64) -> 1 | O64: =PROPER(TRIM(H64)) -> Calcutta | P64: =IFERROR(VLOOKUP(O64,city_map!$A$2:$B$6,2,FALSE()),O64) -> Kolkata | Q64: =IF(ISNUMBER(F64),F64,VALUE(SUBSTITUTE(SUBSTITUTE(F64,"₹",""),",",""))) -> 620 | R64: =IF(E64=99,1,E64) -> 3 | S64: =IF(G64="",0,G64) -> 0.2 | T64: =IF(I64="","Unknown",IF(I64="upi","UPI",I64)) -> Credit Card | U64: =IF(L64="Yes","Y",IF(L64="No","N",L64)) -> N | V64: =ROUND(R64*Q64*(1-S64),2) -> 1488 | W64: =_xlfn.XLOOKUP(D64,products!$A$2:$A$61,products!$C$2:$C$61,"Not found") -> Beauty
A65: O10064 | B65: 2025-01-06 | C65: C0023 | D65: P008 | E65: 2 | F65: 395 | G65: 0.2 | H65: kolkata | I65: UPI | J65: 5 | K65: 4 | L65: N | M65: =IF(ISNUMBER(B65),B65,IF(MID(B65,3,1)="-",DATE(VALUE(RIGHT(B65,4)),VALUE(MID(B65,4,2)),VALUE(LEFT(B65,2))),DATE(VALUE(LEFT(B65,4)),VALUE(MID(B65,6,2)),VALUE(RIGHT(B65,2))))) -> 45663 | N65: =MONTH(M65) -> 1 | O65: =PROPER(TRIM(H65)) -> Kolkata | P65: =IFERROR(VLOOKUP(O65,city_map!$A$2:$B$6,2,FALSE()),O65) -> Kolkata | Q65: =IF(ISNUMBER(F65),F65,VALUE(SUBSTITUTE(SUBSTITUTE(F65,"₹",""),",",""))) -> 395 | R65: =IF(E65=99,1,E65) -> 2 | S65: =IF(G65="",0,G65) -> 0.2 | T65: =IF(I65="","Unknown",IF(I65="upi","UPI",I65)) -> UPI | U65: =IF(L65="Yes","Y",IF(L65="No","N",L65)) -> N | V65: =ROUND(R65*Q65*(1-S65),2) -> 632 | W65: =_xlfn.XLOOKUP(D65,products!$A$2:$A$61,products!$C$2:$C$61,"Not found") -> Electronics
A66: O10065 | B66: 2025-01-06 | C66: C0565 | D66: P030 | E66: 1 | F66: 416 | G66: 0.1 | H66: Kolkata | I66: Debit Card | J66: 4 | K66: 3 | L66: N | M66: =IF(ISNUMBER(B66),B66,IF(MID(B66,3,1)="-",DATE(VALUE(RIGHT(B66,4)),VALUE(MID(B66,4,2)),VALUE(LEFT(B66,2))),DATE(VALUE(LEFT(B66,4)),VALUE(MID(B66,6,2)),VALUE(RIGHT(B66,2))))) -> 45663 | N66: =MONTH(M66) -> 1 | O66: =PROPER(TRIM(H66)) -> Kolkata | P66: =IFERROR(VLOOKUP(O66,city_map!$A$2:$B$6,2,FALSE()),O66) -> Kolkata | Q66: =IF(ISNUMBER(F66),F66,VALUE(SUBSTITUTE(SUBSTITUTE(F66,"₹",""),",",""))) -> 416 | R66: =IF(E66=99,1,E66) -> 1 | S66: =IF(G66="",0,G66) -> 0.1 | T66: =IF(I66="","Unknown",IF(I66="upi","UPI",I66)) -> Debit Card | U66: =IF(L66="Yes","Y",IF(L66="No","N",L66)) -> N | V66: =ROUND(R66*Q66*(1-S66),2) -> 374.4 | W66: =_xlfn.XLOOKUP(D66,products!$A$2:$A$61,products!$C$2:$C$61,"Not found") -> Home
A67: O10066 | B67: 2025-01-06 | C67: C0040 | D67: P024 | E67: 1 | F67: 1880 | G67: 0 | H67: Pune | I67: COD | J67: 5 | K67: 3 | L67: Y | M67: =IF(ISNUMBER(B67),B67,IF(MID(B67,3,1)="-",DATE(VALUE(RIGHT(B67,4)),VALUE(MID(B67,4,2)),VALUE(LEFT(B67,2))),DATE(VALUE(LEFT(B67,4)),VALUE(MID(B67,6,2)),VALUE(RIGHT(B67,2))))) -> 45663 | N67: =MONTH(M67) -> 1 | O67: =PROPER(TRIM(H67)) -> Pune | P67: =IFERROR(VLOOKUP(O67,city_map!$A$2:$B$6,2,FALSE()),O67) -> Pune | Q67: =IF(ISNUMBER(F67),F67,VALUE(SUBSTITUTE(SUBSTITUTE(F67,"₹",""),",",""))) -> 1880 | R67: =IF(E67=99,1,E67) -> 1 | S67: =IF(G67="",0,G67) -> 0 | T67: =IF(I67="","Unknown",IF(I67="upi","UPI",I67)) -> COD | U67: =IF(L67="Yes","Y",IF(L67="No","N",L67)) -> Y | V67: =ROUND(R67*Q67*(1-S67),2) -> 1880 | W67: =_xlfn.XLOOKUP(D67,products!$A$2:$A$61,products!$C$2:$C$61,"Not found") -> Fashion
A68: O10067 | B68: 2025-01-06 | C68: C0612 | D68: P029 | E68: 1 | F68: 676 | G68: 0 | H68: Chennai | I68: Debit Card | J68: 5 | K68: 5 | L68: N | M68: =IF(ISNUMBER(B68),B68,IF(MID(B68,3,1)="-",DATE(VALUE(RIGHT(B68,4)),VALUE(MID(B68,4,2)),VALUE(LEFT(B68,2))),DATE(VALUE(LEFT(B68,4)),VALUE(MID(B68,6,2)),VALUE(RIGHT(B68,2))))) -> 45663 | N68: =MONTH(M68) -> 1 | O68: =PROPER(TRIM(H68)) -> Chennai | P68: =IFERROR(VLOOKUP(O68,city_map!$A$2:$B$6,2,FALSE()),O68) -> Chennai | Q68: =IF(ISNUMBER(F68),F68,VALUE(SUBSTITUTE(SUBSTITUTE(F68,"₹",""),",",""))) -> 676 | R68: =IF(E68=99,1,E68) -> 1 | S68: =IF(G68="",0,G68) -> 0 | T68: =IF(I68="","Unknown",IF(I68="upi","UPI",I68)) -> Debit Card | U68: =IF(L68="Yes","Y",IF(L68="No","N",L68)) -> N | V68: =ROUND(R68*Q68*(1-S68),2) -> 676 | W68: =_xlfn.XLOOKUP(D68,products!$A$2:$A$61,products!$C$2:$C$61,"Not found") -> Home
A69: O10068 | B69: 06-01-2025 | C69: C0017 | D69: P022 | E69: 1 | F69: ₹981 | H69: Ahmedabad | I69: Credit Card | J69: 2 | K69: 4 | L69: N | M69: =IF(ISNUMBER(B69),B69,IF(MID(B69,3,1)="-",DATE(VALUE(RIGHT(B69,4)),VALUE(MID(B69,4,2)),VALUE(LEFT(B69,2))),DATE(VALUE(LEFT(B69,4)),VALUE(MID(B69,6,2)),VALUE(RIGHT(B69,2))))) -> 45663 | N69: =MONTH(M69) -> 1 | O69: =PROPER(TRIM(H69)) -> Ahmedabad | P69: =IFERROR(VLOOKUP(O69,city_map!$A$2:$B$6,2,FALSE()),O69) -> Ahmedabad | Q69: =IF(ISNUMBER(F69),F69,VALUE(SUBSTITUTE(SUBSTITUTE(F69,"₹",""),",",""))) -> 981 | R69: =IF(E69=99,1,E69) -> 1 | S69: =IF(G69="",0,G69) -> 0 | T69: =IF(I69="","Unknown",IF(I69="upi","UPI",I69)) -> Credit Card | U69: =IF(L69="Yes","Y",IF(L69="No","N",L69)) -> N | V69: =ROUND(R69*Q69*(1-S69),2) -> 981 | W69: =_xlfn.XLOOKUP(D69,products!$A$2:$A$61,products!$C$2:$C$61,"Not found") -> Fashion
A70: O10069 | B70: 2025-01-07 | C70: C0080 | D70: P037 | E70: 2 | F70: 512 | G70: 0.05 | H70: Chennai | I70: Net Banking | J70: 4 | K70: 5 | L70: N | M70: =IF(ISNUMBER(B70),B70,IF(MID(B70,3,1)="-",DATE(VALUE(RIGHT(B70,4)),VALUE(MID(B70,4,2)),VALUE(LEFT(B70,2))),DATE(VALUE(LEFT(B70,4)),VALUE(MID(B70,6,2)),VALUE(RIGHT(B70,2))))) -> 45664 | N70: =MONTH(M70) -> 1 | O70: =PROPER(TRIM(H70)) -> Chennai | P70: =IFERROR(VLOOKUP(O70,city_map!$A$2:$B$6,2,FALSE()),O70) -> Chennai | Q70: =IF(ISNUMBER(F70),F70,VALUE(SUBSTITUTE(SUBSTITUTE(F70,"₹",""),",",""))) -> 512 | R70: =IF(E70=99,1,E70) -> 2 | S70: =IF(G70="",0,G70) -> 0.05 | T70: =IF(I70="","Unknown",IF(I70="upi","UPI",I70)) -> Net Banking | U70: =IF(L70="Yes","Y",IF(L70="No","N",L70)) -> N | V70: =ROUND(R70*Q70*(1-S70),2) -> 972.8 | W70: =_xlfn.XLOOKUP(D70,products!$A$2:$A$61,products!$C$2:$C$61,"Not found") -> Books
A71: O10070 | B71: 2025-01-07 | C71: C0070 | D71: P031 | E71: 2 | F71: 798 | G71: 0 | H71: Chennai | I71: UPI | J71: 4 | K71: 5 | L71: N | M71: =IF(ISNUMBER(B71),B71,IF(MID(B71,3,1)="-",DATE(VALUE(RIGHT(B71,4)),VALUE(MID(B71,4,2)),VALUE(LEFT(B71,2))),DATE(VALUE(LEFT(B71,4)),VALUE(MID(B71,6,2)),VALUE(RIGHT(B71,2))))) -> 45664 | N71: =MONTH(M71) -> 1 | O71: =PROPER(TRIM(H71)) -> Chennai | P71: =IFERROR(VLOOKUP(O71,city_map!$A$2:$B$6,2,FALSE()),O71) -> Chennai | Q71: =IF(ISNUMBER(F71),F71,VALUE(SUBSTITUTE(SUBSTITUTE(F71,"₹",""),",",""))) -> 798 | R71: =IF(E71=99,1,E71) -> 2 | S71: =IF(G71="",0,G71) -> 0 | T71: =IF(I71="","Unknown",IF(I71="upi","UPI",I71)) -> UPI | U71: =IF(L71="Yes","Y",IF(L71="No","N",L71)) -> N | V71: =ROUND(R71*Q71*(1-S71),2) -> 1596 | W71: =_xlfn.XLOOKUP(D71,products!$A$2:$A$61,products!$C$2:$C$61,"Not found") -> Home
A72: O10071 | B72: 2025-01-07 | C72: C0409 | D72: P024 | E72: 2 | F72: 1880 | G72: 0.3 | H72: Ahmedabad | J72: 4 | L72: N | M72: =IF(ISNUMBER(B72),B72,IF(MID(B72,3,1)="-",DATE(VALUE(RIGHT(B72,4)),VALUE(MID(B72,4,2)),VALUE(LEFT(B72,2))),DATE(VALUE(LEFT(B72,4)),VALUE(MID(B72,6,2)),VALUE(RIGHT(B72,2))))) -> 45664 | N72: =MONTH(M72) -> 1 | O72: =PROPER(TRIM(H72)) -> Ahmedabad | P72: =IFERROR(VLOOKUP(O72,city_map!$A$2:$B$6,2,FALSE()),O72) -> Ahmedabad | Q72: =IF(ISNUMBER(F72),F72,VALUE(SUBSTITUTE(SUBSTITUTE(F72,"₹",""),",",""))) -> 1880 | R72: =IF(E72=99,1,E72) -> 2 | S72: =IF(G72="",0,G72) -> 0.3 | T72: =IF(I72="","Unknown",IF(I72="upi","UPI",I72)) -> Unknown | U72: =IF(L72="Yes","Y",IF(L72="No","N",L72)) -> N | V72: =ROUND(R72*Q72*(1-S72),2) -> 2632 | W72: =_xlfn.XLOOKUP(D72,products!$A$2:$A$61,products!$C$2:$C$61,"Not found") -> Fashion
A73: O10072 | B73: 2025-01-07 | C73: C0795 | D73: P005 | E73: 1 | F73: 891 | H73: Bengaluru | I73: UPI | J73: 4 | K73: 5 | L73: N | M73: =IF(ISNUMBER(B73),B73,IF(MID(B73,3,1)="-",DATE(VALUE(RIGHT(B73,4)),VALUE(MID(B73,4,2)),VALUE(LEFT(B73,2))),DATE(VALUE(LEFT(B73,4)),VALUE(MID(B73,6,2)),VALUE(RIGHT(B73,2))))) -> 45664 | N73: =MONTH(M73) -> 1 | O73: =PROPER(TRIM(H73)) -> Bengaluru | P73: =IFERROR(VLOOKUP(O73,city_map!$A$2:$B$6,2,FALSE()),O73) -> Bengaluru | Q73: =IF(ISNUMBER(F73),F73,VALUE(SUBSTITUTE(SUBSTITUTE(F73,"₹",""),",",""))) -> 891 | R73: =IF(E73=99,1,E73) -> 1 | S73: =IF(G73="",0,G73) -> 0 | T73: =IF(I73="","Unknown",IF(I73="upi","UPI",I73)) -> UPI | U73: =IF(L73="Yes","Y",IF(L73="No","N",L73)) -> N | V73: =ROUND(R73*Q73*(1-S73),2) -> 891 | W73: =_xlfn.XLOOKUP(D73,products!$A$2:$A$61,products!$C$2:$C$61,"Not found") -> Electronics
A74: O10073 | B74: 2025-01-07 | C74: C0728 | D74: P025 | E74: 2 | F74: 1329 | G74: 0 | H74: Mumbai | I74: UPI | J74: 3 | K74: 4 | L74: N | M74: =IF(ISNUMBER(B74),B74,IF(MID(B74,3,1)="-",DATE(VALUE(RIGHT(B74,4)),VALUE(MID(B74,4,2)),VALUE(LEFT(B74,2))),DATE(VALUE(LEFT(B74,4)),VALUE(MID(B74,6,2)),VALUE(RIGHT(B74,2))))) -> 45664 | N74: =MONTH(M74) -> 1 | O74: =PROPER(TRIM(H74)) -> Mumbai | P74: =IFERROR(VLOOKUP(O74,city_map!$A$2:$B$6,2,FALSE()),O74) -> Mumbai | Q74: =IF(ISNUMBER(F74),F74,VALUE(SUBSTITUTE(SUBSTITUTE(F74,"₹",""),",",""))) -> 1329 | R74: =IF(E74=99,1,E74) -> 2 | S74: =IF(G74="",0,G74) -> 0 | T74: =IF(I74="","Unknown",IF(I74="upi","UPI",I74)) -> UPI | U74: =IF(L74="Yes","Y",IF(L74="No","N",L74)) -> N | V74: =ROUND(R74*Q74*(1-S74),2) -> 2658 | W74: =_xlfn.XLOOKUP(D74,products!$A$2:$A$61,products!$C$2:$C$61,"Not found") -> Home
A75: O10074 | B75: 2025-01-07 | C75: C0173 | D75: P014 | E75: 1 | F75: 1481 | G75: 0 | H75: Chennai | I75: upi | J75: 4 | K75: 4 | L75: N | M75: =IF(ISNUMBER(B75),B75,IF(MID(B75,3,1)="-",DATE(VALUE(RIGHT(B75,4)),VALUE(MID(B75,4,2)),VALUE(LEFT(B75,2))),DATE(VALUE(LEFT(B75,4)),VALUE(MID(B75,6,2)),VALUE(RIGHT(B75,2))))) -> 45664 | N75: =MONTH(M75) -> 1 | O75: =PROPER(TRIM(H75)) -> Chennai | P75: =IFERROR(VLOOKUP(O75,city_map!$A$2:$B$6,2,FALSE()),O75) -> Chennai | Q75: =IF(ISNUMBER(F75),F75,VALUE(SUBSTITUTE(SUBSTITUTE(F75,"₹",""),",",""))) -> 1481 | R75: =IF(E75=99,1,E75) -> 1 | S75: =IF(G75="",0,G75) -> 0 | T75: =IF(I75="","Unknown",IF(I75="upi","UPI",I75)) -> UPI | U75: =IF(L75="Yes","Y",IF(L75="No","N",L75)) -> N | V75: =ROUND(R75*Q75*(1-S75),2) -> 1481 | W75: =_xlfn.XLOOKUP(D75,products!$A$2:$A$61,products!$C$2:$C$61,"Not found") -> Fashion
A76: O10075 | B76: 2025-01-07 | C76: C0461 | D76: P017 | E76: 2 | F76: 1321 | G76: 0 | H76: Bengaluru | I76: Debit Card | J76: 4 | K76: 4 | L76: N | M76: =IF(ISNUMBER(B76),B76,IF(MID(B76,3,1)="-",DATE(VALUE(RIGHT(B76,4)),VALUE(MID(B76,4,2)),VALUE(LEFT(B76,2))),DATE(VALUE(LEFT(B76,4)),VALUE(MID(B76,6,2)),VALUE(RIGHT(B76,2))))) -> 45664 | N76: =MONTH(M76) -> 1 | O76: =PROPER(TRIM(H76)) -> Bengaluru | P76: =IFERROR(VLOOKUP(O76,city_map!$A$2:$B$6,2,FALSE()),O76) -> Bengaluru | Q76: =IF(ISNUMBER(F76),F76,VALUE(SUBSTITUTE(SUBSTITUTE(F76,"₹",""),",",""))) -> 1321 | R76: =IF(E76=99,1,E76) -> 2 | S76: =IF(G76="",0,G76) -> 0 | T76: =IF(I76="","Unknown",IF(I76="upi","UPI",I76)) -> Debit Card | U76: =IF(L76="Yes","Y",IF(L76="No","N",L76)) -> N | V76: =ROUND(R76*Q76*(1-S76),2) -> 2642 | W76: =_xlfn.XLOOKUP(D76,products!$A$2:$A$61,products!$C$2:$C$61,"Not found") -> Fashion
A77: O10076 | B77: 2025-01-07 | C77: C0695 | D77: P042 | E77: 1 | F77: 988 | G77: 0.15 | H77: Pune | I77: COD | J77: 7 | K77: 4 | L77: N | M77: =IF(ISNUMBER(B77),B77,IF(MID(B77,3,1)="-",DATE(VALUE(RIGHT(B77,4)),VALUE(MID(B77,4,2)),VALUE(LEFT(B77,2))),DATE(VALUE(LEFT(B77,4)),VALUE(MID(B77,6,2)),VALUE(RIGHT(B77,2))))) -> 45664 | N77: =MONTH(M77) -> 1 | O77: =PROPER(TRIM(H77)) -> Pune | P77: =IFERROR(VLOOKUP(O77,city_map!$A$2:$B$6,2,FALSE()),O77) -> Pune | Q77: =IF(ISNUMBER(F77),F77,VALUE(SUBSTITUTE(SUBSTITUTE(F77,"₹",""),",",""))) -> 988 | R77: =IF(E77=99,1,E77) -> 1 | S77: =IF(G77="",0,G77) -> 0.15 | T77: =IF(I77="","Unknown",IF(I77="upi","UPI",I77)) -> COD | U77: =IF(L77="Yes","Y",IF(L77="No","N",L77)) -> N | V77: =ROUND(R77*Q77*(1-S77),2) -> 839.8 | W77: =_xlfn.XLOOKUP(D77,products!$A$2:$A$61,products!$C$2:$C$61,"Not found") -> Books
A78: O10077 | B78: 2025-01-07 | C78: C0503 | D78: P025 | E78: 3 | F78: 1253 | G78: 0.1 | H78: Bengaluru | I78: UPI | J78: 5 | K78: 3 | L78: N | M78: =IF(ISNUMBER(B78),B78,IF(MID(B78,3,1)="-",DATE(VALUE(RIGHT(B78,4)),VALUE(MID(B78,4,2)),VALUE(LEFT(B78,2))),DATE(VALUE(LEFT(B78,4)),VALUE(MID(B78,6,2)),VALUE(RIGHT(B78,2))))) -> 45664 | N78: =MONTH(M78) -> 1 | O78: =PROPER(TRIM(H78)) -> Bengaluru | P78: =IFERROR(VLOOKUP(O78,city_map!$A$2:$B$6,2,FALSE()),O78) -> Bengaluru | Q78: =IF(ISNUMBER(F78),F78,VALUE(SUBSTITUTE(SUBSTITUTE(F78,"₹",""),",",""))) -> 1253 | R78: =IF(E78=99,1,E78) -> 3 | S78: =IF(G78="",0,G78) -> 0.1 | T78: =IF(I78="","Unknown",IF(I78="upi","UPI",I78)) -> UPI | U78: =IF(L78="Yes","Y",IF(L78="No","N",L78)) -> N | V78: =ROUND(R78*Q78*(1-S78),2) -> 3383.1 | W78: =_xlfn.XLOOKUP(D78,products!$A$2:$A$61,products!$C$2:$C$61,"Not found") -> Home
A79: O10078 | B79: 2025-01-07 | C79: C0400 | D79: P033 | E79: 3 | F79: 3358 | G79: 0.2 | H79: Jaipur | I79: UPI | J79: 5 | K79: 4 | L79: No | M79: =IF(ISNUMBER(B79),B79,IF(MID(B79,3,1)="-",DATE(VALUE(RIGHT(B79,4)),VALUE(MID(B79,4,2)),VALUE(LEFT(B79,2))),DATE(VALUE(LEFT(B79,4)),VALUE(MID(B79,6,2)),VALUE(RIGHT(B79,2))))) -> 45664 | N79: =MONTH(M79) -> 1 | O79: =PROPER(TRIM(H79)) -> Jaipur | P79: =IFERROR(VLOOKUP(O79,city_map!$A$2:$B$6,2,FALSE()),O79) -> Jaipur | Q79: =IF(ISNUMBER(F79),F79,VALUE(SUBSTITUTE(SUBSTITUTE(F79,"₹",""),",",""))) -> 3358 | R79: =IF(E79=99,1,E79) -> 3 | S79: =IF(G79="",0,G79) -> 0.2 | T79: =IF(I79="","Unknown",IF(I79="upi","UPI",I79)) -> UPI | U79: =IF(L79="Yes","Y",IF(L79="No","N",L79)) -> N | V79: =ROUND(R79*Q79*(1-S79),2) -> 8059.2 | W79: =_xlfn.XLOOKUP(D79,products!$A$2:$A$61,products!$C$2:$C$61,"Not found") -> Home
A80: O10079 | B80: 2025-01-07 | C80: C0502 | D80: P015 | E80: 1 | F80: 2860 | G80: 0 | H80: bengaluru | I80: Credit Card | J80: 4 | K80: 3 | L80: N | M80: =IF(ISNUMBER(B80),B80,IF(MID(B80,3,1)="-",DATE(VALUE(RIGHT(B80,4)),VALUE(MID(B80,4,2)),VALUE(LEFT(B80,2))),DATE(VALUE(LEFT(B80,4)),VALUE(MID(B80,6,2)),VALUE(RIGHT(B80,2))))) -> 45664 | N80: =MONTH(M80) -> 1 | O80: =PROPER(TRIM(H80)) -> Bengaluru | P80: =IFERROR(VLOOKUP(O80,city_map!$A$2:$B$6,2,FALSE()),O80) -> Bengaluru | Q80: =IF(ISNUMBER(F80),F80,VALUE(SUBSTITUTE(SUBSTITUTE(F80,"₹",""),",",""))) -> 2860 | R80: =IF(E80=99,1,E80) -> 1 | S80: =IF(G80="",0,G80) -> 0 | T80: =IF(I80="","Unknown",IF(I80="upi","UPI",I80)) -> Credit Card | U80: =IF(L80="Yes","Y",IF(L80="No","N",L80)) -> N | V80: =ROUND(R80*Q80*(1-S80),2) -> 2860 | W80: =_xlfn.XLOOKUP(D80,products!$A$2:$A$61,products!$C$2:$C$61,"Not found") -> Fashion
A81: O10080 | B81: 2025-01-08 | C81: C0325 | D81: P060 | E81: 4 | F81: 413 | G81: 0.1 | H81: Hyderabad | I81: UPI | J81: 4 | K81: 3 | L81: N | M81: =IF(ISNUMBER(B81),B81,IF(MID(B81,3,1)="-",DATE(VALUE(RIGHT(B81,4)),VALUE(MID(B81,4,2)),VALUE(LEFT(B81,2))),DATE(VALUE(LEFT(B81,4)),VALUE(MID(B81,6,2)),VALUE(RIGHT(B81,2))))) -> 45665 | N81: =MONTH(M81) -> 1 | O81: =PROPER(TRIM(H81)) -> Hyderabad | P81: =IFERROR(VLOOKUP(O81,city_map!$A$2:$B$6,2,FALSE()),O81) -> Hyderabad | Q81: =IF(ISNUMBER(F81),F81,VALUE(SUBSTITUTE(SUBSTITUTE(F81,"₹",""),",",""))) -> 413 | R81: =IF(E81=99,1,E81) -> 4 | S81: =IF(G81="",0,G81) -> 0.1 | T81: =IF(I81="","Unknown",IF(I81="upi","UPI",I81)) -> UPI | U81: =IF(L81="Yes","Y",IF(L81="No","N",L81)) -> N | V81: =ROUND(R81*Q81*(1-S81),2) -> 1486.8 | W81: =_xlfn.XLOOKUP(D81,products!$A$2:$A$61,products!$C$2:$C$61,"Not found") -> Beauty
A82: O10081 | B82: 2025-01-08 | C82: C0627 | D82: P008 | E82: 1 | F82: 394 | G82: 0 | H82: Delhi | I82: UPI | J82: 4 | K82: 3 | L82: N | M82: =IF(ISNUMBER(B82),B82,IF(MID(B82,3,1)="-",DATE(VALUE(RIGHT(B82,4)),VALUE(MID(B82,4,2)),VALUE(LEFT(B82,2))),DATE(VALUE(LEFT(B82,4)),VALUE(MID(B82,6,2)),VALUE(RIGHT(B82,2))))) -> 45665 | N82: =MONTH(M82) -> 1 | O82: =PROPER(TRIM(H82)) -> Delhi | P82: =IFERROR(VLOOKUP(O82,city_map!$A$2:$B$6,2,FALSE()),O82) -> Delhi | Q82: =IF(ISNUMBER(F82),F82,VALUE(SUBSTITUTE(SUBSTITUTE(F82,"₹",""),",",""))) -> 394 | R82: =IF(E82=99,1,E82) -> 1 | S82: =IF(G82="",0,G82) -> 0 | T82: =IF(I82="","Unknown",IF(I82="upi","UPI",I82)) -> UPI | U82: =IF(L82="Yes","Y",IF(L82="No","N",L82)) -> N | V82: =ROUND(R82*Q82*(1-S82),2) -> 394 | W82: =_xlfn.XLOOKUP(D82,products!$A$2:$A$61,products!$C$2:$C$61,"Not found") -> Electronics
A83: O10082 | B83: 2025-01-08 | C83: C0587 | D83: P018 | E83: 2 | F83: 2597 | G83: 0.15 | H83: Delhi | I83: COD | J83: 3 | K83: 3 | L83: Y | M83: =IF(ISNUMBER(B83),B83,IF(MID(B83,3,1)="-",DATE(VALUE(RIGHT(B83,4)),VALUE(MID(B83,4,2)),VALUE(LEFT(B83,2))),DATE(VALUE(LEFT(B83,4)),VALUE(MID(B83,6,2)),VALUE(RIGHT(B83,2))))) -> 45665 | N83: =MONTH(M83) -> 1 | O83: =PROPER(TRIM(H83)) -> Delhi | P83: =IFERROR(VLOOKUP(O83,city_map!$A$2:$B$6,2,FALSE()),O83) -> Delhi | Q83: =IF(ISNUMBER(F83),F83,VALUE(SUBSTITUTE(SUBSTITUTE(F83,"₹",""),",",""))) -> 2597 | R83: =IF(E83=99,1,E83) -> 2 | S83: =IF(G83="",0,G83) -> 0.15 | T83: =IF(I83="","Unknown",IF(I83="upi","UPI",I83)) -> COD | U83: =IF(L83="Yes","Y",IF(L83="No","N",L83)) -> Y | V83: =ROUND(R83*Q83*(1-S83),2) -> 4414.9 | W83: =_xlfn.XLOOKUP(D83,products!$A$2:$A$61,products!$C$2:$C$61,"Not found") -> Fashion
A84: O10083 | B84: 2025-01-08 | C84: C0527 | D84: P011 | E84: 1 | F84: 1232 | G84: 0 | H84: Pune | I84: Credit Card | J84: 7 | L84: Y | M84: =IF(ISNUMBER(B84),B84,IF(MID(B84,3,1)="-",DATE(VALUE(RIGHT(B84,4)),VALUE(MID(B84,4,2)),VALUE(LEFT(B84,2))),DATE(VALUE(LEFT(B84,4)),VALUE(MID(B84,6,2)),VALUE(RIGHT(B84,2))))) -> 45665 | N84: =MONTH(M84) -> 1 | O84: =PROPER(TRIM(H84)) -> Pune | P84: =IFERROR(VLOOKUP(O84,city_map!$A$2:$B$6,2,FALSE()),O84) -> Pune | Q84: =IF(ISNUMBER(F84),F84,VALUE(SUBSTITUTE(SUBSTITUTE(F84,"₹",""),",",""))) -> 1232 | R84: =IF(E84=99,1,E84) -> 1 | S84: =IF(G84="",0,G84) -> 0 | T84: =IF(I84="","Unknown",IF(I84="upi","UPI",I84)) -> Credit Card | U84: =IF(L84="Yes","Y",IF(L84="No","N",L84)) -> Y | V84: =ROUND(R84*Q84*(1-S84),2) -> 1232 | W84: =_xlfn.XLOOKUP(D84,products!$A$2:$A$61,products!$C$2:$C$61,"Not found") -> Electronics
A85: O10084 | B85: 2025-01-08 | C85: C0570 | D85: P040 | E85: 1 | F85: 355 | G85: 0.05 | H85: Chennai | I85: UPI | J85: 6 | K85: 4 | L85: N | M85: =IF(ISNUMBER(B85),B85,IF(MID(B85,3,1)="-",DATE(VALUE(RIGHT(B85,4)),VALUE(MID(B85,4,2)),VALUE(LEFT(B85,2))),DATE(VALUE(LEFT(B85,4)),VALUE(MID(B85,6,2)),VALUE(RIGHT(B85,2))))) -> 45665 | N85: =MONTH(M85) -> 1 | O85: =PROPER(TRIM(H85)) -> Chennai | P85: =IFERROR(VLOOKUP(O85,city_map!$A$2:$B$6,2,FALSE()),O85) -> Chennai | Q85: =IF(ISNUMBER(F85),F85,VALUE(SUBSTITUTE(SUBSTITUTE(F85,"₹",""),",",""))) -> 355 | R85: =IF(E85=99,1,E85) -> 1 | S85: =IF(G85="",0,G85) -> 0.05 | T85: =IF(I85="","Unknown",IF(I85="upi","UPI",I85)) -> UPI | U85: =IF(L85="Yes","Y",IF(L85="No","N",L85)) -> N | V85: =ROUND(R85*Q85*(1-S85),2) -> 337.25 | W85: =_xlfn.XLOOKUP(D85,products!$A$2:$A$61,products!$C$2:$C$61,"Not found") -> Books
A86: O10085 | B86: 2025-01-08 | C86: C0724 | D86: P005 | E86: 1 | F86: 916 | G86: 0.05 | H86: Chennai | I86: Debit Card | J86: 3 | K86: 5 | L86: N | M86: =IF(ISNUMBER(B86),B86,IF(MID(B86,3,1)="-",DATE(VALUE(RIGHT(B86,4)),VALUE(MID(B86,4,2)),VALUE(LEFT(B86,2))),DATE(VALUE(LEFT(B86,4)),VALUE(MID(B86,6,2)),VALUE(RIGHT(B86,2))))) -> 45665 | N86: =MONTH(M86) -> 1 | O86: =PROPER(TRIM(H86)) -> Chennai | P86: =IFERROR(VLOOKUP(O86,city_map!$A$2:$B$6,2,FALSE()),O86) -> Chennai | Q86: =IF(ISNUMBER(F86),F86,VALUE(SUBSTITUTE(SUBSTITUTE(F86,"₹",""),",",""))) -> 916 | R86: =IF(E86=99,1,E86) -> 1 | S86: =IF(G86="",0,G86) -> 0.05 | T86: =IF(I86="","Unknown",IF(I86="upi","UPI",I86)) -> Debit Card | U86: =IF(L86="Yes","Y",IF(L86="No","N",L86)) -> N | V86: =ROUND(R86*Q86*(1-S86),2) -> 870.2 | W86: =_xlfn.XLOOKUP(D86,products!$A$2:$A$61,products!$C$2:$C$61,"Not found") -> Electronics
A87: O10086 | B87: 2025-01-08 | C87: C0738 | D87: P020 | E87: 2 | F87: 2360 | G87: 0 | H87: Pune | I87: UPI | J87: 7 | K87: 3 | L87: N | M87: =IF(ISNUMBER(B87),B87,IF(MID(B87,3,1)="-",DATE(VALUE(RIGHT(B87,4)),VALUE(MID(B87,4,2)),VALUE(LEFT(B87,2))),DATE(VALUE(LEFT(B87,4)),VALUE(MID(B87,6,2)),VALUE(RIGHT(B87,2))))) -> 45665 | N87: =MONTH(M87) -> 1 | O87: =PROPER(TRIM(H87)) -> Pune | P87: =IFERROR(VLOOKUP(O87,city_map!$A$2:$B$6,2,FALSE()),O87) -> Pune | Q87: =IF(ISNUMBER(F87),F87,VALUE(SUBSTITUTE(SUBSTITUTE(F87,"₹",""),",",""))) -> 2360 | R87: =IF(E87=99,1,E87) -> 2 | S87: =IF(G87="",0,G87) -> 0 | T87: =IF(I87="","Unknown",IF(I87="upi","UPI",I87)) -> UPI | U87: =IF(L87="Yes","Y",IF(L87="No","N",L87)) -> N | V87: =ROUND(R87*Q87*(1-S87),2) -> 4720 | W87: =_xlfn.XLOOKUP(D87,products!$A$2:$A$61,products!$C$2:$C$61,"Not found") -> Fashion
A88: O10087 | B88: 2025-01-08 | C88: C0238 | D88: P021 | E88: 3 | F88: 676 | G88: 0.15 | H88: Chennai | I88: UPI | J88: 3 | K88: 5 | L88: N | M88: =IF(ISNUMBER(B88),B88,IF(MID(B88,3,1)="-",DATE(VALUE(RIGHT(B88,4)),VALUE(MID(B88,4,2)),VALUE(LEFT(B88,2))),DATE(VALUE(LEFT(B88,4)),VALUE(MID(B88,6,2)),VALUE(RIGHT(B88,2))))) -> 45665 | N88: =MONTH(M88) -> 1 | O88: =PROPER(TRIM(H88)) -> Chennai | P88: =IFERROR(VLOOKUP(O88,city_map!$A$2:$B$6,2,FALSE()),O88) -> Chennai | Q88: =IF(ISNUMBER(F88),F88,VALUE(SUBSTITUTE(SUBSTITUTE(F88,"₹",""),",",""))) -> 676 | R88: =IF(E88=99,1,E88) -> 3 | S88: =IF(G88="",0,G88) -> 0.15 | T88: =IF(I88="","Unknown",IF(I88="upi","UPI",I88)) -> UPI | U88: =IF(L88="Yes","Y",IF(L88="No","N",L88)) -> N | V88: =ROUND(R88*Q88*(1-S88),2) -> 1723.8 | W88: =_xlfn.XLOOKUP(D88,products!$A$2:$A$61,products!$C$2:$C$61,"Not found") -> Fashion
A89: O10088 | B89: 2025-01-08 | C89: C0207 | D89: P036 | E89: 2 | F89: 2592 | G89: 0.2 | H89: Delhi | I89: COD | J89: 4 | K89: 3 | L89: N | M89: =IF(ISNUMBER(B89),B89,IF(MID(B89,3,1)="-",DATE(VALUE(RIGHT(B89,4)),VALUE(MID(B89,4,2)),VALUE(LEFT(B89,2))),DATE(VALUE(LEFT(B89,4)),VALUE(MID(B89,6,2)),VALUE(RIGHT(B89,2))))) -> 45665 | N89: =MONTH(M89) -> 1 | O89: =PROPER(TRIM(H89)) -> Delhi | P89: =IFERROR(VLOOKUP(O89,city_map!$A$2:$B$6,2,FALSE()),O89) -> Delhi | Q89: =IF(ISNUMBER(F89),F89,VALUE(SUBSTITUTE(SUBSTITUTE(F89,"₹",""),",",""))) -> 2592 | R89: =IF(E89=99,1,E89) -> 2 | S89: =IF(G89="",0,G89) -> 0.2 | T89: =IF(I89="","Unknown",IF(I89="upi","UPI",I89)) -> COD | U89: =IF(L89="Yes","Y",IF(L89="No","N",L89)) -> N | V89: =ROUND(R89*Q89*(1-S89),2) -> 4147.2 | W89: =_xlfn.XLOOKUP(D89,products!$A$2:$A$61,products!$C$2:$C$61,"Not found") -> Home
A90: O10089 | B90: 2025-01-09 | C90: C0227 | D90: P015 | E90: 1 | F90: 2943 | G90: 0 | H90: hyderabad | I90: COD | J90: 3 | K90: 4 | L90: N | M90: =IF(ISNUMBER(B90),B90,IF(MID(B90,3,1)="-",DATE(VALUE(RIGHT(B90,4)),VALUE(MID(B90,4,2)),VALUE(LEFT(B90,2))),DATE(VALUE(LEFT(B90,4)),VALUE(MID(B90,6,2)),VALUE(RIGHT(B90,2))))) -> 45666 | N90: =MONTH(M90) -> 1 | O90: =PROPER(TRIM(H90)) -> Hyderabad | P90: =IFERROR(VLOOKUP(O90,city_map!$A$2:$B$6,2,FALSE()),O90) -> Hyderabad | Q90: =IF(ISNUMBER(F90),F90,VALUE(SUBSTITUTE(SUBSTITUTE(F90,"₹",""),",",""))) -> 2943 | R90: =IF(E90=99,1,E90) -> 1 | S90: =IF(G90="",0,G90) -> 0 | T90: =IF(I90="","Unknown",IF(I90="upi","UPI",I90)) -> COD | U90: =IF(L90="Yes","Y",IF(L90="No","N",L90)) -> N | V90: =ROUND(R90*Q90*(1-S90),2) -> 2943 | W90: =_xlfn.XLOOKUP(D90,products!$A$2:$A$61,products!$C$2:$C$61,"Not found") -> Fashion
A91: O10090 | B91: 2025-01-09 | C91: C0312 | D91: P033 | E91: 1 | F91: 3442 | G91: 0 | H91: Mumbai | I91: UPI | J91: 5 | K91: 4 | L91: N | M91: =IF(ISNUMBER(B91),B91,IF(MID(B91,3,1)="-",DATE(VALUE(RIGHT(B91,4)),VALUE(MID(B91,4,2)),VALUE(LEFT(B91,2))),DATE(VALUE(LEFT(B91,4)),VALUE(MID(B91,6,2)),VALUE(RIGHT(B91,2))))) -> 45666 | N91: =MONTH(M91) -> 1 | O91: =PROPER(TRIM(H91)) -> Mumbai | P91: =IFERROR(VLOOKUP(O91,city_map!$A$2:$B$6,2,FALSE()),O91) -> Mumbai | Q91: =IF(ISNUMBER(F91),F91,VALUE(SUBSTITUTE(SUBSTITUTE(F91,"₹",""),",",""))) -> 3442 | R91: =IF(E91=99,1,E91) -> 1 | S91: =IF(G91="",0,G91) -> 0 | T91: =IF(I91="","Unknown",IF(I91="upi","UPI",I91)) -> UPI | U91: =IF(L91="Yes","Y",IF(L91="No","N",L91)) -> N | V91: =ROUND(R91*Q91*(1-S91),2) -> 3442 | W91: =_xlfn.XLOOKUP(D91,products!$A$2:$A$61,products!$C$2:$C$61,"Not found") -> Home
A92: O10091 | B92: 2025-01-09 | C92: C0574 | D92: P058 | E92: 3 | F92: 192 | G92: 0 | H92: Mumbai | I92: COD | J92: 3 | K92: 5 | L92: N | M92: =IF(ISNUMBER(B92),B92,IF(MID(B92,3,1)="-",DATE(VALUE(RIGHT(B92,4)),VALUE(MID(B92,4,2)),VALUE(LEFT(B92,2))),DATE(VALUE(LEFT(B92,4)),VALUE(MID(B92,6,2)),VALUE(RIGHT(B92,2))))) -> 45666 | N92: =MONTH(M92) -> 1 | O92: =PROPER(TRIM(H92)) -> Mumbai | P92: =IFERROR(VLOOKUP(O92,city_map!$A$2:$B$6,2,FALSE()),O92) -> Mumbai | Q92: =IF(ISNUMBER(F92),F92,VALUE(SUBSTITUTE(SUBSTITUTE(F92,"₹",""),",",""))) -> 192 | R92: =IF(E92=99,1,E92) -> 3 | S92: =IF(G92="",0,G92) -> 0 | T92: =IF(I92="","Unknown",IF(I92="upi","UPI",I92)) -> COD | U92: =IF(L92="Yes","Y",IF(L92="No","N",L92)) -> N | V92: =ROUND(R92*Q92*(1-S92),2) -> 576 | W92: =_xlfn.XLOOKUP(D92,products!$A$2:$A$61,products!$C$2:$C$61,"Not found") -> Beauty
A93: O10092 | B93: 2025-01-09 | C93: C0521 | D93: P037 | E93: 2 | F93: 501 | G93: 0 | H93: Mumbai | I93: Debit Card | J93: 2 | K93: 4 | L93: N | M93: =IF(ISNUMBER(B93),B93,IF(MID(B93,3,1)="-",DATE(VALUE(RIGHT(B93,4)),VALUE(MID(B93,4,2)),VALUE(LEFT(B93,2))),DATE(VALUE(LEFT(B93,4)),VALUE(MID(B93,6,2)),VALUE(RIGHT(B93,2))))) -> 45666 | N93: =MONTH(M93) -> 1 | O93: =PROPER(TRIM(H93)) -> Mumbai | P93: =IFERROR(VLOOKUP(O93,city_map!$A$2:$B$6,2,FALSE()),O93) -> Mumbai | Q93: =IF(ISNUMBER(F93),F93,VALUE(SUBSTITUTE(SUBSTITUTE(F93,"₹",""),",",""))) -> 501 | R93: =IF(E93=99,1,E93) -> 2 | S93: =IF(G93="",0,G93) -> 0 | T93: =IF(I93="","Unknown",IF(I93="upi","UPI",I93)) -> Debit Card | U93: =IF(L93="Yes","Y",IF(L93="No","N",L93)) -> N | V93: =ROUND(R93*Q93*(1-S93),2) -> 1002 | W93: =_xlfn.XLOOKUP(D93,products!$A$2:$A$61,products!$C$2:$C$61,"Not found") -> Books
A94: O10093 | B94: 2025-01-09 | C94: C0056 | D94: P056 | E94: 3 | F94: 430 | G94: 0.2 | H94: Bengaluru | I94: Net Banking | J94: 4 | K94: 2 | L94: Y | M94: =IF(ISNUMBER(B94),B94,IF(MID(B94,3,1)="-",DATE(VALUE(RIGHT(B94,4)),VALUE(MID(B94,4,2)),VALUE(LEFT(B94,2))),DATE(VALUE(LEFT(B94,4)),VALUE(MID(B94,6,2)),VALUE(RIGHT(B94,2))))) -> 45666 | N94: =MONTH(M94) -> 1 | O94: =PROPER(TRIM(H94)) -> Bengaluru | P94: =IFERROR(VLOOKUP(O94,city_map!$A$2:$B$6,2,FALSE()),O94) -> Bengaluru | Q94: =IF(ISNUMBER(F94),F94,VALUE(SUBSTITUTE(SUBSTITUTE(F94,"₹",""),",",""))) -> 430 | R94: =IF(E94=99,1,E94) -> 3 | S94: =IF(G94="",0,G94) -> 0.2 | T94: =IF(I94="","Unknown",IF(I94="upi","UPI",I94)) -> Net Banking | U94: =IF(L94="Yes","Y",IF(L94="No","N",L94)) -> Y | V94: =ROUND(R94*Q94*(1-S94),2) -> 1032 | W94: =_xlfn.XLOOKUP(D94,products!$A$2:$A$61,products!$C$2:$C$61,"Not found") -> Beauty
A95: O10094 | B95: 2025-01-09 | C95: C0486 | D95: P039 | E95: 2 | F95: 405 | G95: 0.1 | H95: Chennai | I95: Net Banking | J95: 4 | K95: 4 | L95: N | M95: =IF(ISNUMBER(B95),B95,IF(MID(B95,3,1)="-",DATE(VALUE(RIGHT(B95,4)),VALUE(MID(B95,4,2)),VALUE(LEFT(B95,2))),DATE(VALUE(LEFT(B95,4)),VALUE(MID(B95,6,2)),VALUE(RIGHT(B95,2))))) -> 45666 | N95: =MONTH(M95) -> 1 | O95: =PROPER(TRIM(H95)) -> Chennai | P95: =IFERROR(VLOOKUP(O95,city_map!$A$2:$B$6,2,FALSE()),O95) -> Chennai | Q95: =IF(ISNUMBER(F95),F95,VALUE(SUBSTITUTE(SUBSTITUTE(F95,"₹",""),",",""))) -> 405 | R95: =IF(E95=99,1,E95) -> 2 | S95: =IF(G95="",0,G95) -> 0.1 | T95: =IF(I95="","Unknown",IF(I95="upi","UPI",I95)) -> Net Banking | U95: =IF(L95="Yes","Y",IF(L95="No","N",L95)) -> N | V95: =ROUND(R95*Q95*(1-S95),2) -> 729 | W95: =_xlfn.XLOOKUP(D95,products!$A$2:$A$61,products!$C$2:$C$61,"Not found") -> Books
A96: O10095 | B96: 2025-01-09 | C96: C0512 | D96: P060 | E96: 2 | F96: 410 | G96: 0 | H96: Lucknow | I96: UPI | J96: 8 | K96: 4 | L96: N | M96: =IF(ISNUMBER(B96),B96,IF(MID(B96,3,1)="-",DATE(VALUE(RIGHT(B96,4)),VALUE(MID(B96,4,2)),VALUE(LEFT(B96,2))),DATE(VALUE(LEFT(B96,4)),VALUE(MID(B96,6,2)),VALUE(RIGHT(B96,2))))) -> 45666 | N96: =MONTH(M96) -> 1 | O96: =PROPER(TRIM(H96)) -> Lucknow | P96: =IFERROR(VLOOKUP(O96,city_map!$A$2:$B$6,2,FALSE()),O96) -> Lucknow | Q96: =IF(ISNUMBER(F96),F96,VALUE(SUBSTITUTE(SUBSTITUTE(F96,"₹",""),",",""))) -> 410 | R96: =IF(E96=99,1,E96) -> 2 | S96: =IF(G96="",0,G96) -> 0 | T96: =IF(I96="","Unknown",IF(I96="upi","UPI",I96)) -> UPI | U96: =IF(L96="Yes","Y",IF(L96="No","N",L96)) -> N | V96: =ROUND(R96*Q96*(1-S96),2) -> 820 | W96: =_xlfn.XLOOKUP(D96,products!$A$2:$A$61,products!$C$2:$C$61,"Not found") -> Beauty
... A103: O10102 | B103: 2025-01-10 | C103: C0384 | D103: P015 | E103: 1 | F103: 2930 | G103: 0.3 | H103: Lucknow | I103: COD | J103: 6 | K103: 4 | L103: N | M103: =IF(ISNUMBER(B103),B103,IF(MID(B103,3,1)="-",DATE(VALUE(RIGHT(B103,4)),VALUE(MID(B103,4,2)),VALUE(LEFT(B103,2))),DATE(VALUE(LEFT(B103,4)),VALUE(MID(B103,6,2)),VALUE(RIGHT(B103,2))))) -> 45667 | N103: =MONTH(M103) -> 1 | O103: =PROPER(TRIM(H103)) -> Lucknow | P103: =IFERROR(VLOOKUP(O103,city_map!$A$2:$B$6,2,FALSE()),O103) -> Lucknow | Q103: =IF(ISNUMBER(F103),F103,VALUE(SUBSTITUTE(SUBSTITUTE(F103,"₹",""),",",""))) -> 2930 | R103: =IF(E103=99,1,E103) -> 1 | S103: =IF(G103="",0,G103) -> 0.3 | T103: =IF(I103="","Unknown",IF(I103="upi","UPI",I103)) -> COD | U103: =IF(L103="Yes","Y",IF(L103="No","N",L103)) -> N | V103: =ROUND(R103*Q103*(1-S103),2) -> 2051 | W103: =_xlfn.XLOOKUP(D103,products!$A$2:$A$61,products!$C$2:$C$61,"Not found") -> Fashion
A104: O10103 | B104: 2025-01-10 | C104: C0104 | D104: P042 | E104: 1 | F104: 961 | G104: 0.1 | H104: Delhi | J104: 5 | K104: 4 | L104: N | M104: =IF(ISNUMBER(B104),B104,IF(MID(B104,3,1)="-",DATE(VALUE(RIGHT(B104,4)),VALUE(MID(B104,4,2)),VALUE(LEFT(B104,2))),DATE(VALUE(LEFT(B104,4)),VALUE(MID(B104,6,2)),VALUE(RIGHT(B104,2))))) -> 45667 | N104: =MONTH(M104) -> 1 | O104: =PROPER(TRIM(H104)) -> Delhi | P104: =IFERROR(VLOOKUP(O104,city_map!$A$2:$B$6,2,FALSE()),O104) -> Delhi | Q104: =IF(ISNUMBER(F104),F104,VALUE(SUBSTITUTE(SUBSTITUTE(F104,"₹",""),",",""))) -> 961 | R104: =IF(E104=99,1,E104) -> 1 | S104: =IF(G104="",0,G104) -> 0.1 | T104: =IF(I104="","Unknown",IF(I104="upi","UPI",I104)) -> Unknown | U104: =IF(L104="Yes","Y",IF(L104="No","N",L104)) -> N | V104: =ROUND(R104*Q104*(1-S104),2) -> 864.9 | W104: =_xlfn.XLOOKUP(D104,products!$A$2:$A$61,products!$C$2:$C$61,"Not found") -> Books
A105: O10104 | B105: 2025-01-10 | C105: C0397 | D105: P033 | E105: 1 | F105: 3444 | G105: 0 | H105: Hyderabad | I105: UPI | J105: 7 | K105: 4 | L105: N | M105: =IF(ISNUMBER(B105),B105,IF(MID(B105,3,1)="-",DATE(VALUE(RIGHT(B105,4)),VALUE(MID(B105,4,2)),VALUE(LEFT(B105,2))),DATE(VALUE(LEFT(B105,4)),VALUE(MID(B105,6,2)),VALUE(RIGHT(B105,2))))) -> 45667 | N105: =MONTH(M105) -> 1 | O105: =PROPER(TRIM(H105)) -> Hyderabad | P105: =IFERROR(VLOOKUP(O105,city_map!$A$2:$B$6,2,FALSE()),O105) -> Hyderabad | Q105: =IF(ISNUMBER(F105),F105,VALUE(SUBSTITUTE(SUBSTITUTE(F105,"₹",""),",",""))) -> 3444 | R105: =IF(E105=99,1,E105) -> 1 | S105: =IF(G105="",0,G105) -> 0 | T105: =IF(I105="","Unknown",IF(I105="upi","UPI",I105)) -> UPI | U105: =IF(L105="Yes","Y",IF(L105="No","N",L105)) -> N | V105: =ROUND(R105*Q105*(1-S105),2) -> 3444 | W105: =_xlfn.XLOOKUP(D105,products!$A$2:$A$61,products!$C$2:$C$61,"Not found") -> Home
A106: O10105 | B106: 2025-01-10 | C106: C0138 | D106: P012 | E106: 1 | F106: 2111 | G106: 0 | H106: Delhi | I106: Credit Card | J106: 4 | K106: 5 | L106: N | M106: =IF(ISNUMBER(B106),B106,IF(MID(B106,3,1)="-",DATE(VALUE(RIGHT(B106,4)),VALUE(MID(B106,4,2)),VALUE(LEFT(B106,2))),DATE(VALUE(LEFT(B106,4)),VALUE(MID(B106,6,2)),VALUE(RIGHT(B106,2))))) -> 45667 | N106: =MONTH(M106) -> 1 | O106: =PROPER(TRIM(H106)) -> Delhi | P106: =IFERROR(VLOOKUP(O106,city_map!$A$2:$B$6,2,FALSE()),O106) -> Delhi | Q106: =IF(ISNUMBER(F106),F106,VALUE(SUBSTITUTE(SUBSTITUTE(F106,"₹",""),",",""))) -> 2111 | R106: =IF(E106=99,1,E106) -> 1 | S106: =IF(G106="",0,G106) -> 0 | T106: =IF(I106="","Unknown",IF(I106="upi","UPI",I106)) -> Credit Card | U106: =IF(L106="Yes","Y",IF(L106="No","N",L106)) -> N | V106: =ROUND(R106*Q106*(1-S106),2) -> 2111 | W106: =_xlfn.XLOOKUP(D106,products!$A$2:$A$61,products!$C$2:$C$61,"Not found") -> Electronics
A107: O10106 | B107: 2025-01-10 | C107: C0117 | D107: P028 | E107: 2 | F107: 1076 | G107: 0.3 | H107: Kolkata | I107: UPI | J107: 4 | K107: 5 | L107: N | M107: =IF(ISNUMBER(B107),B107,IF(MID(B107,3,1)="-",DATE(VALUE(RIGHT(B107,4)),VALUE(MID(B107,4,2)),VALUE(LEFT(B107,2))),DATE(VALUE(LEFT(B107,4)),VALUE(MID(B107,6,2)),VALUE(RIGHT(B107,2))))) -> 45667 | N107: =MONTH(M107) -> 1 | O107: =PROPER(TRIM(H107)) -> Kolkata | P107: =IFERROR(VLOOKUP(O107,city_map!$A$2:$B$6,2,FALSE()),O107) -> Kolkata | Q107: =IF(ISNUMBER(F107),F107,VALUE(SUBSTITUTE(SUBSTITUTE(F107,"₹",""),",",""))) -> 1076 | R107: =IF(E107=99,1,E107) -> 2 | S107: =IF(G107="",0,G107) -> 0.3 | T107: =IF(I107="","Unknown",IF(I107="upi","UPI",I107)) -> UPI | U107: =IF(L107="Yes","Y",IF(L107="No","N",L107)) -> N | V107: =ROUND(R107*Q107*(1-S107),2) -> 1506.4 | W107: =_xlfn.XLOOKUP(D107,products!$A$2:$A$61,products!$C$2:$C$61,"Not found") -> Home
A108: O10107 | B108: 2025-01-10 | C108: C0327 | D108: P020 | E108: 1 | F108: 2345 | G108: 0.05 | H108: Mumbai | I108: Credit Card | J108: 3 | K108: 4 | L108: N | M108: =IF(ISNUMBER(B108),B108,IF(MID(B108,3,1)="-",DATE(VALUE(RIGHT(B108,4)),VALUE(MID(B108,4,2)),VALUE(LEFT(B108,2))),DATE(VALUE(LEFT(B108,4)),VALUE(MID(B108,6,2)),VALUE(RIGHT(B108,2))))) -> 45667 | N108: =MONTH(M108) -> 1 | O108: =PROPER(TRIM(H108)) -> Mumbai | P108: =IFERROR(VLOOKUP(O108,city_map!$A$2:$B$6,2,FALSE()),O108) -> Mumbai | Q108: =IF(ISNUMBER(F108),F108,VALUE(SUBSTITUTE(SUBSTITUTE(F108,"₹",""),",",""))) -> 2345 | R108: =IF(E108=99,1,E108) -> 1 | S108: =IF(G108="",0,G108) -> 0.05 | T108: =IF(I108="","Unknown",IF(I108="upi","UPI",I108)) -> Credit Card | U108: =IF(L108="Yes","Y",IF(L108="No","N",L108)) -> N | V108: =ROUND(R108*Q108*(1-S108),2) -> 2227.75 | W108: =_xlfn.XLOOKUP(D108,products!$A$2:$A$61,products!$C$2:$C$61,"Not found") -> Fashion
A109: O10108 | B109: 2025-01-10 | C109: C0268 | D109: P038 | E109: 1 | F109: 879 | G109: 0 | H109: Bengaluru | I109: Credit Card | J109: 2 | K109: 4 | L109: N | M109: =IF(ISNUMBER(B109),B109,IF(MID(B109,3,1)="-",DATE(VALUE(RIGHT(B109,4)),VALUE(MID(B109,4,2)),VALUE(LEFT(B109,2))),DATE(VALUE(LEFT(B109,4)),VALUE(MID(B109,6,2)),VALUE(RIGHT(B109,2))))) -> 45667 | N109: =MONTH(M109) -> 1 | O109: =PROPER(TRIM(H109)) -> Bengaluru | P109: =IFERROR(VLOOKUP(O109,city_map!$A$2:$B$6,2,FALSE()),O109) -> Bengaluru | Q109: =IF(ISNUMBER(F109),F109,VALUE(SUBSTITUTE(SUBSTITUTE(F109,"₹",""),",",""))) -> 879 | R109: =IF(E109=99,1,E109) -> 1 | S109: =IF(G109="",0,G109) -> 0 | T109: =IF(I109="","Unknown",IF(I109="upi","UPI",I109)) -> Credit Card | U109: =IF(L109="Yes","Y",IF(L109="No","N",L109)) -> N | V109: =ROUND(R109*Q109*(1-S109),2) -> 879 | W109: =_xlfn.XLOOKUP(D109,products!$A$2:$A$61,products!$C$2:$C$61,"Not found") -> Books
A110: O10109 | B110: 2025-01-10 | C110: C0475 | D110: P020 | E110: 1 | F110: 2263 | G110: 0 | H110: Mumbai | I110: UPI | J110: 3 | K110: 4 | L110: Y | M110: =IF(ISNUMBER(B110),B110,IF(MID(B110,3,1)="-",DATE(VALUE(RIGHT(B110,4)),VALUE(MID(B110,4,2)),VALUE(LEFT(B110,2))),DATE(VALUE(LEFT(B110,4)),VALUE(MID(B110,6,2)),VALUE(RIGHT(B110,2))))) -> 45667 | N110: =MONTH(M110) -> 1 | O110: =PROPER(TRIM(H110)) -> Mumbai | P110: =IFERROR(VLOOKUP(O110,city_map!$A$2:$B$6,2,FALSE()),O110) -> Mumbai | Q110: =IF(ISNUMBER(F110),F110,VALUE(SUBSTITUTE(SUBSTITUTE(F110,"₹",""),",",""))) -> 2263 | R110: =IF(E110=99,1,E110) -> 1 | S110: =IF(G110="",0,G110) -> 0 | T110: =IF(I110="","Unknown",IF(I110="upi","UPI",I110)) -> UPI | U110: =IF(L110="Yes","Y",IF(L110="No","N",L110)) -> Y | V110: =ROUND(R110*Q110*(1-S110),2) -> 2263 | W110: =_xlfn.XLOOKUP(D110,products!$A$2:$A$61,products!$C$2:$C$61,"Not found") -> Fashion
A111: O10110 | B111: 2025-01-10 | C111: C0160 | D111: P018 | E111: 4 | F111: ₹2,563 | G111: 0.15 | H111: Bengaluru | I111: UPI | J111: 6 | K111: 3 | L111: Y | M111: =IF(ISNUMBER(B111),B111,IF(MID(B111,3,1)="-",DATE(VALUE(RIGHT(B111,4)),VALUE(MID(B111,4,2)),VALUE(LEFT(B111,2))),DATE(VALUE(LEFT(B111,4)),VALUE(MID(B111,6,2)),VALUE(RIGHT(B111,2))))) -> 45667 | N111: =MONTH(M111) -> 1 | O111: =PROPER(TRIM(H111)) -> Bengaluru | P111: =IFERROR(VLOOKUP(O111,city_map!$A$2:$B$6,2,FALSE()),O111) -> Bengaluru | Q111: =IF(ISNUMBER(F111),F111,VALUE(SUBSTITUTE(SUBSTITUTE(F111,"₹",""),",",""))) -> 2563 | R111: =IF(E111=99,1,E111) -> 4 | S111: =IF(G111="",0,G111) -> 0.15 | T111: =IF(I111="","Unknown",IF(I111="upi","UPI",I111)) -> UPI | U111: =IF(L111="Yes","Y",IF(L111="No","N",L111)) -> Y | V111: =ROUND(R111*Q111*(1-S111),2) -> 8714.2 | W111: =_xlfn.XLOOKUP(D111,products!$A$2:$A$61,products!$C$2:$C$61,"Not found") -> Fashion
A112: O10111 | B112: 10-01-2025 | C112: C0010 | D112: P012 | E112: 1 | F112: 2235 | G112: 0.2 | H112: Mumbai | I112: COD | J112: 4 | K112: 4 | L112: N | M112: =IF(ISNUMBER(B112),B112,IF(MID(B112,3,1)="-",DATE(VALUE(RIGHT(B112,4)),VALUE(MID(B112,4,2)),VALUE(LEFT(B112,2))),DATE(VALUE(LEFT(B112,4)),VALUE(MID(B112,6,2)),VALUE(RIGHT(B112,2))))) -> 45667 | N112: =MONTH(M112) -> 1 | O112: =PROPER(TRIM(H112)) -> Mumbai | P112: =IFERROR(VLOOKUP(O112,city_map!$A$2:$B$6,2,FALSE()),O112) -> Mumbai | Q112: =IF(ISNUMBER(F112),F112,VALUE(SUBSTITUTE(SUBSTITUTE(F112,"₹",""),",",""))) -> 2235 | R112: =IF(E112=99,1,E112) -> 1 | S112: =IF(G112="",0,G112) -> 0.2 | T112: =IF(I112="","Unknown",IF(I112="upi","UPI",I112)) -> COD | U112: =IF(L112="Yes","Y",IF(L112="No","N",L112)) -> N | V112: =ROUND(R112*Q112*(1-S112),2) -> 1788 | W112: =_xlfn.XLOOKUP(D112,products!$A$2:$A$61,products!$C$2:$C$61,"Not found") -> Electronics
A113: O10112 | B113: 2025-01-10 | C113: C0143 | D113: P054 | E113: 2 | F113: ₹1,540 | G113: 0.05 | H113: DELHI | I113: Net Banking | J113: 2 | K113: 3 | L113: N | M113: =IF(ISNUMBER(B113),B113,IF(MID(B113,3,1)="-",DATE(VALUE(RIGHT(B113,4)),VALUE(MID(B113,4,2)),VALUE(LEFT(B113,2))),DATE(VALUE(LEFT(B113,4)),VALUE(MID(B113,6,2)),VALUE(RIGHT(B113,2))))) -> 45667 | N113: =MONTH(M113) -> 1 | O113: =PROPER(TRIM(H113)) -> Delhi | P113: =IFERROR(VLOOKUP(O113,city_map!$A$2:$B$6,2,FALSE()),O113) -> Delhi | Q113: =IF(ISNUMBER(F113),F113,VALUE(SUBSTITUTE(SUBSTITUTE(F113,"₹",""),",",""))) -> 1540 | R113: =IF(E113=99,1,E113) -> 2 | S113: =IF(G113="",0,G113) -> 0.05 | T113: =IF(I113="","Unknown",IF(I113="upi","UPI",I113)) -> Net Banking | U113: =IF(L113="Yes","Y",IF(L113="No","N",L113)) -> N | V113: =ROUND(R113*Q113*(1-S113),2) -> 2926 | W113: =_xlfn.XLOOKUP(D113,products!$A$2:$A$61,products!$C$2:$C$61,"Not found") -> Beauty
A114: O10113 | B114: 2025-01-11 | C114: C0032 | D114: P057 | E114: 1 | F114: 351 | G114: 0 | H114: Hyderabad | I114: Credit Card | J114: 2 | K114: 4 | L114: N | M114: =IF(ISNUMBER(B114),B114,IF(MID(B114,3,1)="-",DATE(VALUE(RIGHT(B114,4)),VALUE(MID(B114,4,2)),VALUE(LEFT(B114,2))),DATE(VALUE(LEFT(B114,4)),VALUE(MID(B114,6,2)),VALUE(RIGHT(B114,2))))) -> 45668 | N114: =MONTH(M114) -> 1 | O114: =PROPER(TRIM(H114)) -> Hyderabad | P114: =IFERROR(VLOOKUP(O114,city_map!$A$2:$B$6,2,FALSE()),O114) -> Hyderabad | Q114: =IF(ISNUMBER(F114),F114,VALUE(SUBSTITUTE(SUBSTITUTE(F114,"₹",""),",",""))) -> 351 | R114: =IF(E114=99,1,E114) -> 1 | S114: =IF(G114="",0,G114) -> 0 | T114: =IF(I114="","Unknown",IF(I114="upi","UPI",I114)) -> Credit Card | U114: =IF(L114="Yes","Y",IF(L114="No","N",L114)) -> N | V114: =ROUND(R114*Q114*(1-S114),2) -> 351 | W114: =_xlfn.XLOOKUP(D114,products!$A$2:$A$61,products!$C$2:$C$61,"Not found") -> Beauty
A115: O10114 | B115: 2025-01-11 | C115: C0640 | D115: P036 | E115: 3 | F115: 2451 | G115: 0.05 | H115: Ahmedabad | I115: UPI | J115: 3 | K115: 5 | L115: N | M115: =IF(ISNUMBER(B115),B115,IF(MID(B115,3,1)="-",DATE(VALUE(RIGHT(B115,4)),VALUE(MID(B115,4,2)),VALUE(LEFT(B115,2))),DATE(VALUE(LEFT(B115,4)),VALUE(MID(B115,6,2)),VALUE(RIGHT(B115,2))))) -> 45668 | N115: =MONTH(M115) -> 1 | O115: =PROPER(TRIM(H115)) -> Ahmedabad | P115: =IFERROR(VLOOKUP(O115,city_map!$A$2:$B$6,2,FALSE()),O115) -> Ahmedabad | Q115: =IF(ISNUMBER(F115),F115,VALUE(SUBSTITUTE(SUBSTITUTE(F115,"₹",""),",",""))) -> 2451 | R115: =IF(E115=99,1,E115) -> 3 | S115: =IF(G115="",0,G115) -> 0.05 | T115: =IF(I115="","Unknown",IF(I115="upi","UPI",I115)) -> UPI | U115: =IF(L115="Yes","Y",IF(L115="No","N",L115)) -> N | V115: =ROUND(R115*Q115*(1-S115),2) -> 6985.35 | W115: =_xlfn.XLOOKUP(D115,products!$A$2:$A$61,products!$C$2:$C$61,"Not found") -> Home
A116: O10115 | B116: 2025-01-11 | C116: C0270 | D116: P017 | E116: 1 | F116: 1340 | G116: 0.15 | H116: Bengaluru | I116: COD | J116: 3 | K116: 5 | L116: Y | M116: =IF(ISNUMBER(B116),B116,IF(MID(B116,3,1)="-",DATE(VALUE(RIGHT(B116,4)),VALUE(MID(B116,4,2)),VALUE(LEFT(B116,2))),DATE(VALUE(LEFT(B116,4)),VALUE(MID(B116,6,2)),VALUE(RIGHT(B116,2))))) -> 45668 | N116: =MONTH(M116) -> 1 | O116: =PROPER(TRIM(H116)) -> Bengaluru | P116: =IFERROR(VLOOKUP(O116,city_map!$A$2:$B$6,2,FALSE()),O116) -> Bengaluru | Q116: =IF(ISNUMBER(F116),F116,VALUE(SUBSTITUTE(SUBSTITUTE(F116,"₹",""),",",""))) -> 1340 | R116: =IF(E116=99,1,E116) -> 1 | S116: =IF(G116="",0,G116) -> 0.15 | T116: =IF(I116="","Unknown",IF(I116="upi","UPI",I116)) -> COD | U116: =IF(L116="Yes","Y",IF(L116="No","N",L116)) -> Y | V116: =ROUND(R116*Q116*(1-S116),2) -> 1139 | W116: =_xlfn.XLOOKUP(D116,products!$A$2:$A$61,products!$C$2:$C$61,"Not found") -> Fashion
A117: O10116 | B117: 2025-01-11 | C117: C0351 | D117: P014 | E117: 1 | F117: 1492 | G117: 0.05 | H117: Pune | I117: Credit Card | J117: 4 | K117: 5 | L117: N | M117: =IF(ISNUMBER(B117),B117,IF(MID(B117,3,1)="-",DATE(VALUE(RIGHT(B117,4)),VALUE(MID(B117,4,2)),VALUE(LEFT(B117,2))),DATE(VALUE(LEFT(B117,4)),VALUE(MID(B117,6,2)),VALUE(RIGHT(B117,2))))) -> 45668 | N117: =MONTH(M117) -> 1 | O117: =PROPER(TRIM(H117)) -> Pune | P117: =IFERROR(VLOOKUP(O117,city_map!$A$2:$B$6,2,FALSE()),O117) -> Pune | Q117: =IF(ISNUMBER(F117),F117,VALUE(SUBSTITUTE(SUBSTITUTE(F117,"₹",""),",",""))) -> 1492 | R117: =IF(E117=99,1,E117) -> 1 | S117: =IF(G117="",0,G117) -> 0.05 | T117: =IF(I117="","Unknown",IF(I117="upi","UPI",I117)) -> Credit Card | U117: =IF(L117="Yes","Y",IF(L117="No","N",L117)) -> N | V117: =ROUND(R117*Q117*(1-S117),2) -> 1417.4 | W117: =_xlfn.XLOOKUP(D117,products!$A$2:$A$61,products!$C$2:$C$61,"Not found") -> Fashion
A118: O10117 | B118: 2025-01-12 | C118: C0528 | D118: P006 | E118: 2 | F118: 1454 | G118: 0.2 | H118: Jaipur | I118: Debit Card | J118: 4 | K118: 3 | L118: N | M118: =IF(ISNUMBER(B118),B118,IF(MID(B118,3,1)="-",DATE(VALUE(RIGHT(B118,4)),VALUE(MID(B118,4,2)),VALUE(LEFT(B118,2))),DATE(VALUE(LEFT(B118,4)),VALUE(MID(B118,6,2)),VALUE(RIGHT(B118,2))))) -> 45669 | N118: =MONTH(M118) -> 1 | O118: =PROPER(TRIM(H118)) -> Jaipur | P118: =IFERROR(VLOOKUP(O118,city_map!$A$2:$B$6,2,FALSE()),O118) -> Jaipur | Q118: =IF(ISNUMBER(F118),F118,VALUE(SUBSTITUTE(SUBSTITUTE(F118,"₹",""),",",""))) -> 1454 | R118: =IF(E118=99,1,E118) -> 2 | S118: =IF(G118="",0,G118) -> 0.2 | T118: =IF(I118="","Unknown",IF(I118="upi","UPI",I118)) -> Debit Card | U118: =IF(L118="Yes","Y",IF(L118="No","N",L118)) -> N | V118: =ROUND(R118*Q118*(1-S118),2) -> 2326.4 | W118: =_xlfn.XLOOKUP(D118,products!$A$2:$A$61,products!$C$2:$C$61,"Not found") -> Electronics
A119: O10118 | B119: 2025-01-12 | C119: C0462 | D119: P008 | E119: 1 | F119: 416 | G119: 0.15 | H119: Mumbai | I119: UPI | J119: 3 | K119: 4 | L119: N | M119: =IF(ISNUMBER(B119),B119,IF(MID(B119,3,1)="-",DATE(VALUE(RIGHT(B119,4)),VALUE(MID(B119,4,2)),VALUE(LEFT(B119,2))),DATE(VALUE(LEFT(B119,4)),VALUE(MID(B119,6,2)),VALUE(RIGHT(B119,2))))) -> 45669 | N119: =MONTH(M119) -> 1 | O119: =PROPER(TRIM(H119)) -> Mumbai | P119: =IFERROR(VLOOKUP(O119,city_map!$A$2:$B$6,2,FALSE()),O119) -> Mumbai | Q119: =IF(ISNUMBER(F119),F119,VALUE(SUBSTITUTE(SUBSTITUTE(F119,"₹",""),",",""))) -> 416 | R119: =IF(E119=99,1,E119) -> 1 | S119: =IF(G119="",0,G119) -> 0.15 | T119: =IF(I119="","Unknown",IF(I119="upi","UPI",I119)) -> UPI | U119: =IF(L119="Yes","Y",IF(L119="No","N",L119)) -> N | V119: =ROUND(R119*Q119*(1-S119),2) -> 353.6 | W119: =_xlfn.XLOOKUP(D119,products!$A$2:$A$61,products!$C$2:$C$61,"Not found") -> Electronics
A120: O10119 | B120: 2025-01-12 | C120: C0757 | D120: P014 | E120: 1 | F120: 1502 | G120: 0.05 | H120: Bengaluru | I120: COD | J120: 2 | K120: 5 | L120: N | M120: =IF(ISNUMBER(B120),B120,IF(MID(B120,3,1)="-",DATE(VALUE(RIGHT(B120,4)),VALUE(MID(B120,4,2)),VALUE(LEFT(B120,2))),DATE(VALUE(LEFT(B120,4)),VALUE(MID(B120,6,2)),VALUE(RIGHT(B120,2))))) -> 45669 | N120: =MONTH(M120) -> 1 | O120: =PROPER(TRIM(H120)) -> Bengaluru | P120: =IFERROR(VLOOKUP(O120,city_map!$A$2:$B$6,2,FALSE()),O120) -> Bengaluru | Q120: =IF(ISNUMBER(F120),F120,VALUE(SUBSTITUTE(SUBSTITUTE(F120,"₹",""),",",""))) -> 1502 | R120: =IF(E120=99,1,E120) -> 1 | S120: =IF(G120="",0,G120) -> 0.05 | T120: =IF(I120="","Unknown",IF(I120="upi","UPI",I120)) -> COD | U120: =IF(L120="Yes","Y",IF(L120="No","N",L120)) -> N | V120: =ROUND(R120*Q120*(1-S120),2) -> 1426.9 | W120: =_xlfn.XLOOKUP(D120,products!$A$2:$A$61,products!$C$2:$C$61,"Not found") -> Fashion
A121: O10120 | B121: 2025-01-12 | C121: C0311 | D121: P036 | E121: 1 | F121: 2599 | G121: 0.2 | H121: Pune | I121: COD | J121: 7 | K121: 3 | L121: Y | M121: =IF(ISNUMBER(B121),B121,IF(MID(B121,3,1)="-",DATE(VALUE(RIGHT(B121,4)),VALUE(MID(B121,4,2)),VALUE(LEFT(B121,2))),DATE(VALUE(LEFT(B121,4)),VALUE(MID(B121,6,2)),VALUE(RIGHT(B121,2))))) -> 45669 | N121: =MONTH(M121) -> 1 | O121: =PROPER(TRIM(H121)) -> Pune | P121: =IFERROR(VLOOKUP(O121,city_map!$A$2:$B$6,2,FALSE()),O121) -> Pune | Q121: =IF(ISNUMBER(F121),F121,VALUE(SUBSTITUTE(SUBSTITUTE(F121,"₹",""),",",""))) -> 2599 | R121: =IF(E121=99,1,E121) -> 1 | S121: =IF(G121="",0,G121) -> 0.2 | T121: =IF(I121="","Unknown",IF(I121="upi","UPI",I121)) -> COD | U121: =IF(L121="Yes","Y",IF(L121="No","N",L121)) -> Y | V121: =ROUND(R121*Q121*(1-S121),2) -> 2079.2 | W121: =_xlfn.XLOOKUP(D121,products!$A$2:$A$61,products!$C$2:$C$61,"Not found") -> Home
...

Sheet city_map
A1: city_trim | B1: city_standard
A2: New Delhi | B2: Delhi
A3: Bangalore | B3: Bengaluru
A4: Bombay | B4: Mumbai
A5: Madras | B5: Chennai
A6: Calcutta | B6: Kolkata

Sheet products
A1: product_id | B1: product_name | C1: category | D1: list_price | E1: cost_price
A2: P001 | B2: Wireless Earbuds | C2: Electronics | D2: 1999 | E2: 1600
A3: P002 | B3: Bluetooth Speaker | C3: Electronics | D3: 2499 | E3: 1940
A4: P003 | B4: Smartwatch | C4: Electronics | D4: 3999 | E4: 3230
A5: P004 | B5: Power Bank 10000mAh | C5: Electronics | D5: 1299 | E5: 1030
A6: P005 | B6: USB-C Charger | C6: Electronics | D6: 899 | E6: 670
A7: P006 | B7: Gaming Mouse | C7: Electronics | D7: 1499 | E7: 1220
A8: P007 | B8: Mechanical Keyboard | C8: Electronics | D8: 3499 | E8: 2800
A9: P008 | B9: Phone Case | C9: Electronics | D9: 399 | E9: 320
A10: P009 | B10: Smartphone | C10: Electronics | D10: 14999 | E10: 11260
A11: P010 | B11: Tablet | C11: Electronics | D11: 18999 | E11: 14750
A12: P011 | B12: Laptop Stand | C12: Electronics | D12: 1199 | E12: 920
A13: P012 | B13: Webcam HD | C13: Electronics | D13: 2199 | E13: 1790
... A61: P060 | B61: Nail Polish Set | C61: Beauty | D61: 399 | E61: 190

Sheet customers
A1: customer_id | B1: name | C1: gender | D1: age | E1: city | F1: signup_date | G1: membership
A2: C0001 | B2: Neha Kapoor | C2: Female | D2: 18 | E2: Kolkata | F2: 2023-05-31 | G2: Free
A3: C0002 | B3: Sneha Das | C3: Female | D3: 36 | E3: Delhi | F3: 2023-01-16 | G3: Prime
A4: C0003 | B4: Rohit Kulkarni | C4: Male | D4: 20 | E4: Delhi | F4: 2024-07-23 | G4: Prime
A5: C0004 | B5: Nisha Khan | C5: Female | D5: 26 | E5: Kolkata | F5: 2024-12-26 | G5: Free
A6: C0005 | B6: Priya Khan | C6: Female | D6: 27 | E6: Delhi | F6: 2022-07-02 | G6: Free
A7: C0006 | B7: Siddharth Khan | C7: Male | D7: 30 | E7: Delhi | F7: 2023-06-29 | G7: Free
A8: C0007 | B8: Rohan Iyer | C8: Male | D8: 29 | E8: Bengaluru | F8: 2022-11-27 | G8: Prime
A9: C0008 | B9: Isha Reddy | C9: Female | D9: 33 | E9: Chennai | F9: 2023-05-16 | G9: Free
A10: C0009 | B10: Nisha Das | C10: Female | D10: 22 | E10: Mumbai | F10: 2024-02-24 | G10: Prime
A11: C0010 | B11: Pranav Kapoor | C11: Male | D11: 18 | E11: Mumbai | F11: 2024-06-04 | G11: Prime
A12: C0011 | B12: Ananya Gupta | C12: Female | D12: 25 | E12: Bengaluru | F12: 2024-04-10 | G12: Free
A13: C0012 | B13: Sneha Sharma | C13: Female | D13: 21 | E13: Bengaluru | F13: 2024-05-11 | G13: Free
... A801: C0800 | B801: Nisha Joshi | C801: Female | D801: 24 | E801: Mumbai | F801: 2024-04-18 | G801: Free

Sheet Summary
A1: ShopKart 2025 – summary built with SUMIFS / COUNTIFS / AVERAGEIFS
A3: Total revenue (₹) | B3: =SUM(orders_clean!$V$2:$V$5001) -> 14704650
A4: Total orders | B4: =COUNTA(orders_clean!$A$2:$A$5001) -> 5000
A5: Average order value (₹) | B5: =B3/B4 -> 2940.9299
A6: Returned orders | B6: =COUNTIF(orders_clean!$U$2:$U$5001,"Y") -> 687
A7: Overall return rate | B7: =B6/B4 -> 0.1374
A9: By city
A10: city | B10: revenue (₹) | C10: orders | D10: avg order value (₹) | E10: returns | F10: return rate
A11: Delhi | B11: =SUMIFS(orders_clean!$V$2:$V$5001,orders_clean!$P$2:$P$5001,A11) -> 2323405.4 | C11: =COUNTIFS(orders_clean!$P$2:$P$5001,A11) -> 804 | D11: =AVERAGEIFS(orders_clean!$V$2:$V$5001,orders_clean!$P$2:$P$5001,A11) -> 2889.8077 | E11: =COUNTIFS(orders_clean!$P$2:$P$5001,A11,orders_clean!$U$2:$U$5001,"Y") -> 82 | F11: =E11/C11 -> 0.10199005
A12: Bengaluru | B12: =SUMIFS(orders_clean!$V$2:$V$5001,orders_clean!$P$2:$P$5001,A12) -> 2256613.2 | C12: =COUNTIFS(orders_clean!$P$2:$P$5001,A12) -> 736 | D12: =AVERAGEIFS(orders_clean!$V$2:$V$5001,orders_clean!$P$2:$P$5001,A12) -> 3066.0506 | E12: =COUNTIFS(orders_clean!$P$2:$P$5001,A12,orders_clean!$U$2:$U$5001,"Y") -> 89 | F12: =E12/C12 -> 0.12092391
A13: Mumbai | B13: =SUMIFS(orders_clean!$V$2:$V$5001,orders_clean!$P$2:$P$5001,A13) -> 2090206 | C13: =COUNTIFS(orders_clean!$P$2:$P$5001,A13) -> 759 | D13: =AVERAGEIFS(orders_clean!$V$2:$V$5001,orders_clean!$P$2:$P$5001,A13) -> 2753.8946 | E13: =COUNTIFS(orders_clean!$P$2:$P$5001,A13,orders_clean!$U$2:$U$5001,"Y") -> 69 | F13: =E13/C13 -> 0.090909091
A14: Hyderabad | B14: =SUMIFS(orders_clean!$V$2:$V$5001,orders_clean!$P$2:$P$5001,A14) -> 1494616.8 | C14: =COUNTIFS(orders_clean!$P$2:$P$5001,A14) -> 495 | D14: =AVERAGEIFS(orders_clean!$V$2:$V$5001,orders_clean!$P$2:$P$5001,A14) -> 3019.4278 | E14: =COUNTIFS(orders_clean!$P$2:$P$5001,A14,orders_clean!$U$2:$U$5001,"Y") -> 63 | F14: =E14/C14 -> 0.12727273
A15: Pune | B15: =SUMIFS(orders_clean!$V$2:$V$5001,orders_clean!$P$2:$P$5001,A15) -> 1387698.3 | C15: =COUNTIFS(orders_clean!$P$2:$P$5001,A15) -> 451 | D15: =AVERAGEIFS(orders_clean!$V$2:$V$5001,orders_clean!$P$2:$P$5001,A15) -> 3076.9364 | E15: =COUNTIFS(orders_clean!$P$2:$P$5001,A15,orders_clean!$U$2:$U$5001,"Y") -> 146 | F15: =E15/C15 -> 0.32372506
A16: Chennai | B16: =SUMIFS(orders_clean!$V$2:$V$5001,orders_clean!$P$2:$P$5001,A16) -> 1333558.9 | C16: =COUNTIFS(orders_clean!$P$2:$P$5001,A16) -> 442 | D16: =AVERAGEIFS(orders_clean!$V$2:$V$5001,orders_clean!$P$2:$P$5001,A16) -> 3017.1016 | E16: =COUNTIFS(orders_clean!$P$2:$P$5001,A16,orders_clean!$U$2:$U$5001,"Y") -> 56 | F16: =E16/C16 -> 0.12669683
A17: Kolkata | B17: =SUMIFS(orders_clean!$V$2:$V$5001,orders_clean!$P$2:$P$5001,A17) -> 1237204.2 | C17: =COUNTIFS(orders_clean!$P$2:$P$5001,A17) -> 414 | D17: =AVERAGEIFS(orders_clean!$V$2:$V$5001,orders_clean!$P$2:$P$5001,A17) -> 2988.4159 | E17: =COUNTIFS(orders_clean!$P$2:$P$5001,A17,orders_clean!$U$2:$U$5001,"Y") -> 59 | F17: =E17/C17 -> 0.14251208
A18: Ahmedabad | B18: =SUMIFS(orders_clean!$V$2:$V$5001,orders_clean!$P$2:$P$5001,A18) -> 1065043.1 | C18: =COUNTIFS(orders_clean!$P$2:$P$5001,A18) -> 303 | D18: =AVERAGEIFS(orders_clean!$V$2:$V$5001,orders_clean!$P$2:$P$5001,A18) -> 3514.9936 | E18: =COUNTIFS(orders_clean!$P$2:$P$5001,A18,orders_clean!$U$2:$U$5001,"Y") -> 43 | F18: =E18/C18 -> 0.14191419
A19: Lucknow | B19: =SUMIFS(orders_clean!$V$2:$V$5001,orders_clean!$P$2:$P$5001,A19) -> 791223.65 | C19: =COUNTIFS(orders_clean!$P$2:$P$5001,A19) -> 326 | D19: =AVERAGEIFS(orders_clean!$V$2:$V$5001,orders_clean!$P$2:$P$5001,A19) -> 2427.0664 | E19: =COUNTIFS(orders_clean!$P$2:$P$5001,A19,orders_clean!$U$2:$U$5001,"Y") -> 44 | F19: =E19/C19 -> 0.13496933
A20: Jaipur | B20: =SUMIFS(orders_clean!$V$2:$V$5001,orders_clean!$P$2:$P$5001,A20) -> 725080.2 | C20: =COUNTIFS(orders_clean!$P$2:$P$5001,A20) -> 270 | D20: =AVERAGEIFS(orders_clean!$V$2:$V$5001,orders_clean!$P$2:$P$5001,A20) -> 2685.4822 | E20: =COUNTIFS(orders_clean!$P$2:$P$5001,A20,orders_clean!$U$2:$U$5001,"Y") -> 36 | F20: =E20/C20 -> 0.13333333
A21: Total (check) | B21: =SUM(B11:B20) -> 14704650 | C21: =SUM(C11:C20) -> 5000 | E21: =SUM(E11:E20) -> 687 | F21: =IF(AND(B21=B3,C21=B4),"OK – matches total","CHECK city names") -> OK – matches total
A23: By category
A24: category | B24: revenue (₹) | C24: orders | D24: avg order value (₹) | E24: returns | F24: return rate
A25: Electronics | B25: =SUMIFS(orders_clean!$V$2:$V$5001,orders_clean!$W$2:$W$5001,A25) -> 7331018 | C25: =COUNTIFS(orders_clean!$W$2:$W$5001,A25) -> 1152 | D25: =AVERAGEIFS(orders_clean!$V$2:$V$5001,orders_clean!$W$2:$W$5001,A25) -> 6363.7309 | E25: =COUNTIFS(orders_clean!$W$2:$W$5001,A25,orders_clean!$U$2:$U$5001,"Y") -> 155 | F25: =E25/C25 -> 0.13454861
A26: Fashion | B26: =SUMIFS(orders_clean!$V$2:$V$5001,orders_clean!$W$2:$W$5001,A26) -> 3121345.6 | C26: =COUNTIFS(orders_clean!$W$2:$W$5001,A26) -> 1326 | D26: =AVERAGEIFS(orders_clean!$V$2:$V$5001,orders_clean!$W$2:$W$5001,A26) -> 2353.956 | E26: =COUNTIFS(orders_clean!$W$2:$W$5001,A26,orders_clean!$U$2:$U$5001,"Y") -> 279 | F26: =E26/C26 -> 0.21040724
A27: Home | B27: =SUMIFS(orders_clean!$V$2:$V$5001,orders_clean!$W$2:$W$5001,A27) -> 2655047.3 | C27: =COUNTIFS(orders_clean!$W$2:$W$5001,A27) -> 1020 | D27: =AVERAGEIFS(orders_clean!$V$2:$V$5001,orders_clean!$W$2:$W$5001,A27) -> 2602.9875 | E27: =COUNTIFS(orders_clean!$W$2:$W$5001,A27,orders_clean!$U$2:$U$5001,"Y") -> 127 | F27: =E27/C27 -> 0.1245098
A28: Beauty | B28: =SUMIFS(orders_clean!$V$2:$V$5001,orders_clean!$W$2:$W$5001,A28) -> 877640.35 | C28: =COUNTIFS(orders_clean!$W$2:$W$5001,A28) -> 750 | D28: =AVERAGEIFS(orders_clean!$V$2:$V$5001,orders_clean!$W$2:$W$5001,A28) -> 1170.1871 | E28: =COUNTIFS(orders_clean!$W$2:$W$5001,A28,orders_clean!$U$2:$U$5001,"Y") -> 71 | F28: =E28/C28 -> 0.094666667
A29: Books | B29: =SUMIFS(orders_clean!$V$2:$V$5001,orders_clean!$W$2:$W$5001,A29) -> 719598.4 | C29: =COUNTIFS(orders_clean!$W$2:$W$5001,A29) -> 752 | D29: =AVERAGEIFS(orders_clean!$V$2:$V$5001,orders_clean!$W$2:$W$5001,A29) -> 956.91277 | E29: =COUNTIFS(orders_clean!$W$2:$W$5001,A29,orders_clean!$U$2:$U$5001,"Y") -> 55 | F29: =E29/C29 -> 0.073138298
A31: By month
A32: month_no | B32: month | C32: revenue (₹) | D32: orders
A33: 1 | B33: Jan | C33: =SUMIFS(orders_clean!$V$2:$V$5001,orders_clean!$N$2:$N$5001,A33) -> 1073267.1 | D33: =COUNTIFS(orders_clean!$N$2:$N$5001,A33) -> 320
A34: 2 | B34: Feb | C34: =SUMIFS(orders_clean!$V$2:$V$5001,orders_clean!$N$2:$N$5001,A34) -> 863479.5 | D34: =COUNTIFS(orders_clean!$N$2:$N$5001,A34) -> 289
A35: 3 | B35: Mar | C35: =SUMIFS(orders_clean!$V$2:$V$5001,orders_clean!$N$2:$N$5001,A35) -> 1080121.9 | D35: =COUNTIFS(orders_clean!$N$2:$N$5001,A35) -> 361
A36: 4 | B36: Apr | C36: =SUMIFS(orders_clean!$V$2:$V$5001,orders_clean!$N$2:$N$5001,A36) -> 983480.6 | D36: =COUNTIFS(orders_clean!$N$2:$N$5001,A36) -> 365
A37: 5 | B37: May | C37: =SUMIFS(orders_clean!$V$2:$V$5001,orders_clean!$N$2:$N$5001,A37) -> 786912 | D37: =COUNTIFS(orders_clean!$N$2:$N$5001,A37) -> 333
A38: 6 | B38: Jun | C38: =SUMIFS(orders_clean!$V$2:$V$5001,orders_clean!$N$2:$N$5001,A38) -> 793841.15 | D38: =COUNTIFS(orders_clean!$N$2:$N$5001,A38) -> 300
A39: 7 | B39: Jul | C39: =SUMIFS(orders_clean!$V$2:$V$5001,orders_clean!$N$2:$N$5001,A39) -> 873631.5 | D39: =COUNTIFS(orders_clean!$N$2:$N$5001,A39) -> 371
A40: 8 | B40: Aug | C40: =SUMIFS(orders_clean!$V$2:$V$5001,orders_clean!$N$2:$N$5001,A40) -> 1203393.2 | D40: =COUNTIFS(orders_clean!$N$2:$N$5001,A40) -> 410
A41: 9 | B41: Sep | C41: =SUMIFS(orders_clean!$V$2:$V$5001,orders_clean!$N$2:$N$5001,A41) -> 1543639.4 | D41: =COUNTIFS(orders_clean!$N$2:$N$5001,A41) -> 468
A42: 10 | B42: Oct | C42: =SUMIFS(orders_clean!$V$2:$V$5001,orders_clean!$N$2:$N$5001,A42) -> 1978317 | D42: =COUNTIFS(orders_clean!$N$2:$N$5001,A42) -> 637
A43: 11 | B43: Nov | C43: =SUMIFS(orders_clean!$V$2:$V$5001,orders_clean!$N$2:$N$5001,A43) -> 1965664.4 | D43: =COUNTIFS(orders_clean!$N$2:$N$5001,A43) -> 620
A44: 12 | B44: Dec | C44: =SUMIFS(orders_clean!$V$2:$V$5001,orders_clean!$N$2:$N$5001,A44) -> 1558902.1 | D44: =COUNTIFS(orders_clean!$N$2:$N$5001,A44) -> 526

Sheet Pivot_check
A1: Formula version of the pivot table (Rows: city_clean, Columns: category, Values: SUM of revenue)
A3: city | B3: Electronics | C3: Fashion | D3: Home | E3: Beauty | F3: Books | G3: Grand total
A4: Delhi | B4: =SUMIFS(orders_clean!$V$2:$V$5001,orders_clean!$P$2:$P$5001,$A4,orders_clean!$W$2:$W$5001,B$3) -> 1118941.9 | C4: =SUMIFS(orders_clean!$V$2:$V$5001,orders_clean!$P$2:$P$5001,$A4,orders_clean!$W$2:$W$5001,C$3) -> 526306.2 | D4: =SUMIFS(orders_clean!$V$2:$V$5001,orders_clean!$P$2:$P$5001,$A4,orders_clean!$W$2:$W$5001,D$3) -> 419223.55 | E4: =SUMIFS(orders_clean!$V$2:$V$5001,orders_clean!$P$2:$P$5001,$A4,orders_clean!$W$2:$W$5001,E$3) -> 136721.3 | F4: =SUMIFS(orders_clean!$V$2:$V$5001,orders_clean!$P$2:$P$5001,$A4,orders_clean!$W$2:$W$5001,F$3) -> 122212.4 | G4: =SUM(B4:F4) -> 2323405.4
A5: Bengaluru | B5: =SUMIFS(orders_clean!$V$2:$V$5001,orders_clean!$P$2:$P$5001,$A5,orders_clean!$W$2:$W$5001,B$3) -> 1160942.4 | C5: =SUMIFS(orders_clean!$V$2:$V$5001,orders_clean!$P$2:$P$5001,$A5,orders_clean!$W$2:$W$5001,C$3) -> 516667 | D5: =SUMIFS(orders_clean!$V$2:$V$5001,orders_clean!$P$2:$P$5001,$A5,orders_clean!$W$2:$W$5001,D$3) -> 358141.1 | E5: =SUMIFS(orders_clean!$V$2:$V$5001,orders_clean!$P$2:$P$5001,$A5,orders_clean!$W$2:$W$5001,E$3) -> 127868.7 | F5: =SUMIFS(orders_clean!$V$2:$V$5001,orders_clean!$P$2:$P$5001,$A5,orders_clean!$W$2:$W$5001,F$3) -> 92994 | G5: =SUM(B5:F5) -> 2256613.2
A6: Mumbai | B6: =SUMIFS(orders_clean!$V$2:$V$5001,orders_clean!$P$2:$P$5001,$A6,orders_clean!$W$2:$W$5001,B$3) -> 955525.15 | C6: =SUMIFS(orders_clean!$V$2:$V$5001,orders_clean!$P$2:$P$5001,$A6,orders_clean!$W$2:$W$5001,C$3) -> 463504 | D6: =SUMIFS(orders_clean!$V$2:$V$5001,orders_clean!$P$2:$P$5001,$A6,orders_clean!$W$2:$W$5001,D$3) -> 401668.85 | E6: =SUMIFS(orders_clean!$V$2:$V$5001,orders_clean!$P$2:$P$5001,$A6,orders_clean!$W$2:$W$5001,E$3) -> 141933.9 | F6: =SUMIFS(orders_clean!$V$2:$V$5001,orders_clean!$P$2:$P$5001,$A6,orders_clean!$W$2:$W$5001,F$3) -> 127574.1 | G6: =SUM(B6:F6) -> 2090206
A7: Hyderabad | B7: =SUMIFS(orders_clean!$V$2:$V$5001,orders_clean!$P$2:$P$5001,$A7,orders_clean!$W$2:$W$5001,B$3) -> 757993 | C7: =SUMIFS(orders_clean!$V$2:$V$5001,orders_clean!$P$2:$P$5001,$A7,orders_clean!$W$2:$W$5001,C$3) -> 264688.35 | D7: =SUMIFS(orders_clean!$V$2:$V$5001,orders_clean!$P$2:$P$5001,$A7,orders_clean!$W$2:$W$5001,D$3) -> 292564.2 | E7: =SUMIFS(orders_clean!$V$2:$V$5001,orders_clean!$P$2:$P$5001,$A7,orders_clean!$W$2:$W$5001,E$3) -> 106800.7 | F7: =SUMIFS(orders_clean!$V$2:$V$5001,orders_clean!$P$2:$P$5001,$A7,orders_clean!$W$2:$W$5001,F$3) -> 72570.5 | G7: =SUM(B7:F7) -> 1494616.8
A8: Pune | B8: =SUMIFS(orders_clean!$V$2:$V$5001,orders_clean!$P$2:$P$5001,$A8,orders_clean!$W$2:$W$5001,B$3) -> 705290.6 | C8: =SUMIFS(orders_clean!$V$2:$V$5001,orders_clean!$P$2:$P$5001,$A8,orders_clean!$W$2:$W$5001,C$3) -> 323324.3 | D8: =SUMIFS(orders_clean!$V$2:$V$5001,orders_clean!$P$2:$P$5001,$A8,orders_clean!$W$2:$W$5001,D$3) -> 246468.3 | E8: =SUMIFS(orders_clean!$V$2:$V$5001,orders_clean!$P$2:$P$5001,$A8,orders_clean!$W$2:$W$5001,E$3) -> 52753.8 | F8: =SUMIFS(orders_clean!$V$2:$V$5001,orders_clean!$P$2:$P$5001,$A8,orders_clean!$W$2:$W$5001,F$3) -> 59861.3 | G8: =SUM(B8:F8) -> 1387698.3
A9: Chennai | B9: =SUMIFS(orders_clean!$V$2:$V$5001,orders_clean!$P$2:$P$5001,$A9,orders_clean!$W$2:$W$5001,B$3) -> 753000.1 | C9: =SUMIFS(orders_clean!$V$2:$V$5001,orders_clean!$P$2:$P$5001,$A9,orders_clean!$W$2:$W$5001,C$3) -> 241824.55 | D9: =SUMIFS(orders_clean!$V$2:$V$5001,orders_clean!$P$2:$P$5001,$A9,orders_clean!$W$2:$W$5001,D$3) -> 218498.65 | E9: =SUMIFS(orders_clean!$V$2:$V$5001,orders_clean!$P$2:$P$5001,$A9,orders_clean!$W$2:$W$5001,E$3) -> 55511.95 | F9: =SUMIFS(orders_clean!$V$2:$V$5001,orders_clean!$P$2:$P$5001,$A9,orders_clean!$W$2:$W$5001,F$3) -> 64723.65 | G9: =SUM(B9:F9) -> 1333558.9
A10: Kolkata | B10: =SUMIFS(orders_clean!$V$2:$V$5001,orders_clean!$P$2:$P$5001,$A10,orders_clean!$W$2:$W$5001,B$3) -> 655912.9 | C10: =SUMIFS(orders_clean!$V$2:$V$5001,orders_clean!$P$2:$P$5001,$A10,orders_clean!$W$2:$W$5001,C$3) -> 223887.5 | D10: =SUMIFS(orders_clean!$V$2:$V$5001,orders_clean!$P$2:$P$5001,$A10,orders_clean!$W$2:$W$5001,D$3) -> 220579.2 | E10: =SUMIFS(orders_clean!$V$2:$V$5001,orders_clean!$P$2:$P$5001,$A10,orders_clean!$W$2:$W$5001,E$3) -> 93873.95 | F10: =SUMIFS(orders_clean!$V$2:$V$5001,orders_clean!$P$2:$P$5001,$A10,orders_clean!$W$2:$W$5001,F$3) -> 42950.65 | G10: =SUM(B10:F10) -> 1237204.2
A11: Ahmedabad | B11: =SUMIFS(orders_clean!$V$2:$V$5001,orders_clean!$P$2:$P$5001,$A11,orders_clean!$W$2:$W$5001,B$3) -> 625324.1 | C11: =SUMIFS(orders_clean!$V$2:$V$5001,orders_clean!$P$2:$P$5001,$A11,orders_clean!$W$2:$W$5001,C$3) -> 186263.85 | D11: =SUMIFS(orders_clean!$V$2:$V$5001,orders_clean!$P$2:$P$5001,$A11,orders_clean!$W$2:$W$5001,D$3) -> 160823.5 | E11: =SUMIFS(orders_clean!$V$2:$V$5001,orders_clean!$P$2:$P$5001,$A11,orders_clean!$W$2:$W$5001,E$3) -> 47560.2 | F11: =SUMIFS(orders_clean!$V$2:$V$5001,orders_clean!$P$2:$P$5001,$A11,orders_clean!$W$2:$W$5001,F$3) -> 45071.4 | G11: =SUM(B11:F11) -> 1065043.1
A12: Lucknow | B12: =SUMIFS(orders_clean!$V$2:$V$5001,orders_clean!$P$2:$P$5001,$A12,orders_clean!$W$2:$W$5001,B$3) -> 316133.8 | C12: =SUMIFS(orders_clean!$V$2:$V$5001,orders_clean!$P$2:$P$5001,$A12,orders_clean!$W$2:$W$5001,C$3) -> 206385.7 | D12: =SUMIFS(orders_clean!$V$2:$V$5001,orders_clean!$P$2:$P$5001,$A12,orders_clean!$W$2:$W$5001,D$3) -> 148070 | E12: =SUMIFS(orders_clean!$V$2:$V$5001,orders_clean!$P$2:$P$5001,$A12,orders_clean!$W$2:$W$5001,E$3) -> 62336.45 | F12: =SUMIFS(orders_clean!$V$2:$V$5001,orders_clean!$P$2:$P$5001,$A12,orders_clean!$W$2:$W$5001,F$3) -> 58297.7 | G12: =SUM(B12:F12) -> 791223.65
A13: Jaipur | B13: =SUMIFS(orders_clean!$V$2:$V$5001,orders_clean!$P$2:$P$5001,$A13,orders_clean!$W$2:$W$5001,B$3) -> 281954 | C13: =SUMIFS(orders_clean!$V$2:$V$5001,orders_clean!$P$2:$P$5001,$A13,orders_clean!$W$2:$W$5001,C$3) -> 168494.15 | D13: =SUMIFS(orders_clean!$V$2:$V$5001,orders_clean!$P$2:$P$5001,$A13,orders_clean!$W$2:$W$5001,D$3) -> 189009.95 | E13: =SUMIFS(orders_clean!$V$2:$V$5001,orders_clean!$P$2:$P$5001,$A13,orders_clean!$W$2:$W$5001,E$3) -> 52279.4 | F13: =SUMIFS(orders_clean!$V$2:$V$5001,orders_clean!$P$2:$P$5001,$A13,orders_clean!$W$2:$W$5001,F$3) -> 33342.7 | G13: =SUM(B13:F13) -> 725080.2
A14: Grand total | B14: =SUM(B4:B13) -> 7331018 | C14: =SUM(C4:C13) -> 3121345.6 | D14: =SUM(D4:D13) -> 2655047.3 | E14: =SUM(E4:E13) -> 877640.35 | F14: =SUM(F4:F13) -> 719598.4 | G14: =SUM(G4:G13) -> 14704650
